Workbook

Sheet Executive Summary Dashboard
A1: SUPPLY CHAIN MIS | EXECUTIVE SUMMARY DASHBOARD
A2: Integrated Management Information System • Trailing 12-Month Supply Chain, Inventory, Procurement, Fulfillment & Supplier Analytics.
A4: Total Orders | C4: Total Sales | E4: Total Purchase Value | G4: Total Inventory Value | I4: Total Suppliers
A5: =COUNTA('Order Tracking'!$A$5:$A$604) -> 600 | C5: =SUM('Order Tracking'!$L$5:$L$604) -> 49134145 | E5: =SUM('Purchase Management'!$I$5:$I$224) -> 2.3810373e+08 | G5: =SUM('Inventory Management'!$O$5:$O$104) -> 98642688 | I5: =COUNTA('Supplier Database'!$A$5:$A$29) -> 25
A7: Total Products | C7: Pending Orders | E7: Delayed Orders | G7: Order Fulfillment Rate | I7: On-Time Delivery Rate
A8: =COUNTA('Product Master'!$A$5:$A$104) -> 100 | C8: =COUNTIF('Order Tracking'!$M$5:$M$604,"Pending") -> 78 | E8: =COUNTIF('Order Tracking'!$R$5:$R$604,">0") -> 233 | G8: =IFERROR(COUNTIF('Order Tracking'!$M$5:$M$604,"Delivered")/COUNTA('Order Tracking'!$A$5:$A$604),0) -> 0.58166667 | I8: =IFERROR(COUNTIFS('Order Tracking'!$M$5:$M$604,"Delivered",'Order Tracking'!$R$5:$R$604,0)/COUNTIF('Order Tracking'!$M$5:$M$604,"Delivered"),0) -> 0.59598854
A10: Interactive Dashboard Filters (Select dropdown values in yellow cells to filter live KPIs)
A11: Filter: Start Date | B11: Filter: End Date | C11: Filter: Region | D11: Filter: Product Category | E11: Filter: Order Status | F11: Filter: Supplier ID | G11: Filtered Orders | H11: Filtered Sales (₹) | I11: Filtered Delivered | J11: Filtered Fulfillment % | K11: Filtered Supplier PO Value (₹)
A12: 45931 | B12: 46326 | C12: All | D12: All | E12: All | F12: All | G12: =COUNTIFS('Order Tracking'!$B$5:$B$604,">="&A12,'Order Tracking'!$B$5:$B$604,"<="&B12,'Order Tracking'!$E$5:$E$604,IF(C12="All","*",C12),'Order Tracking'!$I$5:$I$604,IF(D12="All","*",D12),'Order Tracking'!$M$5:$M$604,IF(E12="All","*",E12)) -> 600 | H12: =SUMIFS('Order Tracking'!$L$5:$L$604,'Order Tracking'!$B$5:$B$604,">="&A12,'Order Tracking'!$B$5:$B$604,"<="&B12,'Order Tracking'!$E$5:$E$604,IF(C12="All","*",C12),'Order Tracking'!$I$5:$I$604,IF(D12="All","*",D12),'Order Tracking'!$M$5:$M$604,IF(E12="All","*",E12)) -> 49134145 | I12: =COUNTIFS('Order Tracking'!$B$5:$B$604,">="&A12,'Order Tracking'!$B$5:$B$604,"<="&B12,'Order Tracking'!$E$5:$E$604,IF(C12="All","*",C12),'Order Tracking'!$I$5:$I$604,IF(D12="All","*",D12),'Order Tracking'!$M$5:$M$604,"Delivered") -> 349 | J12: =IFERROR(I12/G12,0) -> 0.58166667 | K12: =SUMIFS('Purchase Management'!$I$5:$I$224,'Purchase Management'!$B$5:$B$224,">="&A12,'Purchase Management'!$B$5:$B$224,"<="&B12,'Purchase Management'!$C$5:$C$224,IF(F12="All","*",F12)) -> 2.3810373e+08
A15: Monthly Sales Trend | E15: Orders by Status | I15: Sales by Product Category
A16: Month | B16: Sales Revenue (₹) | C16: Orders | E16: Status | F16: Orders | G16: Share % | I16: Category | J16: Sales Revenue (₹) | K16: Units Ordered
A17: 45962 | B17: =SUMIFS('Order Tracking'!$L$5:$L$604,'Order Tracking'!$B$5:$B$604,">="&A17,'Order Tracking'!$B$5:$B$604,"<"&EDATE(A17,1)) -> 3891158.8 | C17: =COUNTIFS('Order Tracking'!$B$5:$B$604,">="&A17,'Order Tracking'!$B$5:$B$604,"<"&EDATE(A17,1)) -> 50 | E17: Delivered | F17: =COUNTIF('Order Tracking'!$M$5:$M$604,E17) -> 349 | G17: =IFERROR(F17/$A$5,0) -> 0.58166667 | I17: Electronics | J17: =SUMIFS('Order Tracking'!$L$5:$L$604,'Order Tracking'!$I$5:$I$604,I17) -> 7418459.1 | K17: =SUMIFS('Order Tracking'!$J$5:$J$604,'Order Tracking'!$I$5:$I$604,I17) -> 1026
A18: 45992 | B18: =SUMIFS('Order Tracking'!$L$5:$L$604,'Order Tracking'!$B$5:$B$604,">="&A18,'Order Tracking'!$B$5:$B$604,"<"&EDATE(A18,1)) -> 3173007.4 | C18: =COUNTIFS('Order Tracking'!$B$5:$B$604,">="&A18,'Order Tracking'!$B$5:$B$604,"<"&EDATE(A18,1)) -> 41 | E18: Pending | F18: =COUNTIF('Order Tracking'!$M$5:$M$604,E18) -> 78 | G18: =IFERROR(F18/$A$5,0) -> 0.13 | I18: Home & Kitchen | J18: =SUMIFS('Order Tracking'!$L$5:$L$604,'Order Tracking'!$I$5:$I$604,I18) -> 6359299.4 | K18: =SUMIFS('Order Tracking'!$J$5:$J$604,'Order Tracking'!$I$5:$I$604,I18) -> 995
A19: 46023 | B19: =SUMIFS('Order Tracking'!$L$5:$L$604,'Order Tracking'!$B$5:$B$604,">="&A19,'Order Tracking'!$B$5:$B$604,"<"&EDATE(A19,1)) -> 4091315.9 | C19: =COUNTIFS('Order Tracking'!$B$5:$B$604,">="&A19,'Order Tracking'!$B$5:$B$604,"<"&EDATE(A19,1)) -> 47 | E19: Processing | F19: =COUNTIF('Order Tracking'!$M$5:$M$604,E19) -> 76 | G19: =IFERROR(F19/$A$5,0) -> 0.12666667 | I19: Office Supplies | J19: =SUMIFS('Order Tracking'!$L$5:$L$604,'Order Tracking'!$I$5:$I$604,I19) -> 5066638.8 | K19: =SUMIFS('Order Tracking'!$J$5:$J$604,'Order Tracking'!$I$5:$I$604,I19) -> 1140
A20: 46054 | B20: =SUMIFS('Order Tracking'!$L$5:$L$604,'Order Tracking'!$B$5:$B$604,">="&A20,'Order Tracking'!$B$5:$B$604,"<"&EDATE(A20,1)) -> 2977863.2 | C20: =COUNTIFS('Order Tracking'!$B$5:$B$604,">="&A20,'Order Tracking'!$B$5:$B$604,"<"&EDATE(A20,1)) -> 38 | E20: Dispatched | F20: =COUNTIF('Order Tracking'!$M$5:$M$604,E20) -> 56 | G20: =IFERROR(F20/$A$5,0) -> 0.093333333 | I20: Personal Care | J20: =SUMIFS('Order Tracking'!$L$5:$L$604,'Order Tracking'!$I$5:$I$604,I20) -> 5583999.6 | K20: =SUMIFS('Order Tracking'!$J$5:$J$604,'Order Tracking'!$I$5:$I$604,I20) -> 886
A21: 46082 | B21: =SUMIFS('Order Tracking'!$L$5:$L$604,'Order Tracking'!$B$5:$B$604,">="&A21,'Order Tracking'!$B$5:$B$604,"<"&EDATE(A21,1)) -> 4855581 | C21: =COUNTIFS('Order Tracking'!$B$5:$B$604,">="&A21,'Order Tracking'!$B$5:$B$604,"<"&EDATE(A21,1)) -> 63 | E21: Cancelled | F21: =COUNTIF('Order Tracking'!$M$5:$M$604,E21) -> 41 | G21: =IFERROR(F21/$A$5,0) -> 0.068333333 | I21: Industrial | J21: =SUMIFS('Order Tracking'!$L$5:$L$604,'Order Tracking'!$I$5:$I$604,I21) -> 7605893.4 | K21: =SUMIFS('Order Tracking'!$J$5:$J$604,'Order Tracking'!$I$5:$I$604,I21) -> 1139
A22: 46113 | B22: =SUMIFS('Order Tracking'!$L$5:$L$604,'Order Tracking'!$B$5:$B$604,">="&A22,'Order Tracking'!$B$5:$B$604,"<"&EDATE(A22,1)) -> 3579994 | C22: =COUNTIFS('Order Tracking'!$B$5:$B$604,">="&A22,'Order Tracking'!$B$5:$B$604,"<"&EDATE(A22,1)) -> 43 | I22: Packaging | J22: =SUMIFS('Order Tracking'!$L$5:$L$604,'Order Tracking'!$I$5:$I$604,I22) -> 6074915.3 | K22: =SUMIFS('Order Tracking'!$J$5:$J$604,'Order Tracking'!$I$5:$I$604,I22) -> 992
A23: 46143 | B23: =SUMIFS('Order Tracking'!$L$5:$L$604,'Order Tracking'!$B$5:$B$604,">="&A23,'Order Tracking'!$B$5:$B$604,"<"&EDATE(A23,1)) -> 4170402.8 | C23: =COUNTIFS('Order Tracking'!$B$5:$B$604,">="&A23,'Order Tracking'!$B$5:$B$604,"<"&EDATE(A23,1)) -> 53 | I23: Apparel | J23: =SUMIFS('Order Tracking'!$L$5:$L$604,'Order Tracking'!$I$5:$I$604,I23) -> 6042303.9 | K23: =SUMIFS('Order Tracking'!$J$5:$J$604,'Order Tracking'!$I$5:$I$604,I23) -> 919
A24: 46174 | B24: =SUMIFS('Order Tracking'!$L$5:$L$604,'Order Tracking'!$B$5:$B$604,">="&A24,'Order Tracking'!$B$5:$B$604,"<"&EDATE(A24,1)) -> 3324809 | C24: =COUNTIFS('Order Tracking'!$B$5:$B$604,">="&A24,'Order Tracking'!$B$5:$B$604,"<"&EDATE(A24,1)) -> 39 | I24: Automotive | J24: =SUMIFS('Order Tracking'!$L$5:$L$604,'Order Tracking'!$I$5:$I$604,I24) -> 4982635.5 | K24: =SUMIFS('Order Tracking'!$J$5:$J$604,'Order Tracking'!$I$5:$I$604,I24) -> 937
A25: 46204 | B25: =SUMIFS('Order Tracking'!$L$5:$L$604,'Order Tracking'!$B$5:$B$604,">="&A25,'Order Tracking'!$B$5:$B$604,"<"&EDATE(A25,1)) -> 4635139.5 | C25: =COUNTIFS('Order Tracking'!$B$5:$B$604,">="&A25,'Order Tracking'!$B$5:$B$604,"<"&EDATE(A25,1)) -> 48
A26: 46235 | B26: =SUMIFS('Order Tracking'!$L$5:$L$604,'Order Tracking'!$B$5:$B$604,">="&A26,'Order Tracking'!$B$5:$B$604,"<"&EDATE(A26,1)) -> 4350130.2 | C26: =COUNTIFS('Order Tracking'!$B$5:$B$604,">="&A26,'Order Tracking'!$B$5:$B$604,"<"&EDATE(A26,1)) -> 56
A27: 46266 | B27: =SUMIFS('Order Tracking'!$L$5:$L$604,'Order Tracking'!$B$5:$B$604,">="&A27,'Order Tracking'!$B$5:$B$604,"<"&EDATE(A27,1)) -> 3937105 | C27: =COUNTIFS('Order Tracking'!$B$5:$B$604,">="&A27,'Order Tracking'!$B$5:$B$604,"<"&EDATE(A27,1)) -> 54
A28: 46296 | B28: =SUMIFS('Order Tracking'!$L$5:$L$604,'Order Tracking'!$B$5:$B$604,">="&A28,'Order Tracking'!$B$5:$B$604,"<"&EDATE(A28,1)) -> 1868048 | C28: =COUNTIFS('Order Tracking'!$B$5:$B$604,">="&A28,'Order Tracking'!$B$5:$B$604,"<"&EDATE(A28,1)) -> 17
A31: Inventory Value by Category | E31: Supplier Performance Comparison (Top 10) | I31: Monthly Order Fulfillment Trend
A32: Category | B32: Inventory Value (₹) | C32: Units in Stock | E32: Supplier Name | F32: Performance Score | G32: On-Time % | I32: Month | J32: Delivered Orders | K32: Fulfillment Rate
A33: Electronics | B33: =SUMIFS('Inventory Management'!$O$5:$O$104,'Inventory Management'!$C$5:$C$104,A33) -> 1860258.2 | C33: =SUMIFS('Inventory Management'!$K$5:$K$104,'Inventory Management'!$C$5:$C$104,A33) -> 794 | E33: ='Supplier Performance Dashboard'!B12 -> Apex Supplies | F33: ='Supplier Performance Dashboard'!K12 -> 85.9 | G33: ='Supplier Performance Dashboard'!J12 -> 0.75 | I33: 45962 | J33: =COUNTIFS('Order Tracking'!$B$5:$B$604,">="&I33,'Order Tracking'!$B$5:$B$604,"<"&EDATE(I33,1),'Order Tracking'!$M$5:$M$604,"Delivered") -> 23 | K33: =IFERROR(J33/COUNTIFS('Order Tracking'!$B$5:$B$604,">="&I33,'Order Tracking'!$B$5:$B$604,"<"&EDATE(I33,1)),0) -> 0.46
A34: Home & Kitchen | B34: =SUMIFS('Inventory Management'!$O$5:$O$104,'Inventory Management'!$C$5:$C$104,A34) -> 7122143 | C34: =SUMIFS('Inventory Management'!$K$5:$K$104,'Inventory Management'!$C$5:$C$104,A34) -> 1310 | E34: ='Supplier Performance Dashboard'!B13 -> Bright Distributors | F34: ='Supplier Performance Dashboard'!K13 -> 69.8 | G34: ='Supplier Performance Dashboard'!J13 -> 0.5 | I34: 45992 | J34: =COUNTIFS('Order Tracking'!$B$5:$B$604,">="&I34,'Order Tracking'!$B$5:$B$604,"<"&EDATE(I34,1),'Order Tracking'!$M$5:$M$604,"Delivered") -> 20 | K34: =IFERROR(J34/COUNTIFS('Order Tracking'!$B$5:$B$604,">="&I34,'Order Tracking'!$B$5:$B$604,"<"&EDATE(I34,1)),0) -> 0.48780488
A35: Office Supplies | B35: =SUMIFS('Inventory Management'!$O$5:$O$104,'Inventory Management'!$C$5:$C$104,A35) -> 13365786 | C35: =SUMIFS('Inventory Management'!$K$5:$K$104,'Inventory Management'!$C$5:$C$104,A35) -> 4891 | E35: ='Supplier Performance Dashboard'!B14 -> Core Industries | F35: ='Supplier Performance Dashboard'!K14 -> 45.5 | G35: ='Supplier Performance Dashboard'!J14 -> 0 | I35: 46023 | J35: =COUNTIFS('Order Tracking'!$B$5:$B$604,">="&I35,'Order Tracking'!$B$5:$B$604,"<"&EDATE(I35,1),'Order Tracking'!$M$5:$M$604,"Delivered") -> 33 | K35: =IFERROR(J35/COUNTIFS('Order Tracking'!$B$5:$B$604,">="&I35,'Order Tracking'!$B$5:$B$604,"<"&EDATE(I35,1)),0) -> 0.70212766
A36: Personal Care | B36: =SUMIFS('Inventory Management'!$O$5:$O$104,'Inventory Management'!$C$5:$C$104,A36) -> 13705603 | C36: =SUMIFS('Inventory Management'!$K$5:$K$104,'Inventory Management'!$C$5:$C$104,A36) -> 3350 | E36: ='Supplier Performance Dashboard'!B15 -> Delta Trading Co. | F36: ='Supplier Performance Dashboard'!K15 -> 70.2 | G36: ='Supplier Performance Dashboard'!J15 -> 0.5 | I36: 46054 | J36: =COUNTIFS('Order Tracking'!$B$5:$B$604,">="&I36,'Order Tracking'!$B$5:$B$604,"<"&EDATE(I36,1),'Order Tracking'!$M$5:$M$604,"Delivered") -> 26 | K36: =IFERROR(J36/COUNTIFS('Order Tracking'!$B$5:$B$604,">="&I36,'Order Tracking'!$B$5:$B$604,"<"&EDATE(I36,1)),0) -> 0.68421053
A37: Industrial | B37: =SUMIFS('Inventory Management'!$O$5:$O$104,'Inventory Management'!$C$5:$C$104,A37) -> 19204320 | C37: =SUMIFS('Inventory Management'!$K$5:$K$104,'Inventory Management'!$C$5:$C$104,A37) -> 3387 | E37: ='Supplier Performance Dashboard'!B16 -> Ever Logistics | F37: ='Supplier Performance Dashboard'!K16 -> 87.6 | G37: ='Supplier Performance Dashboard'!J16 -> 0.77777778 | I37: 46082 | J37: =COUNTIFS('Order Tracking'!$B$5:$B$604,">="&I37,'Order Tracking'!$B$5:$B$604,"<"&EDATE(I37,1),'Order Tracking'!$M$5:$M$604,"Delivered") -> 44 | K37: =IFERROR(J37/COUNTIFS('Order Tracking'!$B$5:$B$604,">="&I37,'Order Tracking'!$B$5:$B$604,"<"&EDATE(I37,1)),0) -> 0.6984127
A38: Packaging | B38: =SUMIFS('Inventory Management'!$O$5:$O$104,'Inventory Management'!$C$5:$C$104,A38) -> 15464877 | C38: =SUMIFS('Inventory Management'!$K$5:$K$104,'Inventory Management'!$C$5:$C$104,A38) -> 3682 | E38: ='Supplier Performance Dashboard'!B17 -> Frontier Wholesale | F38: ='Supplier Performance Dashboard'!K17 -> 64.1 | G38: ='Supplier Performance Dashboard'!J17 -> 0.28571429 | I38: 46113 | J38: =COUNTIFS('Order Tracking'!$B$5:$B$604,">="&I38,'Order Tracking'!$B$5:$B$604,"<"&EDATE(I38,1),'Order Tracking'!$M$5:$M$604,"Delivered") -> 24 | K38: =IFERROR(J38/COUNTIFS('Order Tracking'!$B$5:$B$604,">="&I38,'Order Tracking'!$B$5:$B$604,"<"&EDATE(I38,1)),0) -> 0.55813953
A39: Apparel | B39: =SUMIFS('Inventory Management'!$O$5:$O$104,'Inventory Management'!$C$5:$C$104,A39) -> 8559432.6 | C39: =SUMIFS('Inventory Management'!$K$5:$K$104,'Inventory Management'!$C$5:$C$104,A39) -> 2622 | E39: ='Supplier Performance Dashboard'!B18 -> Global Partners | F39: ='Supplier Performance Dashboard'!K18 -> 78.7 | G39: ='Supplier Performance Dashboard'!J18 -> 0.57142857 | I39: 46143 | J39: =COUNTIFS('Order Tracking'!$B$5:$B$604,">="&I39,'Order Tracking'!$B$5:$B$604,"<"&EDATE(I39,1),'Order Tracking'!$M$5:$M$604,"Delivered") -> 30 | K39: =IFERROR(J39/COUNTIFS('Order Tracking'!$B$5:$B$604,">="&I39,'Order Tracking'!$B$5:$B$604,"<"&EDATE(I39,1)),0) -> 0.56603774
A40: Automotive | B40: =SUMIFS('Inventory Management'!$O$5:$O$104,'Inventory Management'!$C$5:$C$104,A40) -> 19360269 | C40: =SUMIFS('Inventory Management'!$K$5:$K$104,'Inventory Management'!$C$5:$C$104,A40) -> 4389 | E40: ='Supplier Performance Dashboard'!B19 -> Horizon Supplies | F40: ='Supplier Performance Dashboard'!K19 -> 86.3 | G40: ='Supplier Performance Dashboard'!J19 -> 0.77777778 | I40: 46174 | J40: =COUNTIFS('Order Tracking'!$B$5:$B$604,">="&I40,'Order Tracking'!$B$5:$B$604,"<"&EDATE(I40,1),'Order Tracking'!$M$5:$M$604,"Delivered") -> 20 | K40: =IFERROR(J40/COUNTIFS('Order Tracking'!$B$5:$B$604,">="&I40,'Order Tracking'!$B$5:$B$604,"<"&EDATE(I40,1)),0) -> 0.51282051
E41: ='Supplier Performance Dashboard'!B20 -> Indus Distributors | F41: ='Supplier Performance Dashboard'!K20 -> 88.1 | G41: ='Supplier Performance Dashboard'!J20 -> 0.75 | I41: 46204 | J41: =COUNTIFS('Order Tracking'!$B$5:$B$604,">="&I41,'Order Tracking'!$B$5:$B$604,"<"&EDATE(I41,1),'Order Tracking'!$M$5:$M$604,"Delivered") -> 28 | K41: =IFERROR(J41/COUNTIFS('Order Tracking'!$B$5:$B$604,">="&I41,'Order Tracking'!$B$5:$B$604,"<"&EDATE(I41,1)),0) -> 0.58333333
E42: ='Supplier Performance Dashboard'!B21 -> Jupiter Industries | F42: ='Supplier Performance Dashboard'!K21 -> 87.6 | G42: ='Supplier Performance Dashboard'!J21 -> 0.77777778 | I42: 46235 | J42: =COUNTIFS('Order Tracking'!$B$5:$B$604,">="&I42,'Order Tracking'!$B$5:$B$604,"<"&EDATE(I42,1),'Order Tracking'!$M$5:$M$604,"Delivered") -> 35 | K42: =IFERROR(J42/COUNTIFS('Order Tracking'!$B$5:$B$604,">="&I42,'Order Tracking'!$B$5:$B$604,"<"&EDATE(I42,1)),0) -> 0.625
I43: 46266 | J43: =COUNTIFS('Order Tracking'!$B$5:$B$604,">="&I43,'Order Tracking'!$B$5:$B$604,"<"&EDATE(I43,1),'Order Tracking'!$M$5:$M$604,"Delivered") -> 26 | K43: =IFERROR(J43/COUNTIFS('Order Tracking'!$B$5:$B$604,">="&I43,'Order Tracking'!$B$5:$B$604,"<"&EDATE(I43,1)),0) -> 0.48148148
I44: 46296 | J44: =COUNTIFS('Order Tracking'!$B$5:$B$604,">="&I44,'Order Tracking'!$B$5:$B$604,"<"&EDATE(I44,1),'Order Tracking'!$M$5:$M$604,"Delivered") -> 8 | K44: =IFERROR(J44/COUNTIFS('Order Tracking'!$B$5:$B$604,">="&I44,'Order Tracking'!$B$5:$B$604,"<"&EDATE(I44,1)),0) -> 0.47058824
A47: Key Business Insights & Management Recommendations
A48: 1. Order Fulfillment & Delay Bottlenecks: 57.8% of total orders (347/600) are Delivered with a 59.4% On-Time Delivery Rate; Warehouse Backlog and Carrier Delay drive the largest share of delayed orders.
A49: 2. Inventory Replenishment Priorities: 20 SKUs are currently below Minimum Stock Level (11 Out-of-Stock, 9 Low-Stock); prioritize immediate POs using the Reorder Quantity column in Inventory Management.
A50: 3. High-Value Category Concentration: Industrial, Electronics, and Home & Kitchen generate the largest share of gross revenue, while 62% of catalog SKUs maintain healthy stock buffers.
A51: 4. Supplier Consolidation Opportunity: Top-performing vendors (Indus Distributors, Northstar Partners, Yugma Industries) achieve >85 composite scores; reallocate volume away from lower-scoring vendors.
A52: 5. Interactive Analysis: Use the yellow filter controls in Row 12 above (or table AutoFilters on Sheets 6-10) to slice order volume, sales revenue, and fulfillment rates by Date Window, Region, Category, Status, and Supplier.

Sheet Inventory Dashboard
A1: INVENTORY & STOCK AVAILABILITY DASHBOARD
A2: Monitors warehouse stock levels, inventory valuation (₹), stock movement trends, and low-stock replenishment priorities.
A4: Total SKUs | C4: Total Units in Stock | E4: Total Inventory Value | G4: Stock Availability Rate
A5: =COUNTA('Inventory Management'!$A$5:$A$104) -> 100 | C5: =SUM('Inventory Management'!$K$5:$K$104) -> 24425 | E5: =SUM('Inventory Management'!$O$5:$O$104) -> 98642688 | G5: =IFERROR(COUNTIF('Inventory Management'!$K$5:$K$104,">0")/COUNTA('Inventory Management'!$A$5:$A$104),0) -> 0.89
A7: Low-Stock Items | C7: Out-of-Stock Items | E7: Overstocked Items | G7: Healthy Stock Items
A8: =COUNTIF('Inventory Management'!$P$5:$P$104,"Low Stock") -> 9 | C8: =COUNTIF('Inventory Management'!$P$5:$P$104,"Out of Stock") -> 11 | E8: =COUNTIF('Inventory Management'!$P$5:$P$104,"Overstocked") -> 17 | G8: =COUNTIF('Inventory Management'!$P$5:$P$104,"Healthy Stock") -> 63
A10: Inventory by Category | E10: Inventory Value by Warehouse
A11: Category | B11: Units in Stock | C11: Inventory Value (₹) | E11: Warehouse | F11: Units in Stock | G11: Inventory Value (₹)
A12: Electronics | B12: =SUMIFS('Inventory Management'!$K$5:$K$104,'Inventory Management'!$C$5:$C$104,A12) -> 794 | C12: =SUMIFS('Inventory Management'!$O$5:$O$104,'Inventory Management'!$C$5:$C$104,A12) -> 1860258.2 | E12: Delhi WH | F12: =SUMIFS('Inventory Management'!$K$5:$K$104,'Inventory Management'!$F$5:$F$104,E12) -> 5601 | G12: =SUMIFS('Inventory Management'!$O$5:$O$104,'Inventory Management'!$F$5:$F$104,E12) -> 20277839
A13: Home & Kitchen | B13: =SUMIFS('Inventory Management'!$K$5:$K$104,'Inventory Management'!$C$5:$C$104,A13) -> 1310 | C13: =SUMIFS('Inventory Management'!$O$5:$O$104,'Inventory Management'!$C$5:$C$104,A13) -> 7122143 | E13: Bengaluru WH | F13: =SUMIFS('Inventory Management'!$K$5:$K$104,'Inventory Management'!$F$5:$F$104,E13) -> 4093 | G13: =SUMIFS('Inventory Management'!$O$5:$O$104,'Inventory Management'!$F$5:$F$104,E13) -> 18027088
A14: Office Supplies | B14: =SUMIFS('Inventory Management'!$K$5:$K$104,'Inventory Management'!$C$5:$C$104,A14) -> 4891 | C14: =SUMIFS('Inventory Management'!$O$5:$O$104,'Inventory Management'!$C$5:$C$104,A14) -> 13365786 | E14: Kolkata WH | F14: =SUMIFS('Inventory Management'!$K$5:$K$104,'Inventory Management'!$F$5:$F$104,E14) -> 3758 | G14: =SUMIFS('Inventory Management'!$O$5:$O$104,'Inventory Management'!$F$5:$F$104,E14) -> 21265259
A15: Personal Care | B15: =SUMIFS('Inventory Management'!$K$5:$K$104,'Inventory Management'!$C$5:$C$104,A15) -> 3350 | C15: =SUMIFS('Inventory Management'!$O$5:$O$104,'Inventory Management'!$C$5:$C$104,A15) -> 13705603 | E15: Mumbai WH | F15: =SUMIFS('Inventory Management'!$K$5:$K$104,'Inventory Management'!$F$5:$F$104,E15) -> 6712 | G15: =SUMIFS('Inventory Management'!$O$5:$O$104,'Inventory Management'!$F$5:$F$104,E15) -> 25971115
A16: Industrial | B16: =SUMIFS('Inventory Management'!$K$5:$K$104,'Inventory Management'!$C$5:$C$104,A16) -> 3387 | C16: =SUMIFS('Inventory Management'!$O$5:$O$104,'Inventory Management'!$C$5:$C$104,A16) -> 19204320 | E16: Raipur WH | F16: =SUMIFS('Inventory Management'!$K$5:$K$104,'Inventory Management'!$F$5:$F$104,E16) -> 4261 | G16: =SUMIFS('Inventory Management'!$O$5:$O$104,'Inventory Management'!$F$5:$F$104,E16) -> 13101387
A17: Packaging | B17: =SUMIFS('Inventory Management'!$K$5:$K$104,'Inventory Management'!$C$5:$C$104,A17) -> 3682 | C17: =SUMIFS('Inventory Management'!$O$5:$O$104,'Inventory Management'!$C$5:$C$104,A17) -> 15464877
A18: Apparel | B18: =SUMIFS('Inventory Management'!$K$5:$K$104,'Inventory Management'!$C$5:$C$104,A18) -> 2622 | C18: =SUMIFS('Inventory Management'!$O$5:$O$104,'Inventory Management'!$C$5:$C$104,A18) -> 8559432.6
A19: Automotive | B19: =SUMIFS('Inventory Management'!$K$5:$K$104,'Inventory Management'!$C$5:$C$104,A19) -> 4389 | C19: =SUMIFS('Inventory Management'!$O$5:$O$104,'Inventory Management'!$C$5:$C$104,A19) -> 19360269
A22: Stock Movement Trends (Monthly Units Received vs. Units Sold)
A23: Month | B23: Stock Received (POs) | C23: Units Sold (Orders) | D23: Net Stock Change
A24: 45962 | B24: =SUMIFS('Purchase Management'!$L$5:$L$224,'Purchase Management'!$B$5:$B$224,">="&A24,'Purchase Management'!$B$5:$B$224,"<"&EDATE(A24,1)) -> 2472 | C24: =SUMIFS('Order Tracking'!$J$5:$J$604,'Order Tracking'!$B$5:$B$604,">="&A24,'Order Tracking'!$B$5:$B$604,"<"&EDATE(A24,1),'Order Tracking'!$M$5:$M$604,"<>Cancelled") -> 680 | D24: =B24-C24 -> 1792
A25: 45992 | B25: =SUMIFS('Purchase Management'!$L$5:$L$224,'Purchase Management'!$B$5:$B$224,">="&A25,'Purchase Management'!$B$5:$B$224,"<"&EDATE(A25,1)) -> 2670 | C25: =SUMIFS('Order Tracking'!$J$5:$J$604,'Order Tracking'!$B$5:$B$604,">="&A25,'Order Tracking'!$B$5:$B$604,"<"&EDATE(A25,1),'Order Tracking'!$M$5:$M$604,"<>Cancelled") -> 499 | D25: =B25-C25 -> 2171
A26: 46023 | B26: =SUMIFS('Purchase Management'!$L$5:$L$224,'Purchase Management'!$B$5:$B$224,">="&A26,'Purchase Management'!$B$5:$B$224,"<"&EDATE(A26,1)) -> 2377 | C26: =SUMIFS('Order Tracking'!$J$5:$J$604,'Order Tracking'!$B$5:$B$604,">="&A26,'Order Tracking'!$B$5:$B$604,"<"&EDATE(A26,1),'Order Tracking'!$M$5:$M$604,"<>Cancelled") -> 581 | D26: =B26-C26 -> 1796
A27: 46054 | B27: =SUMIFS('Purchase Management'!$L$5:$L$224,'Purchase Management'!$B$5:$B$224,">="&A27,'Purchase Management'!$B$5:$B$224,"<"&EDATE(A27,1)) -> 1316 | C27: =SUMIFS('Order Tracking'!$J$5:$J$604,'Order Tracking'!$B$5:$B$604,">="&A27,'Order Tracking'!$B$5:$B$604,"<"&EDATE(A27,1),'Order Tracking'!$M$5:$M$604,"<>Cancelled") -> 511 | D27: =B27-C27 -> 805
A28: 46082 | B28: =SUMIFS('Purchase Management'!$L$5:$L$224,'Purchase Management'!$B$5:$B$224,">="&A28,'Purchase Management'!$B$5:$B$224,"<"&EDATE(A28,1)) -> 3722 | C28: =SUMIFS('Order Tracking'!$J$5:$J$604,'Order Tracking'!$B$5:$B$604,">="&A28,'Order Tracking'!$B$5:$B$604,"<"&EDATE(A28,1),'Order Tracking'!$M$5:$M$604,"<>Cancelled") -> 781 | D28: =B28-C28 -> 2941
A29: 46113 | B29: =SUMIFS('Purchase Management'!$L$5:$L$224,'Purchase Management'!$B$5:$B$224,">="&A29,'Purchase Management'!$B$5:$B$224,"<"&EDATE(A29,1)) -> 2100 | C29: =SUMIFS('Order Tracking'!$J$5:$J$604,'Order Tracking'!$B$5:$B$604,">="&A29,'Order Tracking'!$B$5:$B$604,"<"&EDATE(A29,1),'Order Tracking'!$M$5:$M$604,"<>Cancelled") -> 516 | D29: =B29-C29 -> 1584
A30: 46143 | B30: =SUMIFS('Purchase Management'!$L$5:$L$224,'Purchase Management'!$B$5:$B$224,">="&A30,'Purchase Management'!$B$5:$B$224,"<"&EDATE(A30,1)) -> 5569 | C30: =SUMIFS('Order Tracking'!$J$5:$J$604,'Order Tracking'!$B$5:$B$604,">="&A30,'Order Tracking'!$B$5:$B$604,"<"&EDATE(A30,1),'Order Tracking'!$M$5:$M$604,"<>Cancelled") -> 691 | D30: =B30-C30 -> 4878
A31: 46174 | B31: =SUMIFS('Purchase Management'!$L$5:$L$224,'Purchase Management'!$B$5:$B$224,">="&A31,'Purchase Management'!$B$5:$B$224,"<"&EDATE(A31,1)) -> 2339 | C31: =SUMIFS('Order Tracking'!$J$5:$J$604,'Order Tracking'!$B$5:$B$604,">="&A31,'Order Tracking'!$B$5:$B$604,"<"&EDATE(A31,1),'Order Tracking'!$M$5:$M$604,"<>Cancelled") -> 472 | D31: =B31-C31 -> 1867
A32: 46204 | B32: =SUMIFS('Purchase Management'!$L$5:$L$224,'Purchase Management'!$B$5:$B$224,">="&A32,'Purchase Management'!$B$5:$B$224,"<"&EDATE(A32,1)) -> 3525 | C32: =SUMIFS('Order Tracking'!$J$5:$J$604,'Order Tracking'!$B$5:$B$604,">="&A32,'Order Tracking'!$B$5:$B$604,"<"&EDATE(A32,1),'Order Tracking'!$M$5:$M$604,"<>Cancelled") -> 634 | D32: =B32-C32 -> 2891
A33: 46235 | B33: =SUMIFS('Purchase Management'!$L$5:$L$224,'Purchase Management'!$B$5:$B$224,">="&A33,'Purchase Management'!$B$5:$B$224,"<"&EDATE(A33,1)) -> 3017 | C33: =SUMIFS('Order Tracking'!$J$5:$J$604,'Order Tracking'!$B$5:$B$604,">="&A33,'Order Tracking'!$B$5:$B$604,"<"&EDATE(A33,1),'Order Tracking'!$M$5:$M$604,"<>Cancelled") -> 666 | D33: =B33-C33 -> 2351
A34: 46266 | B34: =SUMIFS('Purchase Management'!$L$5:$L$224,'Purchase Management'!$B$5:$B$224,">="&A34,'Purchase Management'!$B$5:$B$224,"<"&EDATE(A34,1)) -> 3388 | C34: =SUMIFS('Order Tracking'!$J$5:$J$604,'Order Tracking'!$B$5:$B$604,">="&A34,'Order Tracking'!$B$5:$B$604,"<"&EDATE(A34,1),'Order Tracking'!$M$5:$M$604,"<>Cancelled") -> 564 | D34: =B34-C34 -> 2824
A35: 46296 | B35: =SUMIFS('Purchase Management'!$L$5:$L$224,'Purchase Management'!$B$5:$B$224,">="&A35,'Purchase Management'!$B$5:$B$224,"<"&EDATE(A35,1)) -> 2751 | C35: =SUMIFS('Order Tracking'!$J$5:$J$604,'Order Tracking'!$B$5:$B$604,">="&A35,'Order Tracking'!$B$5:$B$604,"<"&EDATE(A35,1),'Order Tracking'!$M$5:$M$604,"<>Cancelled") -> 235 | D35: =B35-C35 -> 2516
A38: Low-Stock & Out-of-Stock Product Replenishment Analysis
A39: Product ID | B39: Product Name | C39: Category | D39: Warehouse | E39: Closing Stock | F39: Minimum Stock | G39: Stock Status | H39: Reorder Qty
A40: ='Inventory Management'!A5 -> PRD001 | B40: ='Inventory Management'!B5 -> Everyday Electronics Item 001 | C40: ='Inventory Management'!C5 -> Electronics | D40: ='Inventory Management'!F5 -> Mumbai WH | E40: ='Inventory Management'!K5 -> 0 | F40: ='Inventory Management'!L5 -> 55 | G40: ='Inventory Management'!P5 -> Out of Stock | H40: ='Inventory Management'!Q5 -> 275
A41: ='Inventory Management'!A6 -> PRD002 | B41: ='Inventory Management'!B6 -> Premium Home Item 002 | C41: ='Inventory Management'!C6 -> Home & Kitchen | D41: ='Inventory Management'!F6 -> Raipur WH | E41: ='Inventory Management'!K6 -> 9 | F41: ='Inventory Management'!L6 -> 42 | G41: ='Inventory Management'!P6 -> Low Stock | H41: ='Inventory Management'!Q6 -> 285
A42: ='Inventory Management'!A9 -> PRD005 | B42: ='Inventory Management'!B9 -> Everyday Industrial Item 005 | C42: ='Inventory Management'!C9 -> Industrial | D42: ='Inventory Management'!F9 -> Delhi WH | E42: ='Inventory Management'!K9 -> 0 | F42: ='Inventory Management'!L9 -> 28 | G42: ='Inventory Management'!P9 -> Out of Stock | H42: ='Inventory Management'!Q9 -> 112
A43: ='Inventory Management'!A13 -> PRD009 | B43: ='Inventory Management'!B13 -> Essential Electronics Item 009 | C43: ='Inventory Management'!C13 -> Electronics | D43: ='Inventory Management'!F13 -> Delhi WH | E43: ='Inventory Management'!K13 -> 0 | F43: ='Inventory Management'!L13 -> 24 | G43: ='Inventory Management'!P13 -> Out of Stock | H43: ='Inventory Management'!Q13 -> 96
A44: ='Inventory Management'!A14 -> PRD010 | B44: ='Inventory Management'!B14 -> Essential Home Item 010 | C44: ='Inventory Management'!C14 -> Home & Kitchen | D44: ='Inventory Management'!F14 -> Delhi WH | E44: ='Inventory Management'!K14 -> 22 | F44: ='Inventory Management'!L14 -> 33 | G44: ='Inventory Management'!P14 -> Low Stock | H44: ='Inventory Management'!Q14 -> 275
A45: ='Inventory Management'!A21 -> PRD017 | B45: ='Inventory Management'!B21 -> Premium Electronics Item 017 | C45: ='Inventory Management'!C21 -> Electronics | D45: ='Inventory Management'!F21 -> Kolkata WH | E45: ='Inventory Management'!K21 -> 0 | F45: ='Inventory Management'!L21 -> 59 | G45: ='Inventory Management'!P21 -> Out of Stock | H45: ='Inventory Management'!Q21 -> 472
A46: ='Inventory Management'!A29 -> PRD025 | B46: ='Inventory Management'!B29 -> Pro Electronics Item 025 | C46: ='Inventory Management'!C29 -> Electronics | D46: ='Inventory Management'!F29 -> Kolkata WH | E46: ='Inventory Management'!K29 -> 0 | F46: ='Inventory Management'!L29 -> 56 | G46: ='Inventory Management'!P29 -> Out of Stock | H46: ='Inventory Management'!Q29 -> 224
A47: ='Inventory Management'!A30 -> PRD026 | B47: ='Inventory Management'!B30 -> Classic Home Item 026 | C47: ='Inventory Management'!C30 -> Home & Kitchen | D47: ='Inventory Management'!F30 -> Kolkata WH | E47: ='Inventory Management'!K30 -> 20 | F47: ='Inventory Management'!L30 -> 25 | G47: ='Inventory Management'!P30 -> Low Stock | H47: ='Inventory Management'!Q30 -> 80
A48: ='Inventory Management'!A37 -> PRD033 | B48: ='Inventory Management'!B37 -> Compact Electronics Item 033 | C48: ='Inventory Management'!C37 -> Electronics | D48: ='Inventory Management'!F37 -> Kolkata WH | E48: ='Inventory Management'!K37 -> 0 | F48: ='Inventory Management'!L37 -> 72 | G48: ='Inventory Management'!P37 -> Out of Stock | H48: ='Inventory Management'!Q37 -> 288
A49: ='Inventory Management'!A38 -> PRD034 | B49: ='Inventory Management'!B38 -> Classic Home Item 034 | C49: ='Inventory Management'!C38 -> Home & Kitchen | D49: ='Inventory Management'!F38 -> Kolkata WH | E49: ='Inventory Management'!K38 -> 24 | F49: ='Inventory Management'!L38 -> 50 | G49: ='Inventory Management'!P38 -> Low Stock | H49: ='Inventory Management'!Q38 -> 426
A50: ='Inventory Management'!A45 -> PRD041 | B50: ='Inventory Management'!B45 -> Essential Electronics Item 041 | C50: ='Inventory Management'!C45 -> Electronics | D50: ='Inventory Management'!F45 -> Kolkata WH | E50: ='Inventory Management'!K45 -> 0 | F50: ='Inventory Management'!L45 -> 18 | G50: ='Inventory Management'!P45 -> Out of Stock | H50: ='Inventory Management'!Q45 -> 72
A51: ='Inventory Management'!A46 -> PRD042 | B51: ='Inventory Management'!B46 -> Compact Home Item 042 | C51: ='Inventory Management'!C46 -> Home & Kitchen | D51: ='Inventory Management'!F46 -> Kolkata WH | E51: ='Inventory Management'!K46 -> 25 | F51: ='Inventory Management'!L46 -> 48 | G51: ='Inventory Management'!P46 -> Low Stock | H51: ='Inventory Management'!Q46 -> 215
A52: ='Inventory Management'!A53 -> PRD049 | B52: ='Inventory Management'!B53 -> Premium Electronics Item 049 | C52: ='Inventory Management'!C53 -> Electronics | D52: ='Inventory Management'!F53 -> Raipur WH | E52: ='Inventory Management'!K53 -> 0 | F52: ='Inventory Management'!L53 -> 30 | G52: ='Inventory Management'!P53 -> Out of Stock | H52: ='Inventory Management'!Q53 -> 240
A53: ='Inventory Management'!A54 -> PRD050 | B53: ='Inventory Management'!B54 -> Eco Home Item 050 | C53: ='Inventory Management'!C54 -> Home & Kitchen | D53: ='Inventory Management'!F54 -> Delhi WH | E53: ='Inventory Management'!K54 -> 13 | F53: ='Inventory Management'!L54 -> 23 | G53: ='Inventory Management'!P54 -> Low Stock | H53: ='Inventory Management'!Q54 -> 102
A54: ='Inventory Management'!A61 -> PRD057 | B54: ='Inventory Management'!B61 -> Essential Electronics Item 057 | C54: ='Inventory Management'!C61 -> Electronics | D54: ='Inventory Management'!F61 -> Kolkata WH | E54: ='Inventory Management'!K61 -> 0 | F54: ='Inventory Management'!L61 -> 25 | G54: ='Inventory Management'!P61 -> Out of Stock | H54: ='Inventory Management'!Q61 -> 100
A55: ='Inventory Management'!A62 -> PRD058 | B55: ='Inventory Management'!B62 -> Pro Home Item 058 | C55: ='Inventory Management'!C62 -> Home & Kitchen | D55: ='Inventory Management'!F62 -> Mumbai WH | E55: ='Inventory Management'!K62 -> 38 | F55: ='Inventory Management'!L62 -> 77 | G55: ='Inventory Management'!P62 -> Low Stock | H55: ='Inventory Management'!Q62 -> 347
A56: ='Inventory Management'!A69 -> PRD065 | B56: ='Inventory Management'!B69 -> Compact Electronics Item 065 | C56: ='Inventory Management'!C69 -> Electronics | D56: ='Inventory Management'!F69 -> Delhi WH | E56: ='Inventory Management'!K69 -> 0 | F56: ='Inventory Management'!L69 -> 28 | G56: ='Inventory Management'!P69 -> Out of Stock | H56: ='Inventory Management'!Q69 -> 252
A57: ='Inventory Management'!A70 -> PRD066 | B57: ='Inventory Management'!B70 -> Classic Home Item 066 | C57: ='Inventory Management'!C70 -> Home & Kitchen | D57: ='Inventory Management'!F70 -> Mumbai WH | E57: ='Inventory Management'!K70 -> 5 | F57: ='Inventory Management'!L70 -> 38 | G57: ='Inventory Management'!P70 -> Low Stock | H57: ='Inventory Management'!Q70 -> 299
A58: ='Inventory Management'!A77 -> PRD073 | B58: ='Inventory Management'!B77 -> Essential Electronics Item 073 | C58: ='Inventory Management'!C77 -> Electronics | D58: ='Inventory Management'!F77 -> Mumbai WH | E58: ='Inventory Management'!K77 -> 0 | F58: ='Inventory Management'!L77 -> 51 | G58: ='Inventory Management'!P77 -> Out of Stock | H58: ='Inventory Management'!Q77 -> 306
A59: ='Inventory Management'!A78 -> PRD074 | B59: ='Inventory Management'!B78 -> Pro Home Item 074 | C59: ='Inventory Management'!C78 -> Home & Kitchen | D59: ='Inventory Management'!F78 -> Mumbai WH | E59: ='Inventory Management'!K78 -> 22 | F59: ='Inventory Management'!L78 -> 40 | G59: ='Inventory Management'!P78 -> Low Stock | H59: ='Inventory Management'!Q78 -> 338

Sheet Order Management Dashboard
A1: ORDER MANAGEMENT & FULFILLMENT DASHBOARD
A2: Tracks order processing, regional fulfillment, delivery turnaround time (TAT), delay root causes, and urgent order exceptions.
A4: Total Orders | C4: Completed Orders | E4: Pending Orders | G4: Processing Orders | I4: Cancelled Orders
A5: =COUNTA('Order Tracking'!$A$5:$A$604) -> 600 | C5: =COUNTIF('Order Tracking'!$M$5:$M$604,"Delivered") -> 349 | E5: =COUNTIF('Order Tracking'!$M$5:$M$604,"Pending") -> 78 | G5: =COUNTIF('Order Tracking'!$M$5:$M$604,"Processing") -> 76 | I5: =COUNTIF('Order Tracking'!$M$5:$M$604,"Cancelled") -> 41
A7: Delayed Orders | C7: Average Order Value | E7: Average Delivery TAT | G7: Order Fulfillment Rate | I7: On-Time Delivery Rate
A8: =COUNTIF('Order Tracking'!$R$5:$R$604,">0") -> 233 | C8: =IFERROR(AVERAGE('Order Tracking'!$L$5:$L$604),0) -> 81890.242 | E8: =IFERROR(AVERAGEIFS('Order Tracking'!$Q$5:$Q$604,'Order Tracking'!$M$5:$M$604,"Delivered"),0) -> 6.756447 | G8: =IFERROR(COUNTIF('Order Tracking'!$M$5:$M$604,"Delivered")/COUNTA('Order Tracking'!$A$5:$A$604),0) -> 0.58166667 | I8: =IFERROR(COUNTIFS('Order Tracking'!$M$5:$M$604,"Delivered",'Order Tracking'!$R$5:$R$604,0)/COUNTIF('Order Tracking'!$M$5:$M$604,"Delivered"),0) -> 0.59598854
A10: Orders by Status | E10: Orders by Region | I10: Delayed Orders by Reason
A11: Order Status | B11: Orders | C11: Share % | E11: Region | F11: Orders | G11: Sales Value (₹) | I11: Delay Reason | J11: Orders | K11: Share %
A12: Delivered | B12: =COUNTIF('Order Tracking'!$M$5:$M$604,A12) -> 349 | C12: =IFERROR(B12/$A$5,0) -> 0.58166667 | E12: North | F12: =COUNTIF('Order Tracking'!$E$5:$E$604,E12) -> 113 | G12: =SUMIFS('Order Tracking'!$L$5:$L$604,'Order Tracking'!$E$5:$E$604,E12) -> 9382569.8 | I12: Warehouse backlog | J12: =COUNTIFS('Order Tracking'!$T$5:$T$604,I12,'Order Tracking'!$R$5:$R$604,">0") -> 64 | K12: =IFERROR(J12/$A$8,0) -> 0.27467811
A13: Pending | B13: =COUNTIF('Order Tracking'!$M$5:$M$604,A13) -> 78 | C13: =IFERROR(B13/$A$5,0) -> 0.13 | E13: South | F13: =COUNTIF('Order Tracking'!$E$5:$E$604,E13) -> 109 | G13: =SUMIFS('Order Tracking'!$L$5:$L$604,'Order Tracking'!$E$5:$E$604,E13) -> 7999582.5 | I13: Awaiting stock | J13: =COUNTIFS('Order Tracking'!$T$5:$T$604,I13,'Order Tracking'!$R$5:$R$604,">0") -> 28 | K13: =IFERROR(J13/$A$8,0) -> 0.12017167
A14: Processing | B14: =COUNTIF('Order Tracking'!$M$5:$M$604,A14) -> 76 | C14: =IFERROR(B14/$A$5,0) -> 0.12666667 | E14: East | F14: =COUNTIF('Order Tracking'!$E$5:$E$604,E14) -> 119 | G14: =SUMIFS('Order Tracking'!$L$5:$L$604,'Order Tracking'!$E$5:$E$604,E14) -> 10093289 | I14: Address issue | J14: =COUNTIFS('Order Tracking'!$T$5:$T$604,I14,'Order Tracking'!$R$5:$R$604,">0") -> 30 | K14: =IFERROR(J14/$A$8,0) -> 0.12875536
A15: Dispatched | B15: =COUNTIF('Order Tracking'!$M$5:$M$604,A15) -> 56 | C15: =IFERROR(B15/$A$5,0) -> 0.093333333 | E15: West | F15: =COUNTIF('Order Tracking'!$E$5:$E$604,E15) -> 140 | G15: =SUMIFS('Order Tracking'!$L$5:$L$604,'Order Tracking'!$E$5:$E$604,E15) -> 12258217 | I15: Supplier delay | J15: =COUNTIFS('Order Tracking'!$T$5:$T$604,I15,'Order Tracking'!$R$5:$R$604,">0") -> 26 | K15: =IFERROR(J15/$A$8,0) -> 0.11158798
A16: Cancelled | B16: =COUNTIF('Order Tracking'!$M$5:$M$604,A16) -> 41 | C16: =IFERROR(B16/$A$5,0) -> 0.068333333 | E16: Central | F16: =COUNTIF('Order Tracking'!$E$5:$E$604,E16) -> 119 | G16: =SUMIFS('Order Tracking'!$L$5:$L$604,'Order Tracking'!$E$5:$E$604,E16) -> 9400486.9 | I16: Weather disruption | J16: =COUNTIFS('Order Tracking'!$T$5:$T$604,I16,'Order Tracking'!$R$5:$R$604,">0") -> 29 | K16: =IFERROR(J16/$A$8,0) -> 0.12446352
I17: Carrier delay | J17: =COUNTIFS('Order Tracking'!$T$5:$T$604,I17,'Order Tracking'!$R$5:$R$604,">0") -> 45 | K17: =IFERROR(J17/$A$8,0) -> 0.19313305
I18: Payment hold | J18: =COUNTIFS('Order Tracking'!$T$5:$T$604,I18,'Order Tracking'!$R$5:$R$604,">0") -> 11 | K18: =IFERROR(J18/$A$8,0) -> 0.0472103
A21: Monthly Order Volume | E21: Delivery Performance Breakdown
A22: Month | B22: Order Volume | C22: Delivered Orders | E22: Delivery Outcome | F22: Orders | G22: Share %
A23: 45962 | B23: =COUNTIFS('Order Tracking'!$B$5:$B$604,">="&A23,'Order Tracking'!$B$5:$B$604,"<"&EDATE(A23,1)) -> 50 | C23: =COUNTIFS('Order Tracking'!$B$5:$B$604,">="&A23,'Order Tracking'!$B$5:$B$604,"<"&EDATE(A23,1),'Order Tracking'!$M$5:$M$604,"Delivered") -> 23 | E23: On-Time Delivered | F23: =COUNTIFS('Order Tracking'!$M$5:$M$604,"Delivered",'Order Tracking'!$R$5:$R$604,0) -> 208 | G23: =IFERROR(F23/$A$5,0) -> 0.34666667
A24: 45992 | B24: =COUNTIFS('Order Tracking'!$B$5:$B$604,">="&A24,'Order Tracking'!$B$5:$B$604,"<"&EDATE(A24,1)) -> 41 | C24: =COUNTIFS('Order Tracking'!$B$5:$B$604,">="&A24,'Order Tracking'!$B$5:$B$604,"<"&EDATE(A24,1),'Order Tracking'!$M$5:$M$604,"Delivered") -> 20 | E24: Late Delivered | F24: =COUNTIFS('Order Tracking'!$M$5:$M$604,"Delivered",'Order Tracking'!$R$5:$R$604,">0") -> 141 | G24: =IFERROR(F24/$A$5,0) -> 0.235
A25: 46023 | B25: =COUNTIFS('Order Tracking'!$B$5:$B$604,">="&A25,'Order Tracking'!$B$5:$B$604,"<"&EDATE(A25,1)) -> 47 | C25: =COUNTIFS('Order Tracking'!$B$5:$B$604,">="&A25,'Order Tracking'!$B$5:$B$604,"<"&EDATE(A25,1),'Order Tracking'!$M$5:$M$604,"Delivered") -> 33 | E25: In-Transit (Dispatched) | F25: =COUNTIF('Order Tracking'!$M$5:$M$604,"Dispatched") -> 56 | G25: =IFERROR(F25/$A$5,0) -> 0.093333333
A26: 46054 | B26: =COUNTIFS('Order Tracking'!$B$5:$B$604,">="&A26,'Order Tracking'!$B$5:$B$604,"<"&EDATE(A26,1)) -> 38 | C26: =COUNTIFS('Order Tracking'!$B$5:$B$604,">="&A26,'Order Tracking'!$B$5:$B$604,"<"&EDATE(A26,1),'Order Tracking'!$M$5:$M$604,"Delivered") -> 26 | E26: Open Queue (Pending/Processing) | F26: =COUNTIF('Order Tracking'!$M$5:$M$604,"Pending")+COUNTIF('Order Tracking'!$M$5:$M$604,"Processing") -> 154 | G26: =IFERROR(F26/$A$5,0) -> 0.25666667
A27: 46082 | B27: =COUNTIFS('Order Tracking'!$B$5:$B$604,">="&A27,'Order Tracking'!$B$5:$B$604,"<"&EDATE(A27,1)) -> 63 | C27: =COUNTIFS('Order Tracking'!$B$5:$B$604,">="&A27,'Order Tracking'!$B$5:$B$604,"<"&EDATE(A27,1),'Order Tracking'!$M$5:$M$604,"Delivered") -> 44 | E27: Cancelled Orders | F27: =COUNTIF('Order Tracking'!$M$5:$M$604,"Cancelled") -> 41 | G27: =IFERROR(F27/$A$5,0) -> 0.068333333
A28: 46113 | B28: =COUNTIFS('Order Tracking'!$B$5:$B$604,">="&A28,'Order Tracking'!$B$5:$B$604,"<"&EDATE(A28,1)) -> 43 | C28: =COUNTIFS('Order Tracking'!$B$5:$B$604,">="&A28,'Order Tracking'!$B$5:$B$604,"<"&EDATE(A28,1),'Order Tracking'!$M$5:$M$604,"Delivered") -> 24
A29: 46143 | B29: =COUNTIFS('Order Tracking'!$B$5:$B$604,">="&A29,'Order Tracking'!$B$5:$B$604,"<"&EDATE(A29,1)) -> 53 | C29: =COUNTIFS('Order Tracking'!$B$5:$B$604,">="&A29,'Order Tracking'!$B$5:$B$604,"<"&EDATE(A29,1),'Order Tracking'!$M$5:$M$604,"Delivered") -> 30
A30: 46174 | B30: =COUNTIFS('Order Tracking'!$B$5:$B$604,">="&A30,'Order Tracking'!$B$5:$B$604,"<"&EDATE(A30,1)) -> 39 | C30: =COUNTIFS('Order Tracking'!$B$5:$B$604,">="&A30,'Order Tracking'!$B$5:$B$604,"<"&EDATE(A30,1),'Order Tracking'!$M$5:$M$604,"Delivered") -> 20
A31: 46204 | B31: =COUNTIFS('Order Tracking'!$B$5:$B$604,">="&A31,'Order Tracking'!$B$5:$B$604,"<"&EDATE(A31,1)) -> 48 | C31: =COUNTIFS('Order Tracking'!$B$5:$B$604,">="&A31,'Order Tracking'!$B$5:$B$604,"<"&EDATE(A31,1),'Order Tracking'!$M$5:$M$604,"Delivered") -> 28
A32: 46235 | B32: =COUNTIFS('Order Tracking'!$B$5:$B$604,">="&A32,'Order Tracking'!$B$5:$B$604,"<"&EDATE(A32,1)) -> 56 | C32: =COUNTIFS('Order Tracking'!$B$5:$B$604,">="&A32,'Order Tracking'!$B$5:$B$604,"<"&EDATE(A32,1),'Order Tracking'!$M$5:$M$604,"Delivered") -> 35
A33: 46266 | B33: =COUNTIFS('Order Tracking'!$B$5:$B$604,">="&A33,'Order Tracking'!$B$5:$B$604,"<"&EDATE(A33,1)) -> 54 | C33: =COUNTIFS('Order Tracking'!$B$5:$B$604,">="&A33,'Order Tracking'!$B$5:$B$604,"<"&EDATE(A33,1),'Order Tracking'!$M$5:$M$604,"Delivered") -> 26
A34: 46296 | B34: =COUNTIFS('Order Tracking'!$B$5:$B$604,">="&A34,'Order Tracking'!$B$5:$B$604,"<"&EDATE(A34,1)) -> 17 | C34: =COUNTIFS('Order Tracking'!$B$5:$B$604,">="&A34,'Order Tracking'!$B$5:$B$604,"<"&EDATE(A34,1),'Order Tracking'!$M$5:$M$604,"Delivered") -> 8
A37: Orders Requiring Immediate Management Attention (Top 20 Overdue Open Orders)
A38: Order ID | B38: Order Date | C38: Customer Name | D38: Region | E38: Product Name | F38: Order Value (₹) | G38: Order Status | H38: Expected Delivery | I38: Delay Reason
A39: ='Order Tracking'!A6 -> ORD0002 | B39: ='Order Tracking'!B6 -> 46161 | C39: ='Order Tracking'!D6 -> Diya Mishra | D39: ='Order Tracking'!E6 -> North | E39: ='Order Tracking'!H6 -> Eco Automotive Item 048 | F39: ='Order Tracking'!L6 -> 10672.08 | G39: ='Order Tracking'!M6 -> Dispatched | H39: ='Order Tracking'!O6 -> 46167 | I39: ='Order Tracking'!T6 -> Carrier delay
A40: ='Order Tracking'!A12 -> ORD0008 | B40: ='Order Tracking'!B12 -> 46017 | C40: ='Order Tracking'!D12 -> Ishaan Mishra | D40: ='Order Tracking'!E12 -> Central | E40: ='Order Tracking'!H12 -> Smart Home Item 018 | F40: ='Order Tracking'!L12 -> 34161.66 | G40: ='Order Tracking'!M12 -> Dispatched | H40: ='Order Tracking'!O12 -> 46019 | I40: ='Order Tracking'!T12 -> Carrier delay
A41: ='Order Tracking'!A15 -> ORD0011 | B41: ='Order Tracking'!B15 -> 45939 | C41: ='Order Tracking'!D15 -> Arjun Mishra | D41: ='Order Tracking'!E15 -> West | E41: ='Order Tracking'!H15 -> Compact Electronics Item 065 | F41: ='Order Tracking'!L15 -> 28691.08 | G41: ='Order Tracking'!M15 -> Dispatched | H41: ='Order Tracking'!O15 -> 45943 | I41: ='Order Tracking'!T15 -> Carrier delay
A42: ='Order Tracking'!A18 -> ORD0014 | B42: ='Order Tracking'!B18 -> 45979 | C42: ='Order Tracking'!D18 -> Ishaan Khan | D42: ='Order Tracking'!E18 -> North | E42: ='Order Tracking'!H18 -> Compact Personal Item 068 | F42: ='Order Tracking'!L18 -> 52123.4 | G42: ='Order Tracking'!M18 -> Dispatched | H42: ='Order Tracking'!O18 -> 45988 | I42: ='Order Tracking'!T18 -> Carrier delay
A43: ='Order Tracking'!A20 -> ORD0016 | B43: ='Order Tracking'!B20 -> 46130 | C43: ='Order Tracking'!D20 -> Ira Sharma | D43: ='Order Tracking'!E20 -> Central | E43: ='Order Tracking'!H20 -> Compact Apparel Item 087 | F43: ='Order Tracking'!L20 -> 109200.26 | G43: ='Order Tracking'!M20 -> Processing | H43: ='Order Tracking'!O20 -> 46134 | I43: ='Order Tracking'!T20 -> Warehouse backlog
A44: ='Order Tracking'!A28 -> ORD0024 | B44: ='Order Tracking'!B28 -> 46125 | C44: ='Order Tracking'!D28 -> Vivaan Das | D44: ='Order Tracking'!E28 -> West | E44: ='Order Tracking'!H28 -> Eco Office Item 043 | F44: ='Order Tracking'!L28 -> 35356.72 | G44: ='Order Tracking'!M28 -> Processing | H44: ='Order Tracking'!O28 -> 46129 | I44: ='Order Tracking'!T28 -> Awaiting stock
A45: ='Order Tracking'!A30 -> ORD0026 | B45: ='Order Tracking'!B30 -> 46219 | C45: ='Order Tracking'!D30 -> Vivaan Das | D45: ='Order Tracking'!E30 -> Central | E45: ='Order Tracking'!H30 -> Classic Home Item 026 | F45: ='Order Tracking'!L30 -> 29388.42 | G45: ='Order Tracking'!M30 -> Pending | H45: ='Order Tracking'!O30 -> 46221 | I45: ='Order Tracking'!T30 -> Warehouse backlog
A46: ='Order Tracking'!A32 -> ORD0028 | B46: ='Order Tracking'!B32 -> 46124 | C46: ='Order Tracking'!D32 -> Ira Iyer | D46: ='Order Tracking'!E32 -> West | E46: ='Order Tracking'!H32 -> Essential Home Item 010 | F46: ='Order Tracking'!L32 -> 118220 | G46: ='Order Tracking'!M32 -> Pending | H46: ='Order Tracking'!O32 -> 46132 | I46: ='Order Tracking'!T32 -> Warehouse backlog
A47: ='Order Tracking'!A36 -> ORD0032 | B47: ='Order Tracking'!B36 -> 46178 | C47: ='Order Tracking'!D36 -> Aditi Sharma | D47: ='Order Tracking'!E36 -> West | E47: ='Order Tracking'!H36 -> Essential Industrial Item 045 | F47: ='Order Tracking'!L36 -> 148633.95 | G47: ='Order Tracking'!M36 -> Processing | H47: ='Order Tracking'!O36 -> 46187 | I47: ='Order Tracking'!T36 -> Awaiting stock
A48: ='Order Tracking'!A38 -> ORD0034 | B48: ='Order Tracking'!B38 -> 46167 | C48: ='Order Tracking'!D38 -> Vivaan Das | D48: ='Order Tracking'!E38 -> West | E48: ='Order Tracking'!H38 -> Premium Packaging Item 030 | F48: ='Order Tracking'!L38 -> 39861.66 | G48: ='Order Tracking'!M38 -> Pending | H48: ='Order Tracking'!O38 -> 46175 | I48: ='Order Tracking'!T38 -> Payment hold
A49: ='Order Tracking'!A54 -> ORD0050 | B49: ='Order Tracking'!B54 -> 46150 | C49: ='Order Tracking'!D54 -> Ira Gupta | D49: ='Order Tracking'!E54 -> South | E49: ='Order Tracking'!H54 -> Classic Home Item 026 | F49: ='Order Tracking'!L54 -> 29388.42 | G49: ='Order Tracking'!M54 -> Dispatched | H49: ='Order Tracking'!O54 -> 46156 | I49: ='Order Tracking'!T54 -> Carrier delay
A50: ='Order Tracking'!A60 -> ORD0056 | B50: ='Order Tracking'!B60 -> 46072 | C50: ='Order Tracking'!D60 -> Aditi Nair | D50: ='Order Tracking'!E60 -> North | E50: ='Order Tracking'!H60 -> Essential Office Item 083 | F50: ='Order Tracking'!L60 -> 74122.02 | G50: ='Order Tracking'!M60 -> Pending | H50: ='Order Tracking'!O60 -> 46078 | I50: ='Order Tracking'!T60 -> Warehouse backlog
A51: ='Order Tracking'!A66 -> ORD0062 | B51: ='Order Tracking'!B66 -> 46244 | C51: ='Order Tracking'!D66 -> Kabir Iyer | D51: ='Order Tracking'!E66 -> North | E51: ='Order Tracking'!H66 -> Smart Packaging Item 078 | F51: ='Order Tracking'!L66 -> 13814.9 | G51: ='Order Tracking'!M66 -> Processing | H51: ='Order Tracking'!O66 -> 46248 | I51: ='Order Tracking'!T66 -> Warehouse backlog
A52: ='Order Tracking'!A74 -> ORD0070 | B52: ='Order Tracking'!B74 -> 46108 | C52: ='Order Tracking'!D74 -> Vivaan Mehta | D52: ='Order Tracking'!E74 -> North | E52: ='Order Tracking'!H74 -> Compact Home Item 082 | F52: ='Order Tracking'!L74 -> 3454.52 | G52: ='Order Tracking'!M74 -> Processing | H52: ='Order Tracking'!O74 -> 46116 | I52: ='Order Tracking'!T74 -> Awaiting stock
A53: ='Order Tracking'!A76 -> ORD0072 | B53: ='Order Tracking'!B76 -> 45974 | C53: ='Order Tracking'!D76 -> Diya Singh | D53: ='Order Tracking'!E76 -> North | E53: ='Order Tracking'!H76 -> Everyday Office Item 075 | F53: ='Order Tracking'!L76 -> 34760.15 | G53: ='Order Tracking'!M76 -> Pending | H53: ='Order Tracking'!O76 -> 45982 | I53: ='Order Tracking'!T76 -> Awaiting stock
A54: ='Order Tracking'!A78 -> ORD0074 | B54: ='Order Tracking'!B78 -> 46050 | C54: ='Order Tracking'!D78 -> Meera Das | D54: ='Order Tracking'!E78 -> South | E54: ='Order Tracking'!H78 -> Essential Home Item 010 | F54: ='Order Tracking'!L78 -> 184718.75 | G54: ='Order Tracking'!M78 -> Processing | H54: ='Order Tracking'!O78 -> 46053 | I54: ='Order Tracking'!T78 -> Warehouse backlog
A55: ='Order Tracking'!A90 -> ORD0086 | B55: ='Order Tracking'!B90 -> 46204 | C55: ='Order Tracking'!D90 -> Meera Verma | D55: ='Order Tracking'!E90 -> North | E55: ='Order Tracking'!H90 -> Eco Apparel Item 095 | F55: ='Order Tracking'!L90 -> 54811.39 | G55: ='Order Tracking'!M90 -> Dispatched | H55: ='Order Tracking'!O90 -> 46212 | I55: ='Order Tracking'!T90 -> Carrier delay
A56: ='Order Tracking'!A96 -> ORD0092 | B56: ='Order Tracking'!B96 -> 45996 | C56: ='Order Tracking'!D96 -> Reyansh Sahu | D56: ='Order Tracking'!E96 -> North | E56: ='Order Tracking'!H96 -> Eco Apparel Item 023 | F56: ='Order Tracking'!L96 -> 45429.67 | G56: ='Order Tracking'!M96 -> Dispatched | H56: ='Order Tracking'!O96 -> 45998 | I56: ='Order Tracking'!T96 -> Carrier delay
A57: ='Order Tracking'!A108 -> ORD0104 | B57: ='Order Tracking'!B108 -> 46133 | C57: ='Order Tracking'!D108 -> Dev Verma | D57: ='Order Tracking'!E108 -> North | E57: ='Order Tracking'!H108 -> Essential Personal Item 092 | F57: ='Order Tracking'!L108 -> 166721.96 | G57: ='Order Tracking'!M108 -> Dispatched | H57: ='Order Tracking'!O108 -> 46137 | I57: ='Order Tracking'!T108 -> Carrier delay
A58: ='Order Tracking'!A112 -> ORD0108 | B58: ='Order Tracking'!B112 -> 46205 | C58: ='Order Tracking'!D112 -> Arjun Singh | D58: ='Order Tracking'!E112 -> West | E58: ='Order Tracking'!H112 -> Essential Industrial Item 045 | F58: ='Order Tracking'!L112 -> 128816.09 | G58: ='Order Tracking'!M112 -> Pending | H58: ='Order Tracking'!O112 -> 46214 | I58: ='Order Tracking'!T112 -> Awaiting stock

Sheet Supplier Performance Dashboard
A1: SUPPLIER PERFORMANCE & RELIABILITY DASHBOARD
A2: Evaluates 25 suppliers on purchase volume, delivery lead time, on-time delivery %, quality rate, composite score, and performance tier.
A4: Total Suppliers | C4: Active Suppliers | E4: Total Purchase Value | G4: Avg Supplier Delivery Time
A5: =COUNTA('Supplier Database'!$A$5:$A$29) -> 25 | C5: =COUNTIF('Supplier Database'!$K$5:$K$29,"Active") -> 24 | E5: =SUM('Purchase Management'!$I$5:$I$224) -> 2.3810373e+08 | G5: =IFERROR(AVERAGE(G12:G36),0) -> 9.3339632
A7: On-Time Delivery % | C7: Defective Items % | E7: Average Supplier Rating
A8: =IFERROR(SUM(E12:E36)/(SUM(E12:E36)+SUM(F12:F36)),0) -> 0.50793651 | C8: =IFERROR(SUM(H12:H36)/SUM('Purchase Management'!$G$5:$G$224),0) -> 0.018246767 | E8: =AVERAGE('Supplier Database'!$J$5:$J$29) -> 4.016
A10: Supplier Performance Scorecard (All 25 Suppliers)
A11: Supplier ID | B11: Supplier Name | C11: Total Purchase Orders | D11: Total Purchase Value | E11: On-Time Deliveries | F11: Late Deliveries | G11: Average Delivery Time | H11: Defective Units | I11: Quality Rate | J11: On-Time % | K11: Supplier Performance Score | L11: Performance Category
A12: SUP001 | B12: =VLOOKUP(A12,'Supplier Database'!$A$5:$K$29,2,FALSE()) -> Apex Supplies | C12: =COUNTIF('Purchase Management'!$C$5:$C$224,A12) -> 4 | D12: =SUMIF('Purchase Management'!$C$5:$C$224,A12,'Purchase Management'!$I$5:$I$224) -> 2246214.5 | E12: =COUNTIFS('Purchase Management'!$C$5:$C$224,A12,'Purchase Management'!$N$5:$N$224,"Received",'Purchase Management'!$O$5:$O$224,0) -> 3 | F12: =COUNTIFS('Purchase Management'!$C$5:$C$224,A12,'Purchase Management'!$O$5:$O$224,">0") -> 1 | G12: =VLOOKUP(A12,'Supplier Database'!$A$5:$K$29,9,FALSE())+IFERROR(AVERAGEIF('Purchase Management'!$C$5:$C$224,A12,'Purchase Management'!$O$5:$O$224),0) -> 4.5 | H12: =ROUND(SUMIF('Purchase Management'!$C$5:$C$224,A12,'Purchase Management'!$G$5:$G$224)*(5.5-VLOOKUP(A12,'Supplier Database'!$A$5:$K$29,10,FALSE()))*0.012,0) -> 15 | I12: =IFERROR(1-H12/MAX(1,SUMIF('Purchase Management'!$C$5:$C$224,A12,'Purchase Management'!$G$5:$G$224)),1) -> 0.98705781 | J12: =IFERROR(E12/MAX(1,E12+F12),0) -> 0.75 | K12: =ROUND(0.45*J12*100+0.35*I12*100+0.2*(VLOOKUP(A12,'Supplier Database'!$A$5:$K$29,10,FALSE())*20),1) -> 85.9 | L12: =IF(K12>=85,"Excellent",IF(K12>=75,"Good",IF(K12>=65,"Average","Poor"))) -> Excellent
A13: SUP002 | B13: =VLOOKUP(A13,'Supplier Database'!$A$5:$K$29,2,FALSE()) -> Bright Distributors | C13: =COUNTIF('Purchase Management'!$C$5:$C$224,A13) -> 9 | D13: =SUMIF('Purchase Management'!$C$5:$C$224,A13,'Purchase Management'!$I$5:$I$224) -> 7825955.3 | E13: =COUNTIFS('Purchase Management'!$C$5:$C$224,A13,'Purchase Management'!$N$5:$N$224,"Received",'Purchase Management'!$O$5:$O$224,0) -> 4 | F13: =COUNTIFS('Purchase Management'!$C$5:$C$224,A13,'Purchase Management'!$O$5:$O$224,">0") -> 4 | G13: =VLOOKUP(A13,'Supplier Database'!$A$5:$K$29,9,FALSE())+IFERROR(AVERAGEIF('Purchase Management'!$C$5:$C$224,A13,'Purchase Management'!$O$5:$O$224),0) -> 9.5555556 | H13: =ROUND(SUMIF('Purchase Management'!$C$5:$C$224,A13,'Purchase Management'!$G$5:$G$224)*(5.5-VLOOKUP(A13,'Supplier Database'!$A$5:$K$29,10,FALSE()))*0.012,0) -> 69 | I13: =IFERROR(1-H13/MAX(1,SUMIF('Purchase Management'!$C$5:$C$224,A13,'Purchase Management'!$G$5:$G$224)),1) -> 0.97370427 | J13: =IFERROR(E13/MAX(1,E13+F13),0) -> 0.5 | K13: =ROUND(0.45*J13*100+0.35*I13*100+0.2*(VLOOKUP(A13,'Supplier Database'!$A$5:$K$29,10,FALSE())*20),1) -> 69.8 | L13: =IF(K13>=85,"Excellent",IF(K13>=75,"Good",IF(K13>=65,"Average","Poor"))) -> Average
A14: SUP003 | B14: =VLOOKUP(A14,'Supplier Database'!$A$5:$K$29,2,FALSE()) -> Core Industries | C14: =COUNTIF('Purchase Management'!$C$5:$C$224,A14) -> 3 | D14: =SUMIF('Purchase Management'!$C$5:$C$224,A14,'Purchase Management'!$I$5:$I$224) -> 2086946.9 | E14: =COUNTIFS('Purchase Management'!$C$5:$C$224,A14,'Purchase Management'!$N$5:$N$224,"Received",'Purchase Management'!$O$5:$O$224,0) -> 0 | F14: =COUNTIFS('Purchase Management'!$C$5:$C$224,A14,'Purchase Management'!$O$5:$O$224,">0") -> 3 | G14: =VLOOKUP(A14,'Supplier Database'!$A$5:$K$29,9,FALSE())+IFERROR(AVERAGEIF('Purchase Management'!$C$5:$C$224,A14,'Purchase Management'!$O$5:$O$224),0) -> 7.6666667 | H14: =ROUND(SUMIF('Purchase Management'!$C$5:$C$224,A14,'Purchase Management'!$G$5:$G$224)*(5.5-VLOOKUP(A14,'Supplier Database'!$A$5:$K$29,10,FALSE()))*0.012,0) -> 25 | I14: =IFERROR(1-H14/MAX(1,SUMIF('Purchase Management'!$C$5:$C$224,A14,'Purchase Management'!$G$5:$G$224)),1) -> 0.9682338 | J14: =IFERROR(E14/MAX(1,E14+F14),0) -> 0 | K14: =ROUND(0.45*J14*100+0.35*I14*100+0.2*(VLOOKUP(A14,'Supplier Database'!$A$5:$K$29,10,FALSE())*20),1) -> 45.5 | L14: =IF(K14>=85,"Excellent",IF(K14>=75,"Good",IF(K14>=65,"Average","Poor"))) -> Poor
A15: SUP004 | B15: =VLOOKUP(A15,'Supplier Database'!$A$5:$K$29,2,FALSE()) -> Delta Trading Co. | C15: =COUNTIF('Purchase Management'!$C$5:$C$224,A15) -> 10 | D15: =SUMIF('Purchase Management'!$C$5:$C$224,A15,'Purchase Management'!$I$5:$I$224) -> 20947982 | E15: =COUNTIFS('Purchase Management'!$C$5:$C$224,A15,'Purchase Management'!$N$5:$N$224,"Received",'Purchase Management'!$O$5:$O$224,0) -> 4 | F15: =COUNTIFS('Purchase Management'!$C$5:$C$224,A15,'Purchase Management'!$O$5:$O$224,">0") -> 4 | G15: =VLOOKUP(A15,'Supplier Database'!$A$5:$K$29,9,FALSE())+IFERROR(AVERAGEIF('Purchase Management'!$C$5:$C$224,A15,'Purchase Management'!$O$5:$O$224),0) -> 11.4 | H15: =ROUND(SUMIF('Purchase Management'!$C$5:$C$224,A15,'Purchase Management'!$G$5:$G$224)*(5.5-VLOOKUP(A15,'Supplier Database'!$A$5:$K$29,10,FALSE()))*0.012,0) -> 86 | I15: =IFERROR(1-H15/MAX(1,SUMIF('Purchase Management'!$C$5:$C$224,A15,'Purchase Management'!$G$5:$G$224)),1) -> 0.97490516 | J15: =IFERROR(E15/MAX(1,E15+F15),0) -> 0.5 | K15: =ROUND(0.45*J15*100+0.35*I15*100+0.2*(VLOOKUP(A15,'Supplier Database'!$A$5:$K$29,10,FALSE())*20),1) -> 70.2 | L15: =IF(K15>=85,"Excellent",IF(K15>=75,"Good",IF(K15>=65,"Average","Poor"))) -> Average
A16: SUP005 | B16: =VLOOKUP(A16,'Supplier Database'!$A$5:$K$29,2,FALSE()) -> Ever Logistics | C16: =COUNTIF('Purchase Management'!$C$5:$C$224,A16) -> 11 | D16: =SUMIF('Purchase Management'!$C$5:$C$224,A16,'Purchase Management'!$I$5:$I$224) -> 11196676 | E16: =COUNTIFS('Purchase Management'!$C$5:$C$224,A16,'Purchase Management'!$N$5:$N$224,"Received",'Purchase Management'!$O$5:$O$224,0) -> 7 | F16: =COUNTIFS('Purchase Management'!$C$5:$C$224,A16,'Purchase Management'!$O$5:$O$224,">0") -> 2 | G16: =VLOOKUP(A16,'Supplier Database'!$A$5:$K$29,9,FALSE())+IFERROR(AVERAGEIF('Purchase Management'!$C$5:$C$224,A16,'Purchase Management'!$O$5:$O$224),0) -> 3.2727273 | H16: =ROUND(SUMIF('Purchase Management'!$C$5:$C$224,A16,'Purchase Management'!$G$5:$G$224)*(5.5-VLOOKUP(A16,'Supplier Database'!$A$5:$K$29,10,FALSE()))*0.012,0) -> 39 | I16: =IFERROR(1-H16/MAX(1,SUMIF('Purchase Management'!$C$5:$C$224,A16,'Purchase Management'!$G$5:$G$224)),1) -> 0.98792196 | J16: =IFERROR(E16/MAX(1,E16+F16),0) -> 0.77777778 | K16: =ROUND(0.45*J16*100+0.35*I16*100+0.2*(VLOOKUP(A16,'Supplier Database'!$A$5:$K$29,10,FALSE())*20),1) -> 87.6 | L16: =IF(K16>=85,"Excellent",IF(K16>=75,"Good",IF(K16>=65,"Average","Poor"))) -> Excellent
A17: SUP006 | B17: =VLOOKUP(A17,'Supplier Database'!$A$5:$K$29,2,FALSE()) -> Frontier Wholesale | C17: =COUNTIF('Purchase Management'!$C$5:$C$224,A17) -> 9 | D17: =SUMIF('Purchase Management'!$C$5:$C$224,A17,'Purchase Management'!$I$5:$I$224) -> 9951347.4 | E17: =COUNTIFS('Purchase Management'!$C$5:$C$224,A17,'Purchase Management'!$N$5:$N$224,"Received",'Purchase Management'!$O$5:$O$224,0) -> 2 | F17: =COUNTIFS('Purchase Management'!$C$5:$C$224,A17,'Purchase Management'!$O$5:$O$224,">0") -> 5 | G17: =VLOOKUP(A17,'Supplier Database'!$A$5:$K$29,9,FALSE())+IFERROR(AVERAGEIF('Purchase Management'!$C$5:$C$224,A17,'Purchase Management'!$O$5:$O$224),0) -> 13.444444 | H17: =ROUND(SUMIF('Purchase Management'!$C$5:$C$224,A17,'Purchase Management'!$G$5:$G$224)*(5.5-VLOOKUP(A17,'Supplier Database'!$A$5:$K$29,10,FALSE()))*0.012,0) -> 43 | I17: =IFERROR(1-H17/MAX(1,SUMIF('Purchase Management'!$C$5:$C$224,A17,'Purchase Management'!$G$5:$G$224)),1) -> 0.98426637 | J17: =IFERROR(E17/MAX(1,E17+F17),0) -> 0.28571429 | K17: =ROUND(0.45*J17*100+0.35*I17*100+0.2*(VLOOKUP(A17,'Supplier Database'!$A$5:$K$29,10,FALSE())*20),1) -> 64.1 | L17: =IF(K17>=85,"Excellent",IF(K17>=75,"Good",IF(K17>=65,"Average","Poor"))) -> Poor
A18: SUP007 | B18: =VLOOKUP(A18,'Supplier Database'!$A$5:$K$29,2,FALSE()) -> Global Partners | C18: =COUNTIF('Purchase Management'!$C$5:$C$224,A18) -> 7 | D18: =SUMIF('Purchase Management'!$C$5:$C$224,A18,'Purchase Management'!$I$5:$I$224) -> 8152619.9 | E18: =COUNTIFS('Purchase Management'!$C$5:$C$224,A18,'Purchase Management'!$N$5:$N$224,"Received",'Purchase Management'!$O$5:$O$224,0) -> 4 | F18: =COUNTIFS('Purchase Management'!$C$5:$C$224,A18,'Purchase Management'!$O$5:$O$224,">0") -> 3 | G18: =VLOOKUP(A18,'Supplier Database'!$A$5:$K$29,9,FALSE())+IFERROR(AVERAGEIF('Purchase Management'!$C$5:$C$224,A18,'Purchase Management'!$O$5:$O$224),0) -> 15.571429 | H18: =ROUND(SUMIF('Purchase Management'!$C$5:$C$224,A18,'Purchase Management'!$G$5:$G$224)*(5.5-VLOOKUP(A18,'Supplier Database'!$A$5:$K$29,10,FALSE()))*0.012,0) -> 25 | I18: =IFERROR(1-H18/MAX(1,SUMIF('Purchase Management'!$C$5:$C$224,A18,'Purchase Management'!$G$5:$G$224)),1) -> 0.98903509 | J18: =IFERROR(E18/MAX(1,E18+F18),0) -> 0.57142857 | K18: =ROUND(0.45*J18*100+0.35*I18*100+0.2*(VLOOKUP(A18,'Supplier Database'!$A$5:$K$29,10,FALSE())*20),1) -> 78.7 | L18: =IF(K18>=85,"Excellent",IF(K18>=75,"Good",IF(K18>=65,"Average","Poor"))) -> Good
A19: SUP008 | B19: =VLOOKUP(A19,'Supplier Database'!$A$5:$K$29,2,FALSE()) -> Horizon Supplies | C19: =COUNTIF('Purchase Management'!$C$5:$C$224,A19) -> 11 | D19: =SUMIF('Purchase Management'!$C$5:$C$224,A19,'Purchase Management'!$I$5:$I$224) -> 8308347.5 | E19: =COUNTIFS('Purchase Management'!$C$5:$C$224,A19,'Purchase Management'!$N$5:$N$224,"Received",'Purchase Management'!$O$5:$O$224,0) -> 7 | F19: =COUNTIFS('Purchase Management'!$C$5:$C$224,A19,'Purchase Management'!$O$5:$O$224,">0") -> 2 | G19: =VLOOKUP(A19,'Supplier Database'!$A$5:$K$29,9,FALSE())+IFERROR(AVERAGEIF('Purchase Management'!$C$5:$C$224,A19,'Purchase Management'!$O$5:$O$224),0) -> 5.6363636 | H19: =ROUND(SUMIF('Purchase Management'!$C$5:$C$224,A19,'Purchase Management'!$G$5:$G$224)*(5.5-VLOOKUP(A19,'Supplier Database'!$A$5:$K$29,10,FALSE()))*0.012,0) -> 37 | I19: =IFERROR(1-H19/MAX(1,SUMIF('Purchase Management'!$C$5:$C$224,A19,'Purchase Management'!$G$5:$G$224)),1) -> 0.98453177 | J19: =IFERROR(E19/MAX(1,E19+F19),0) -> 0.77777778 | K19: =ROUND(0.45*J19*100+0.35*I19*100+0.2*(VLOOKUP(A19,'Supplier Database'!$A$5:$K$29,10,FALSE())*20),1) -> 86.3 | L19: =IF(K19>=85,"Excellent",IF(K19>=75,"Good",IF(K19>=65,"Average","Poor"))) -> Excellent
A20: SUP009 | B20: =VLOOKUP(A20,'Supplier Database'!$A$5:$K$29,2,FALSE()) -> Indus Distributors | C20: =COUNTIF('Purchase Management'!$C$5:$C$224,A20) -> 4 | D20: =SUMIF('Purchase Management'!$C$5:$C$224,A20,'Purchase Management'!$I$5:$I$224) -> 4328441.5 | E20: =COUNTIFS('Purchase Management'!$C$5:$C$224,A20,'Purchase Management'!$N$5:$N$224,"Received",'Purchase Management'!$O$5:$O$224,0) -> 3 | F20: =COUNTIFS('Purchase Management'!$C$5:$C$224,A20,'Purchase Management'!$O$5:$O$224,">0") -> 1 | G20: =VLOOKUP(A20,'Supplier Database'!$A$5:$K$29,9,FALSE())+IFERROR(AVERAGEIF('Purchase Management'!$C$5:$C$224,A20,'Purchase Management'!$O$5:$O$224),0) -> 9.5 | H20: =ROUND(SUMIF('Purchase Management'!$C$5:$C$224,A20,'Purchase Management'!$G$5:$G$224)*(5.5-VLOOKUP(A20,'Supplier Database'!$A$5:$K$29,10,FALSE()))*0.012,0) -> 7 | I20: =IFERROR(1-H20/MAX(1,SUMIF('Purchase Management'!$C$5:$C$224,A20,'Purchase Management'!$G$5:$G$224)),1) -> 0.99314398 | J20: =IFERROR(E20/MAX(1,E20+F20),0) -> 0.75 | K20: =ROUND(0.45*J20*100+0.35*I20*100+0.2*(VLOOKUP(A20,'Supplier Database'!$A$5:$K$29,10,FALSE())*20),1) -> 88.1 | L20: =IF(K20>=85,"Excellent",IF(K20>=75,"Good",IF(K20>=65,"Average","Poor"))) -> Excellent
A21: SUP010 | B21: =VLOOKUP(A21,'Supplier Database'!$A$5:$K$29,2,FALSE()) -> Jupiter Industries | C21: =COUNTIF('Purchase Management'!$C$5:$C$224,A21) -> 12 | D21: =SUMIF('Purchase Management'!$C$5:$C$224,A21,'Purchase Management'!$I$5:$I$224) -> 12994660 | E21: =COUNTIFS('Purchase Management'!$C$5:$C$224,A21,'Purchase Management'!$N$5:$N$224,"Received",'Purchase Management'!$O$5:$O$224,0) -> 7 | F21: =COUNTIFS('Purchase Management'!$C$5:$C$224,A21,'Purchase Management'!$O$5:$O$224,">0") -> 2 | G21: =VLOOKUP(A21,'Supplier Database'!$A$5:$K$29,9,FALSE())+IFERROR(AVERAGEIF('Purchase Management'!$C$5:$C$224,A21,'Purchase Management'!$O$5:$O$224),0) -> 14.666667 | H21: =ROUND(SUMIF('Purchase Management'!$C$5:$C$224,A21,'Purchase Management'!$G$5:$G$224)*(5.5-VLOOKUP(A21,'Supplier Database'!$A$5:$K$29,10,FALSE()))*0.012,0) -> 40 | I21: =IFERROR(1-H21/MAX(1,SUMIF('Purchase Management'!$C$5:$C$224,A21,'Purchase Management'!$G$5:$G$224)),1) -> 0.98786776 | J21: =IFERROR(E21/MAX(1,E21+F21),0) -> 0.77777778 | K21: =ROUND(0.45*J21*100+0.35*I21*100+0.2*(VLOOKUP(A21,'Supplier Database'!$A$5:$K$29,10,FALSE())*20),1) -> 87.6 | L21: =IF(K21>=85,"Excellent",IF(K21>=75,"Good",IF(K21>=65,"Average","Poor"))) -> Excellent
A22: SUP011 | B22: =VLOOKUP(A22,'Supplier Database'!$A$5:$K$29,2,FALSE()) -> Kinetic Trading Co. | C22: =COUNTIF('Purchase Management'!$C$5:$C$224,A22) -> 11 | D22: =SUMIF('Purchase Management'!$C$5:$C$224,A22,'Purchase Management'!$I$5:$I$224) -> 9110465.2 | E22: =COUNTIFS('Purchase Management'!$C$5:$C$224,A22,'Purchase Management'!$N$5:$N$224,"Received",'Purchase Management'!$O$5:$O$224,0) -> 4 | F22: =COUNTIFS('Purchase Management'!$C$5:$C$224,A22,'Purchase Management'!$O$5:$O$224,">0") -> 5 | G22: =VLOOKUP(A22,'Supplier Database'!$A$5:$K$29,9,FALSE())+IFERROR(AVERAGEIF('Purchase Management'!$C$5:$C$224,A22,'Purchase Management'!$O$5:$O$224),0) -> 13.272727 | H22: =ROUND(SUMIF('Purchase Management'!$C$5:$C$224,A22,'Purchase Management'!$G$5:$G$224)*(5.5-VLOOKUP(A22,'Supplier Database'!$A$5:$K$29,10,FALSE()))*0.012,0) -> 18 | I22: =IFERROR(1-H22/MAX(1,SUMIF('Purchase Management'!$C$5:$C$224,A22,'Purchase Management'!$G$5:$G$224)),1) -> 0.99048626 | J22: =IFERROR(E22/MAX(1,E22+F22),0) -> 0.44444444 | K22: =ROUND(0.45*J22*100+0.35*I22*100+0.2*(VLOOKUP(A22,'Supplier Database'!$A$5:$K$29,10,FALSE())*20),1) -> 73.5 | L22: =IF(K22>=85,"Excellent",IF(K22>=75,"Good",IF(K22>=65,"Average","Poor"))) -> Average
A23: SUP012 | B23: =VLOOKUP(A23,'Supplier Database'!$A$5:$K$29,2,FALSE()) -> Lotus Logistics | C23: =COUNTIF('Purchase Management'!$C$5:$C$224,A23) -> 10 | D23: =SUMIF('Purchase Management'!$C$5:$C$224,A23,'Purchase Management'!$I$5:$I$224) -> 13330848 | E23: =COUNTIFS('Purchase Management'!$C$5:$C$224,A23,'Purchase Management'!$N$5:$N$224,"Received",'Purchase Management'!$O$5:$O$224,0) -> 7 | F23: =COUNTIFS('Purchase Management'!$C$5:$C$224,A23,'Purchase Management'!$O$5:$O$224,">0") -> 3 | G23: =VLOOKUP(A23,'Supplier Database'!$A$5:$K$29,9,FALSE())+IFERROR(AVERAGEIF('Purchase Management'!$C$5:$C$224,A23,'Purchase Management'!$O$5:$O$224),0) -> 11.3 | H23: =ROUND(SUMIF('Purchase Management'!$C$5:$C$224,A23,'Purchase Management'!$G$5:$G$224)*(5.5-VLOOKUP(A23,'Supplier Database'!$A$5:$K$29,10,FALSE()))*0.012,0) -> 26 | I23: =IFERROR(1-H23/MAX(1,SUMIF('Purchase Management'!$C$5:$C$224,A23,'Purchase Management'!$G$5:$G$224)),1) -> 0.98925176 | J23: =IFERROR(E23/MAX(1,E23+F23),0) -> 0.7 | K23: =ROUND(0.45*J23*100+0.35*I23*100+0.2*(VLOOKUP(A23,'Supplier Database'!$A$5:$K$29,10,FALSE())*20),1) -> 84.5 | L23: =IF(K23>=85,"Excellent",IF(K23>=75,"Good",IF(K23>=65,"Average","Poor"))) -> Good
... A36: SUP025 | B36: =VLOOKUP(A36,'Supplier Database'!$A$5:$K$29,2,FALSE()) -> Zenith Trading Co. | C36: =COUNTIF('Purchase Management'!$C$5:$C$224,A36) -> 12 | D36: =SUMIF('Purchase Management'!$C$5:$C$224,A36,'Purchase Management'!$I$5:$I$224) -> 14661700 | E36: =COUNTIFS('Purchase Management'!$C$5:$C$224,A36,'Purchase Management'!$N$5:$N$224,"Received",'Purchase Management'!$O$5:$O$224,0) -> 6 | F36: =COUNTIFS('Purchase Management'!$C$5:$C$224,A36,'Purchase Management'!$O$5:$O$224,">0") -> 5 | G36: =VLOOKUP(A36,'Supplier Database'!$A$5:$K$29,9,FALSE())+IFERROR(AVERAGEIF('Purchase Management'!$C$5:$C$224,A36,'Purchase Management'!$O$5:$O$224),0) -> 6 | H36: =ROUND(SUMIF('Purchase Management'!$C$5:$C$224,A36,'Purchase Management'!$G$5:$G$224)*(5.5-VLOOKUP(A36,'Supplier Database'!$A$5:$K$29,10,FALSE()))*0.012,0) -> 53 | I36: =IFERROR(1-H36/MAX(1,SUMIF('Purchase Management'!$C$5:$C$224,A36,'Purchase Management'!$G$5:$G$224)),1) -> 0.98554677 | J36: =IFERROR(E36/MAX(1,E36+F36),0) -> 0.54545455 | K36: =ROUND(0.45*J36*100+0.35*I36*100+0.2*(VLOOKUP(A36,'Supplier Database'!$A$5:$K$29,10,FALSE())*20),1) -> 76.2 | L36: =IF(K36>=85,"Excellent",IF(K36>=75,"Good",IF(K36>=65,"Average","Poor"))) -> Good

Sheet Product Performance Dashboard
A1: PRODUCT PERFORMANCE & PROFITABILITY DASHBOARD
A2: SKU-level demand, sales revenue, unit profitability, category contribution, return rates, and inventory risk signals.
A4: Total Products | C4: Total Units Sold | E4: Total Sales Revenue | G4: Average Selling Price
A5: =COUNTA('Product Master'!$A$5:$A$104) -> 100 | C5: =SUM(C24:C123) -> 8034 | E5: =SUM(D24:D123) -> 49134145 | G5: =AVERAGE('Product Master'!$F$5:$F$104) -> 5883.8146
A7: Best-Selling Product | C7: Lowest-Selling Product | E7: Product Return Rate | G7: Total Gross Profit
A8: =INDEX(A24:A123,MATCH(MAX(C24:C123),C24:C123,0)) -> PRD062 | C8: =INDEX(A24:A123,MATCH(MIN(C24:C123),C24:C123,0)) -> PRD024 | E8: =IFERROR(SUM('Inventory Management'!$J$5:$J$104)/SUM('Inventory Management'!$I$5:$I$104),0) -> 0.0085756398 | G8: =SUM(I24:I123) -> 14577584
A11: Revenue & Profitability by Product Category
A12: Product Category | B12: Units Sold | C12: Sales Revenue (₹) | D12: Gross Profit (₹) | E12: Return Rate
A13: Electronics | B13: =SUMIF(E24:E123,A13,C24:C123) -> 1026 | C13: =SUMIF(E24:E123,A13,D24:D123) -> 7418459.1 | D13: =SUMIF(E24:E123,A13,I24:I123) -> 2333398.4 | E13: =IFERROR(SUMIF('Inventory Management'!$C$5:$C$104,A13,'Inventory Management'!$J$5:$J$104)/SUMIF('Inventory Management'!$C$5:$C$104,A13,'Inventory Management'!$I$5:$I$104),0) -> 0.016059957
A14: Home & Kitchen | B14: =SUMIF(E24:E123,A14,C24:C123) -> 995 | C14: =SUMIF(E24:E123,A14,D24:D123) -> 6359299.4 | D14: =SUMIF(E24:E123,A14,I24:I123) -> 1600191.7 | E14: =IFERROR(SUMIF('Inventory Management'!$C$5:$C$104,A14,'Inventory Management'!$J$5:$J$104)/SUMIF('Inventory Management'!$C$5:$C$104,A14,'Inventory Management'!$I$5:$I$104),0) -> 0.0031545741
A15: Office Supplies | B15: =SUMIF(E24:E123,A15,C24:C123) -> 1140 | C15: =SUMIF(E24:E123,A15,D24:D123) -> 5066638.8 | D15: =SUMIF(E24:E123,A15,I24:I123) -> 1541791.7 | E15: =IFERROR(SUMIF('Inventory Management'!$C$5:$C$104,A15,'Inventory Management'!$J$5:$J$104)/SUMIF('Inventory Management'!$C$5:$C$104,A15,'Inventory Management'!$I$5:$I$104),0) -> 0.0057088487
A16: Personal Care | B16: =SUMIF(E24:E123,A16,C24:C123) -> 886 | C16: =SUMIF(E24:E123,A16,D24:D123) -> 5583999.6 | D16: =SUMIF(E24:E123,A16,I24:I123) -> 1670028.7 | E16: =IFERROR(SUMIF('Inventory Management'!$C$5:$C$104,A16,'Inventory Management'!$J$5:$J$104)/SUMIF('Inventory Management'!$C$5:$C$104,A16,'Inventory Management'!$I$5:$I$104),0) -> 0.0034924331
A17: Industrial | B17: =SUMIF(E24:E123,A17,C24:C123) -> 1139 | C17: =SUMIF(E24:E123,A17,D24:D123) -> 7605893.4 | D17: =SUMIF(E24:E123,A17,I24:I123) -> 2207153.6 | E17: =IFERROR(SUMIF('Inventory Management'!$C$5:$C$104,A17,'Inventory Management'!$J$5:$J$104)/SUMIF('Inventory Management'!$C$5:$C$104,A17,'Inventory Management'!$I$5:$I$104),0) -> 0.011976048
A18: Packaging | B18: =SUMIF(E24:E123,A18,C24:C123) -> 992 | C18: =SUMIF(E24:E123,A18,D24:D123) -> 6074915.3 | D18: =SUMIF(E24:E123,A18,I24:I123) -> 1965801.5 | E18: =IFERROR(SUMIF('Inventory Management'!$C$5:$C$104,A18,'Inventory Management'!$J$5:$J$104)/SUMIF('Inventory Management'!$C$5:$C$104,A18,'Inventory Management'!$I$5:$I$104),0) -> 0.0030991736
A19: Apparel | B19: =SUMIF(E24:E123,A19,C24:C123) -> 919 | C19: =SUMIF(E24:E123,A19,D24:D123) -> 6042303.9 | D19: =SUMIF(E24:E123,A19,I24:I123) -> 1963784.5 | E19: =IFERROR(SUMIF('Inventory Management'!$C$5:$C$104,A19,'Inventory Management'!$J$5:$J$104)/SUMIF('Inventory Management'!$C$5:$C$104,A19,'Inventory Management'!$I$5:$I$104),0) -> 0.0024660912
A20: Automotive | B20: =SUMIF(E24:E123,A20,C24:C123) -> 937 | C20: =SUMIF(E24:E123,A20,D24:D123) -> 4982635.5 | D20: =SUMIF(E24:E123,A20,I24:I123) -> 1295433.6 | E20: =IFERROR(SUMIF('Inventory Management'!$C$5:$C$104,A20,'Inventory Management'!$J$5:$J$104)/SUMIF('Inventory Management'!$C$5:$C$104,A20,'Inventory Management'!$I$5:$I$104),0) -> 0.022547914
A22: Product Performance Ranking, Profitability & Inventory Signal (100 SKUs)
A23: Product ID | B23: Product Name | C23: Units Sold | D23: Revenue | E23: Category | F23: Unit Cost | G23: Selling Price | H23: Profit / Unit | I23: Total Profit | J23: Profit Margin | K23: Inventory Signal
A24: PRD001 | B24: =VLOOKUP(A24,'Product Master'!$A$5:$K$104,2,FALSE()) -> Everyday Electronics Item 001 | C24: =SUMIF('Order Tracking'!$G$5:$G$604,A24,'Order Tracking'!$J$5:$J$604) -> 50 | D24: =SUMIF('Order Tracking'!$G$5:$G$604,A24,'Order Tracking'!$L$5:$L$604) -> 145620 | E24: =VLOOKUP(A24,'Product Master'!$A$5:$K$104,3,FALSE()) -> Electronics | F24: =VLOOKUP(A24,'Product Master'!$A$5:$K$104,5,FALSE()) -> 2345.85 | G24: =VLOOKUP(A24,'Product Master'!$A$5:$K$104,6,FALSE()) -> 2912.4 | H24: =G24-F24 -> 566.55 | I24: =C24*H24 -> 28327.5 | J24: =IFERROR(H24/G24,0) -> 0.19453028 | K24: =VLOOKUP(A24,'Inventory Management'!$A$5:$Q$104,16,FALSE()) -> Out of Stock
A25: PRD002 | B25: =VLOOKUP(A25,'Product Master'!$A$5:$K$104,2,FALSE()) -> Premium Home Item 002 | C25: =SUMIF('Order Tracking'!$G$5:$G$604,A25,'Order Tracking'!$J$5:$J$604) -> 16 | D25: =SUMIF('Order Tracking'!$G$5:$G$604,A25,'Order Tracking'!$L$5:$L$604) -> 150869.92 | E25: =VLOOKUP(A25,'Product Master'!$A$5:$K$104,3,FALSE()) -> Home & Kitchen | F25: =VLOOKUP(A25,'Product Master'!$A$5:$K$104,5,FALSE()) -> 7961.45 | G25: =VLOOKUP(A25,'Product Master'!$A$5:$K$104,6,FALSE()) -> 9429.37 | H25: =G25-F25 -> 1467.92 | I25: =C25*H25 -> 23486.72 | J25: =IFERROR(H25/G25,0) -> 0.1556753 | K25: =VLOOKUP(A25,'Inventory Management'!$A$5:$Q$104,16,FALSE()) -> Low Stock
A26: PRD003 | B26: =VLOOKUP(A26,'Product Master'!$A$5:$K$104,2,FALSE()) -> Premium Office Item 003 | C26: =SUMIF('Order Tracking'!$G$5:$G$604,A26,'Order Tracking'!$J$5:$J$604) -> 65 | D26: =SUMIF('Order Tracking'!$G$5:$G$604,A26,'Order Tracking'!$L$5:$L$604) -> 107454.75 | E26: =VLOOKUP(A26,'Product Master'!$A$5:$K$104,3,FALSE()) -> Office Supplies | F26: =VLOOKUP(A26,'Product Master'!$A$5:$K$104,5,FALSE()) -> 1229.99 | G26: =VLOOKUP(A26,'Product Master'!$A$5:$K$104,6,FALSE()) -> 1653.15 | H26: =G26-F26 -> 423.16 | I26: =C26*H26 -> 27505.4 | J26: =IFERROR(H26/G26,0) -> 0.25597193 | K26: =VLOOKUP(A26,'Inventory Management'!$A$5:$Q$104,16,FALSE()) -> Healthy Stock
A27: PRD004 | B27: =VLOOKUP(A27,'Product Master'!$A$5:$K$104,2,FALSE()) -> Everyday Personal Item 004 | C27: =SUMIF('Order Tracking'!$G$5:$G$604,A27,'Order Tracking'!$J$5:$J$604) -> 27 | D27: =SUMIF('Order Tracking'!$G$5:$G$604,A27,'Order Tracking'!$L$5:$L$604) -> 146952.63 | E27: =VLOOKUP(A27,'Product Master'!$A$5:$K$104,3,FALSE()) -> Personal Care | F27: =VLOOKUP(A27,'Product Master'!$A$5:$K$104,5,FALSE()) -> 3791.99 | G27: =VLOOKUP(A27,'Product Master'!$A$5:$K$104,6,FALSE()) -> 5442.69 | H27: =G27-F27 -> 1650.7 | I27: =C27*H27 -> 44568.9 | J27: =IFERROR(H27/G27,0) -> 0.30328753 | K27: =VLOOKUP(A27,'Inventory Management'!$A$5:$Q$104,16,FALSE()) -> Healthy Stock
A28: PRD005 | B28: =VLOOKUP(A28,'Product Master'!$A$5:$K$104,2,FALSE()) -> Everyday Industrial Item 005 | C28: =SUMIF('Order Tracking'!$G$5:$G$604,A28,'Order Tracking'!$J$5:$J$604) -> 87 | D28: =SUMIF('Order Tracking'!$G$5:$G$604,A28,'Order Tracking'!$L$5:$L$604) -> 136911.03 | E28: =VLOOKUP(A28,'Product Master'!$A$5:$K$104,3,FALSE()) -> Industrial | F28: =VLOOKUP(A28,'Product Master'!$A$5:$K$104,5,FALSE()) -> 988.05 | G28: =VLOOKUP(A28,'Product Master'!$A$5:$K$104,6,FALSE()) -> 1573.69 | H28: =G28-F28 -> 585.64 | I28: =C28*H28 -> 50950.68 | J28: =IFERROR(H28/G28,0) -> 0.37214445 | K28: =VLOOKUP(A28,'Inventory Management'!$A$5:$Q$104,16,FALSE()) -> Out of Stock
A29: PRD006 | B29: =VLOOKUP(A29,'Product Master'!$A$5:$K$104,2,FALSE()) -> Pro Packaging Item 006 | C29: =SUMIF('Order Tracking'!$G$5:$G$604,A29,'Order Tracking'!$J$5:$J$604) -> 94 | D29: =SUMIF('Order Tracking'!$G$5:$G$604,A29,'Order Tracking'!$L$5:$L$604) -> 175509.28 | E29: =VLOOKUP(A29,'Product Master'!$A$5:$K$104,3,FALSE()) -> Packaging | F29: =VLOOKUP(A29,'Product Master'!$A$5:$K$104,5,FALSE()) -> 1422.65 | G29: =VLOOKUP(A29,'Product Master'!$A$5:$K$104,6,FALSE()) -> 1867.12 | H29: =G29-F29 -> 444.47 | I29: =C29*H29 -> 41780.18 | J29: =IFERROR(H29/G29,0) -> 0.23805112 | K29: =VLOOKUP(A29,'Inventory Management'!$A$5:$Q$104,16,FALSE()) -> Healthy Stock
A30: PRD007 | B30: =VLOOKUP(A30,'Product Master'!$A$5:$K$104,2,FALSE()) -> Everyday Apparel Item 007 | C30: =SUMIF('Order Tracking'!$G$5:$G$604,A30,'Order Tracking'!$J$5:$J$604) -> 37 | D30: =SUMIF('Order Tracking'!$G$5:$G$604,A30,'Order Tracking'!$L$5:$L$604) -> 381168.82 | E30: =VLOOKUP(A30,'Product Master'!$A$5:$K$104,3,FALSE()) -> Apparel | F30: =VLOOKUP(A30,'Product Master'!$A$5:$K$104,5,FALSE()) -> 7267.41 | G30: =VLOOKUP(A30,'Product Master'!$A$5:$K$104,6,FALSE()) -> 10301.86 | H30: =G30-F30 -> 3034.45 | I30: =C30*H30 -> 112274.65 | J30: =IFERROR(H30/G30,0) -> 0.2945536 | K30: =VLOOKUP(A30,'Inventory Management'!$A$5:$Q$104,16,FALSE()) -> Healthy Stock
A31: PRD008 | B31: =VLOOKUP(A31,'Product Master'!$A$5:$K$104,2,FALSE()) -> Smart Automotive Item 008 | C31: =SUMIF('Order Tracking'!$G$5:$G$604,A31,'Order Tracking'!$J$5:$J$604) -> 149 | D31: =SUMIF('Order Tracking'!$G$5:$G$604,A31,'Order Tracking'!$L$5:$L$604) -> 1264864 | E31: =VLOOKUP(A31,'Product Master'!$A$5:$K$104,3,FALSE()) -> Automotive | F31: =VLOOKUP(A31,'Product Master'!$A$5:$K$104,5,FALSE()) -> 7069.94 | G31: =VLOOKUP(A31,'Product Master'!$A$5:$K$104,6,FALSE()) -> 8489.02 | H31: =G31-F31 -> 1419.08 | I31: =C31*H31 -> 211442.92 | J31: =IFERROR(H31/G31,0) -> 0.16716653 | K31: =VLOOKUP(A31,'Inventory Management'!$A$5:$Q$104,16,FALSE()) -> Overstocked
A32: PRD009 | B32: =VLOOKUP(A32,'Product Master'!$A$5:$K$104,2,FALSE()) -> Essential Electronics Item 009 | C32: =SUMIF('Order Tracking'!$G$5:$G$604,A32,'Order Tracking'!$J$5:$J$604) -> 80 | D32: =SUMIF('Order Tracking'!$G$5:$G$604,A32,'Order Tracking'!$L$5:$L$604) -> 462276.8 | E32: =VLOOKUP(A32,'Product Master'!$A$5:$K$104,3,FALSE()) -> Electronics | F32: =VLOOKUP(A32,'Product Master'!$A$5:$K$104,5,FALSE()) -> 3822.58 | G32: =VLOOKUP(A32,'Product Master'!$A$5:$K$104,6,FALSE()) -> 5778.46 | H32: =G32-F32 -> 1955.88 | I32: =C32*H32 -> 156470.4 | J32: =IFERROR(H32/G32,0) -> 0.33847773 | K32: =VLOOKUP(A32,'Inventory Management'!$A$5:$Q$104,16,FALSE()) -> Out of Stock
A33: PRD010 | B33: =VLOOKUP(A33,'Product Master'!$A$5:$K$104,2,FALSE()) -> Essential Home Item 010 | C33: =SUMIF('Order Tracking'!$G$5:$G$604,A33,'Order Tracking'!$J$5:$J$604) -> 147 | D33: =SUMIF('Order Tracking'!$G$5:$G$604,A33,'Order Tracking'!$L$5:$L$604) -> 1086146.2 | E33: =VLOOKUP(A33,'Product Master'!$A$5:$K$104,3,FALSE()) -> Home & Kitchen | F33: =VLOOKUP(A33,'Product Master'!$A$5:$K$104,5,FALSE()) -> 5910.74 | G33: =VLOOKUP(A33,'Product Master'!$A$5:$K$104,6,FALSE()) -> 7388.75 | H33: =G33-F33 -> 1478.01 | I33: =C33*H33 -> 217267.47 | J33: =IFERROR(H33/G33,0) -> 0.20003519 | K33: =VLOOKUP(A33,'Inventory Management'!$A$5:$Q$104,16,FALSE()) -> Low Stock
A34: PRD011 | B34: =VLOOKUP(A34,'Product Master'!$A$5:$K$104,2,FALSE()) -> Essential Office Item 011 | C34: =SUMIF('Order Tracking'!$G$5:$G$604,A34,'Order Tracking'!$J$5:$J$604) -> 37 | D34: =SUMIF('Order Tracking'!$G$5:$G$604,A34,'Order Tracking'!$L$5:$L$604) -> 23527.19 | E34: =VLOOKUP(A34,'Product Master'!$A$5:$K$104,3,FALSE()) -> Office Supplies | F34: =VLOOKUP(A34,'Product Master'!$A$5:$K$104,5,FALSE()) -> 470.53 | G34: =VLOOKUP(A34,'Product Master'!$A$5:$K$104,6,FALSE()) -> 635.87 | H34: =G34-F34 -> 165.34 | I34: =C34*H34 -> 6117.58 | J34: =IFERROR(H34/G34,0) -> 0.2600217 | K34: =VLOOKUP(A34,'Inventory Management'!$A$5:$Q$104,16,FALSE()) -> Overstocked
A35: PRD012 | B35: =VLOOKUP(A35,'Product Master'!$A$5:$K$104,2,FALSE()) -> Eco Personal Item 012 | C35: =SUMIF('Order Tracking'!$G$5:$G$604,A35,'Order Tracking'!$J$5:$J$604) -> 149 | D35: =SUMIF('Order Tracking'!$G$5:$G$604,A35,'Order Tracking'!$L$5:$L$604) -> 1145138 | E35: =VLOOKUP(A35,'Product Master'!$A$5:$K$104,3,FALSE()) -> Personal Care | F35: =VLOOKUP(A35,'Product Master'!$A$5:$K$104,5,FALSE()) -> 5708.9 | G35: =VLOOKUP(A35,'Product Master'!$A$5:$K$104,6,FALSE()) -> 7685.49 | H35: =G35-F35 -> 1976.59 | I35: =C35*H35 -> 294511.91 | J35: =IFERROR(H35/G35,0) -> 0.25718464 | K35: =VLOOKUP(A35,'Inventory Management'!$A$5:$Q$104,16,FALSE()) -> Healthy Stock
... A123: PRD100 | B123: =VLOOKUP(A123,'Product Master'!$A$5:$K$104,2,FALSE()) -> Smart Personal Item 100 | C123: =SUMIF('Order Tracking'!$G$5:$G$604,A123,'Order Tracking'!$J$5:$J$604) -> 74 | D123: =SUMIF('Order Tracking'!$G$5:$G$604,A123,'Order Tracking'!$L$5:$L$604) -> 736058.76 | E123: =VLOOKUP(A123,'Product Master'!$A$5:$K$104,3,FALSE()) -> Personal Care | F123: =VLOOKUP(A123,'Product Master'!$A$5:$K$104,5,FALSE()) -> 7321.29 | G123: =VLOOKUP(A123,'Product Master'!$A$5:$K$104,6,FALSE()) -> 9946.74 | H123: =G123-F123 -> 2625.45 | I123: =C123*H123 -> 194283.3 | J123: =IFERROR(H123/G123,0) -> 0.2639508 | K123: =VLOOKUP(A123,'Inventory Management'!$A$5:$Q$104,16,FALSE()) -> Healthy Stock

Sheet Order Tracking
A1: ORDER TRACKING DATABASE (600 ORDERS)
A2: Structured sales order database • VLOOKUP retrieves Product Name & Category; formulas calculate Order Value, Delivery TAT, and Delay Days.
A4: Order ID | B4: Order Date | C4: Customer ID | D4: Customer Name | E4: Region | F4: Warehouse | G4: Product ID | H4: Product Name | I4: Product Category | J4: Quantity Ordered | K4: Unit Price | L4: Order Value | M4: Order Status | N4: Dispatch Date | O4: Expected Delivery Date | P4: Actual Delivery Date | Q4: Delivery TAT | R4: Delay Days | S4: Payment Status | T4: Delay Reason
A5: ORD0001 | B5: 46046 | C5: CUS0066 | D5: Vivaan Rao | E5: South | F5: Mumbai WH | G5: PRD039 | H5: =VLOOKUP(G5,'Product Master'!$A$5:$K$104,2,FALSE()) -> Eco Apparel Item 039 | I5: =VLOOKUP(G5,'Product Master'!$A$5:$K$104,3,FALSE()) -> Apparel | J5: 2 | K5: 3575.06 | L5: =J5*K5 -> 7150.12 | M5: Delivered | N5: 46047 | O5: 46054 | P5: 46056 | Q5: =IF(P5<>"",MAX(1,P5-B5),IF(M5="Dispatched",MAX(1,O5-B5),0)) -> 10 | R5: =IF(M5="Cancelled",0,IF(P5<>"",MAX(0,P5-O5),IF(T5<>"None",MAX(1,O5-B5-2),0))) -> 2 | S5: Paid | T5: Warehouse backlog
A6: ORD0002 | B6: 46161 | C6: CUS0097 | D6: Diya Mishra | E6: North | F6: Raipur WH | G6: PRD048 | H6: =VLOOKUP(G6,'Product Master'!$A$5:$K$104,2,FALSE()) -> Eco Automotive Item 048 | I6: =VLOOKUP(G6,'Product Master'!$A$5:$K$104,3,FALSE()) -> Automotive | J6: 24 | K6: 444.67 | L6: =J6*K6 -> 10672.08 | M6: Dispatched | N6: 46163 | O6: 46167 | Q6: =IF(P6<>"",MAX(1,P6-B6),IF(M6="Dispatched",MAX(1,O6-B6),0)) -> 6 | R6: =IF(M6="Cancelled",0,IF(P6<>"",MAX(0,P6-O6),IF(T6<>"None",MAX(1,O6-B6-2),0))) -> 4 | S6: Paid | T6: Carrier delay
A7: ORD0003 | B7: 46231 | C7: CUS0055 | D7: Vivaan Iyer | E7: Central | F7: Bengaluru WH | G7: PRD093 | H7: =VLOOKUP(G7,'Product Master'!$A$5:$K$104,2,FALSE()) -> Compact Industrial Item 093 | I7: =VLOOKUP(G7,'Product Master'!$A$5:$K$104,3,FALSE()) -> Industrial | J7: 16 | K7: 7420.7 | L7: =J7*K7 -> 118731.2 | M7: Delivered | N7: 46233 | O7: 46238 | P7: 46234 | Q7: =IF(P7<>"",MAX(1,P7-B7),IF(M7="Dispatched",MAX(1,O7-B7),0)) -> 3 | R7: =IF(M7="Cancelled",0,IF(P7<>"",MAX(0,P7-O7),IF(T7<>"None",MAX(1,O7-B7-2),0))) -> 0 | S7: Paid | T7: None
A8: ORD0004 | B8: 46176 | C8: CUS0098 | D8: Dev Mehta | E8: Central | F8: Bengaluru WH | G8: PRD032 | H8: =VLOOKUP(G8,'Product Master'!$A$5:$K$104,2,FALSE()) -> Smart Automotive Item 032 | I8: =VLOOKUP(G8,'Product Master'!$A$5:$K$104,3,FALSE()) -> Automotive | J8: 13 | K8: 10211.16 | L8: =J8*K8 -> 132745.08 | M8: Dispatched | N8: 46178 | O8: 46183 | Q8: =IF(P8<>"",MAX(1,P8-B8),IF(M8="Dispatched",MAX(1,O8-B8),0)) -> 7 | R8: =IF(M8="Cancelled",0,IF(P8<>"",MAX(0,P8-O8),IF(T8<>"None",MAX(1,O8-B8-2),0))) -> 0 | S8: Paid | T8: None
A9: ORD0005 | B9: 46088 | C9: CUS0095 | D9: Reyansh Singh | E9: East | F9: Raipur WH | G9: PRD034 | H9: =VLOOKUP(G9,'Product Master'!$A$5:$K$104,2,FALSE()) -> Classic Home Item 034 | I9: =VLOOKUP(G9,'Product Master'!$A$5:$K$104,3,FALSE()) -> Home & Kitchen | J9: 16 | K9: 3243.31 | L9: =J9*K9 -> 51892.96 | M9: Delivered | N9: 46090 | O9: 46097 | P9: 46097 | Q9: =IF(P9<>"",MAX(1,P9-B9),IF(M9="Dispatched",MAX(1,O9-B9),0)) -> 9 | R9: =IF(M9="Cancelled",0,IF(P9<>"",MAX(0,P9-O9),IF(T9<>"None",MAX(1,O9-B9-2),0))) -> 0 | S9: Paid | T9: None
A10: ORD0006 | B10: 46044 | C10: CUS0051 | D10: Reyansh Nair | E10: South | F10: Delhi WH | G10: PRD095 | H10: =VLOOKUP(G10,'Product Master'!$A$5:$K$104,2,FALSE()) -> Eco Apparel Item 095 | I10: =VLOOKUP(G10,'Product Master'!$A$5:$K$104,3,FALSE()) -> Apparel | J10: 9 | K10: 2884.81 | L10: =J10*K10 -> 25963.29 | M10: Delivered | N10: 46046 | O10: 46052 | P10: 46051 | Q10: =IF(P10<>"",MAX(1,P10-B10),IF(M10="Dispatched",MAX(1,O10-B10),0)) -> 7 | R10: =IF(M10="Cancelled",0,IF(P10<>"",MAX(0,P10-O10),IF(T10<>"None",MAX(1,O10-B10-2),0))) -> 0 | S10: Paid | T10: None
A11: ORD0007 | B11: 46056 | C11: CUS0118 | D11: Meera Iyer | E11: Central | F11: Kolkata WH | G11: PRD064 | H11: =VLOOKUP(G11,'Product Master'!$A$5:$K$104,2,FALSE()) -> Compact Automotive Item 064 | I11: =VLOOKUP(G11,'Product Master'!$A$5:$K$104,3,FALSE()) -> Automotive | J11: 9 | K11: 4156.81 | L11: =J11*K11 -> 37411.29 | M11: Processing | O11: 46065 | Q11: =IF(P11<>"",MAX(1,P11-B11),IF(M11="Dispatched",MAX(1,O11-B11),0)) -> 0 | R11: =IF(M11="Cancelled",0,IF(P11<>"",MAX(0,P11-O11),IF(T11<>"None",MAX(1,O11-B11-2),0))) -> 0 | S11: Pending | T11: None
A12: ORD0008 | B12: 46017 | C12: CUS0215 | D12: Ishaan Mishra | E12: Central | F12: Mumbai WH | G12: PRD018 | H12: =VLOOKUP(G12,'Product Master'!$A$5:$K$104,2,FALSE()) -> Smart Home Item 018 | I12: =VLOOKUP(G12,'Product Master'!$A$5:$K$104,3,FALSE()) -> Home & Kitchen | J12: 6 | K12: 5693.61 | L12: =J12*K12 -> 34161.66 | M12: Dispatched | N12: 46017 | O12: 46019 | Q12: =IF(P12<>"",MAX(1,P12-B12),IF(M12="Dispatched",MAX(1,O12-B12),0)) -> 2 | R12: =IF(M12="Cancelled",0,IF(P12<>"",MAX(0,P12-O12),IF(T12<>"None",MAX(1,O12-B12-2),0))) -> 1 | S12: Paid | T12: Carrier delay
A13: ORD0009 | B13: 45934 | C13: CUS0130 | D13: Dev Rao | E13: South | F13: Bengaluru WH | G13: PRD053 | H13: =VLOOKUP(G13,'Product Master'!$A$5:$K$104,2,FALSE()) -> Classic Industrial Item 053 | I13: =VLOOKUP(G13,'Product Master'!$A$5:$K$104,3,FALSE()) -> Industrial | J13: 3 | K13: 10730.84 | L13: =J13*K13 -> 32192.52 | M13: Processing | O13: 45936 | Q13: =IF(P13<>"",MAX(1,P13-B13),IF(M13="Dispatched",MAX(1,O13-B13),0)) -> 0 | R13: =IF(M13="Cancelled",0,IF(P13<>"",MAX(0,P13-O13),IF(T13<>"None",MAX(1,O13-B13-2),0))) -> 0 | S13: Paid | T13: None
A14: ORD0010 | B14: 46257 | C14: CUS0005 | D14: Arjun Mehta | E14: Central | F14: Mumbai WH | G14: PRD086 | H14: =VLOOKUP(G14,'Product Master'!$A$5:$K$104,2,FALSE()) -> Classic Packaging Item 086 | I14: =VLOOKUP(G14,'Product Master'!$A$5:$K$104,3,FALSE()) -> Packaging | J14: 22 | K14: 7631.52 | L14: =J14*K14 -> 167893.44 | M14: Delivered | N14: 46260 | O14: 46264 | P14: 46262 | Q14: =IF(P14<>"",MAX(1,P14-B14),IF(M14="Dispatched",MAX(1,O14-B14),0)) -> 5 | R14: =IF(M14="Cancelled",0,IF(P14<>"",MAX(0,P14-O14),IF(T14<>"None",MAX(1,O14-B14-2),0))) -> 0 | S14: Refunded | T14: None
A15: ORD0011 | B15: 45939 | C15: CUS0050 | D15: Arjun Mishra | E15: West | F15: Bengaluru WH | G15: PRD065 | H15: =VLOOKUP(G15,'Product Master'!$A$5:$K$104,2,FALSE()) -> Compact Electronics Item 065 | I15: =VLOOKUP(G15,'Product Master'!$A$5:$K$104,3,FALSE()) -> Electronics | J15: 4 | K15: 7172.77 | L15: =J15*K15 -> 28691.08 | M15: Dispatched | N15: 45940 | O15: 45943 | Q15: =IF(P15<>"",MAX(1,P15-B15),IF(M15="Dispatched",MAX(1,O15-B15),0)) -> 4 | R15: =IF(M15="Cancelled",0,IF(P15<>"",MAX(0,P15-O15),IF(T15<>"None",MAX(1,O15-B15-2),0))) -> 2 | S15: Paid | T15: Carrier delay
A16: ORD0012 | B16: 46134 | C16: CUS0168 | D16: Diya Patel | E16: East | F16: Mumbai WH | G16: PRD011 | H16: =VLOOKUP(G16,'Product Master'!$A$5:$K$104,2,FALSE()) -> Essential Office Item 011 | I16: =VLOOKUP(G16,'Product Master'!$A$5:$K$104,3,FALSE()) -> Office Supplies | J16: 15 | K16: 635.87 | L16: =J16*K16 -> 9538.05 | M16: Delivered | N16: 46136 | O16: 46139 | P16: 46137 | Q16: =IF(P16<>"",MAX(1,P16-B16),IF(M16="Dispatched",MAX(1,O16-B16),0)) -> 3 | R16: =IF(M16="Cancelled",0,IF(P16<>"",MAX(0,P16-O16),IF(T16<>"None",MAX(1,O16-B16-2),0))) -> 0 | S16: Paid | T16: None
A17: ORD0013 | B17: 46124 | C17: CUS0166 | D17: Reyansh Joshi | E17: West | F17: Delhi WH | G17: PRD071 | H17: =VLOOKUP(G17,'Product Master'!$A$5:$K$104,2,FALSE()) -> Pro Apparel Item 071 | I17: =VLOOKUP(G17,'Product Master'!$A$5:$K$104,3,FALSE()) -> Apparel | J17: 21 | K17: 10275.49 | L17: =J17*K17 -> 215785.29 | M17: Delivered | N17: 46124 | O17: 46128 | P17: 46132 | Q17: =IF(P17<>"",MAX(1,P17-B17),IF(M17="Dispatched",MAX(1,O17-B17),0)) -> 8 | R17: =IF(M17="Cancelled",0,IF(P17<>"",MAX(0,P17-O17),IF(T17<>"None",MAX(1,O17-B17-2),0))) -> 4 | S17: Refunded | T17: Weather disruption
A18: ORD0014 | B18: 45979 | C18: CUS0012 | D18: Ishaan Khan | E18: North | F18: Bengaluru WH | G18: PRD068 | H18: =VLOOKUP(G18,'Product Master'!$A$5:$K$104,2,FALSE()) -> Compact Personal Item 068 | I18: =VLOOKUP(G18,'Product Master'!$A$5:$K$104,3,FALSE()) -> Personal Care | J18: 7 | K18: 7446.2 | L18: =J18*K18 -> 52123.4 | M18: Dispatched | N18: 45981 | O18: 45988 | Q18: =IF(P18<>"",MAX(1,P18-B18),IF(M18="Dispatched",MAX(1,O18-B18),0)) -> 9 | R18: =IF(M18="Cancelled",0,IF(P18<>"",MAX(0,P18-O18),IF(T18<>"None",MAX(1,O18-B18-2),0))) -> 7 | S18: Partially Paid | T18: Carrier delay
A19: ORD0015 | B19: 46209 | C19: CUS0077 | D19: Meera Joshi | E19: North | F19: Bengaluru WH | G19: PRD073 | H19: =VLOOKUP(G19,'Product Master'!$A$5:$K$104,2,FALSE()) -> Essential Electronics Item 073 | I19: =VLOOKUP(G19,'Product Master'!$A$5:$K$104,3,FALSE()) -> Electronics | J19: 11 | K19: 8260.77 | L19: =J19*K19 -> 90868.47 | M19: Delivered | N19: 46210 | O19: 46214 | P19: 46216 | Q19: =IF(P19<>"",MAX(1,P19-B19),IF(M19="Dispatched",MAX(1,O19-B19),0)) -> 7 | R19: =IF(M19="Cancelled",0,IF(P19<>"",MAX(0,P19-O19),IF(T19<>"None",MAX(1,O19-B19-2),0))) -> 2 | S19: Paid | T19: Carrier delay
A20: ORD0016 | B20: 46130 | C20: CUS0129 | D20: Ira Sharma | E20: Central | F20: Kolkata WH | G20: PRD087 | H20: =VLOOKUP(G20,'Product Master'!$A$5:$K$104,2,FALSE()) -> Compact Apparel Item 087 | I20: =VLOOKUP(G20,'Product Master'!$A$5:$K$104,3,FALSE()) -> Apparel | J20: 13 | K20: 8400.02 | L20: =J20*K20 -> 109200.26 | M20: Processing | O20: 46134 | Q20: =IF(P20<>"",MAX(1,P20-B20),IF(M20="Dispatched",MAX(1,O20-B20),0)) -> 0 | R20: =IF(M20="Cancelled",0,IF(P20<>"",MAX(0,P20-O20),IF(T20<>"None",MAX(1,O20-B20-2),0))) -> 2 | S20: Paid | T20: Warehouse backlog
A21: ORD0017 | B21: 46049 | C21: CUS0008 | D21: Arjun Sahu | E21: East | F21: Raipur WH | G21: PRD010 | H21: =VLOOKUP(G21,'Product Master'!$A$5:$K$104,2,FALSE()) -> Essential Home Item 010 | I21: =VLOOKUP(G21,'Product Master'!$A$5:$K$104,3,FALSE()) -> Home & Kitchen | J21: 25 | K21: 7388.75 | L21: =J21*K21 -> 184718.75 | M21: Pending | O21: 46057 | Q21: =IF(P21<>"",MAX(1,P21-B21),IF(M21="Dispatched",MAX(1,O21-B21),0)) -> 0 | R21: =IF(M21="Cancelled",0,IF(P21<>"",MAX(0,P21-O21),IF(T21<>"None",MAX(1,O21-B21-2),0))) -> 0 | S21: Refunded | T21: None
A22: ORD0018 | B22: 46182 | C22: CUS0205 | D22: Saanvi Iyer | E22: East | F22: Raipur WH | G22: PRD030 | H22: =VLOOKUP(G22,'Product Master'!$A$5:$K$104,2,FALSE()) -> Premium Packaging Item 030 | I22: =VLOOKUP(G22,'Product Master'!$A$5:$K$104,3,FALSE()) -> Packaging | J22: 13 | K22: 6643.61 | L22: =J22*K22 -> 86366.93 | M22: Delivered | N22: 46182 | O22: 46190 | P22: 46190 | Q22: =IF(P22<>"",MAX(1,P22-B22),IF(M22="Dispatched",MAX(1,O22-B22),0)) -> 8 | R22: =IF(M22="Cancelled",0,IF(P22<>"",MAX(0,P22-O22),IF(T22<>"None",MAX(1,O22-B22-2),0))) -> 0 | S22: Paid | T22: None
A23: ORD0019 | B23: 46068 | C23: CUS0002 | D23: Aditi Das | E23: West | F23: Bengaluru WH | G23: PRD020 | H23: =VLOOKUP(G23,'Product Master'!$A$5:$K$104,2,FALSE()) -> Eco Personal Item 020 | I23: =VLOOKUP(G23,'Product Master'!$A$5:$K$104,3,FALSE()) -> Personal Care | J23: 24 | K23: 4674.99 | L23: =J23*K23 -> 112199.76 | M23: Delivered | N23: 46068 | O23: 46075 | P23: 46073 | Q23: =IF(P23<>"",MAX(1,P23-B23),IF(M23="Dispatched",MAX(1,O23-B23),0)) -> 5 | R23: =IF(M23="Cancelled",0,IF(P23<>"",MAX(0,P23-O23),IF(T23<>"None",MAX(1,O23-B23-2),0))) -> 0 | S23: Paid | T23: None
A24: ORD0020 | B24: 46069 | C24: CUS0023 | D24: Ira Mehta | E24: South | F24: Delhi WH | G24: PRD014 | H24: =VLOOKUP(G24,'Product Master'!$A$5:$K$104,2,FALSE()) -> Pro Packaging Item 014 | I24: =VLOOKUP(G24,'Product Master'!$A$5:$K$104,3,FALSE()) -> Packaging | J24: 6 | K24: 4696.7 | L24: =J24*K24 -> 28180.2 | M24: Delivered | N24: 46069 | O24: 46077 | P24: 46073 | Q24: =IF(P24<>"",MAX(1,P24-B24),IF(M24="Dispatched",MAX(1,O24-B24),0)) -> 4 | R24: =IF(M24="Cancelled",0,IF(P24<>"",MAX(0,P24-O24),IF(T24<>"None",MAX(1,O24-B24-2),0))) -> 0 | S24: Paid | T24: None
A25: ORD0021 | B25: 46237 | C25: CUS0176 | D25: Rohan Verma | E25: West | F25: Delhi WH | G25: PRD042 | H25: =VLOOKUP(G25,'Product Master'!$A$5:$K$104,2,FALSE()) -> Compact Home Item 042 | I25: =VLOOKUP(G25,'Product Master'!$A$5:$K$104,3,FALSE()) -> Home & Kitchen | J25: 10 | K25: 5892.15 | L25: =J25*K25 -> 58921.5 | M25: Delivered | N25: 46238 | O25: 46240 | P25: 46248 | Q25: =IF(P25<>"",MAX(1,P25-B25),IF(M25="Dispatched",MAX(1,O25-B25),0)) -> 11 | R25: =IF(M25="Cancelled",0,IF(P25<>"",MAX(0,P25-O25),IF(T25<>"None",MAX(1,O25-B25-2),0))) -> 8 | S25: Paid | T25: Warehouse backlog
A26: ORD0022 | B26: 46085 | C26: CUS0124 | D26: Ishaan Rao | E26: West | F26: Bengaluru WH | G26: PRD035 | H26: =VLOOKUP(G26,'Product Master'!$A$5:$K$104,2,FALSE()) -> Smart Office Item 035 | I26: =VLOOKUP(G26,'Product Master'!$A$5:$K$104,3,FALSE()) -> Office Supplies | J26: 3 | K26: 7869.66 | L26: =J26*K26 -> 23608.98 | M26: Delivered | N26: 46088 | O26: 46091 | P26: 46091 | Q26: =IF(P26<>"",MAX(1,P26-B26),IF(M26="Dispatched",MAX(1,O26-B26),0)) -> 6 | R26: =IF(M26="Cancelled",0,IF(P26<>"",MAX(0,P26-O26),IF(T26<>"None",MAX(1,O26-B26-2),0))) -> 0 | S26: Paid | T26: None
A27: ORD0023 | B27: 46057 | C27: CUS0002 | D27: Rohan Rao | E27: West | F27: Raipur WH | G27: PRD093 | H27: =VLOOKUP(G27,'Product Master'!$A$5:$K$104,2,FALSE()) -> Compact Industrial Item 093 | I27: =VLOOKUP(G27,'Product Master'!$A$5:$K$104,3,FALSE()) -> Industrial | J27: 20 | K27: 7420.7 | L27: =J27*K27 -> 148414 | M27: Delivered | N27: 46058 | O27: 46060 | P27: 46060 | Q27: =IF(P27<>"",MAX(1,P27-B27),IF(M27="Dispatched",MAX(1,O27-B27),0)) -> 3 | R27: =IF(M27="Cancelled",0,IF(P27<>"",MAX(0,P27-O27),IF(T27<>"None",MAX(1,O27-B27-2),0))) -> 0 | S27: Partially Paid | T27: None
A28: ORD0024 | B28: 46125 | C28: CUS0083 | D28: Vivaan Das | E28: West | F28: Kolkata WH | G28: PRD043 | H28: =VLOOKUP(G28,'Product Master'!$A$5:$K$104,2,FALSE()) -> Eco Office Item 043 | I28: =VLOOKUP(G28,'Product Master'!$A$5:$K$104,3,FALSE()) -> Office Supplies | J28: 14 | K28: 2525.48 | L28: =J28*K28 -> 35356.72 | M28: Processing | O28: 46129 | Q28: =IF(P28<>"",MAX(1,P28-B28),IF(M28="Dispatched",MAX(1,O28-B28),0)) -> 0 | R28: =IF(M28="Cancelled",0,IF(P28<>"",MAX(0,P28-O28),IF(T28<>"None",MAX(1,O28-B28-2),0))) -> 2 | S28: Paid | T28: Awaiting stock
A29: ORD0025 | B29: 46134 | C29: CUS0072 | D29: Rohan Rao | E29: East | F29: Mumbai WH | G29: PRD041 | H29: =VLOOKUP(G29,'Product Master'!$A$5:$K$104,2,FALSE()) -> Essential Electronics Item 041 | I29: =VLOOKUP(G29,'Product Master'!$A$5:$K$104,3,FALSE()) -> Electronics | J29: 19 | K29: 12841.6 | L29: =J29*K29 -> 243990.4 | M29: Processing | O29: 46141 | Q29: =IF(P29<>"",MAX(1,P29-B29),IF(M29="Dispatched",MAX(1,O29-B29),0)) -> 0 | R29: =IF(M29="Cancelled",0,IF(P29<>"",MAX(0,P29-O29),IF(T29<>"None",MAX(1,O29-B29-2),0))) -> 0 | S29: Paid | T29: None
A30: ORD0026 | B30: 46219 | C30: CUS0119 | D30: Vivaan Das | E30: Central | F30: Raipur WH | G30: PRD026 | H30: =VLOOKUP(G30,'Product Master'!$A$5:$K$104,2,FALSE()) -> Classic Home Item 026 | I30: =VLOOKUP(G30,'Product Master'!$A$5:$K$104,3,FALSE()) -> Home & Kitchen | J30: 6 | K30: 4898.07 | L30: =J30*K30 -> 29388.42 | M30: Pending | O30: 46221 | Q30: =IF(P30<>"",MAX(1,P30-B30),IF(M30="Dispatched",MAX(1,O30-B30),0)) -> 0 | R30: =IF(M30="Cancelled",0,IF(P30<>"",MAX(0,P30-O30),IF(T30<>"None",MAX(1,O30-B30-2),0))) -> 1 | S30: Pending | T30: Warehouse backlog
A31: ORD0027 | B31: 46285 | C31: CUS0169 | D31: Kabir Iyer | E31: West | F31: Mumbai WH | G31: PRD009 | H31: =VLOOKUP(G31,'Product Master'!$A$5:$K$104,2,FALSE()) -> Essential Electronics Item 009 | I31: =VLOOKUP(G31,'Product Master'!$A$5:$K$104,3,FALSE()) -> Electronics | J31: 5 | K31: 5778.46 | L31: =J31*K31 -> 28892.3 | M31: Pending | O31: 46290 | Q31: =IF(P31<>"",MAX(1,P31-B31),IF(M31="Dispatched",MAX(1,O31-B31),0)) -> 0 | R31: =IF(M31="Cancelled",0,IF(P31<>"",MAX(0,P31-O31),IF(T31<>"None",MAX(1,O31-B31-2),0))) -> 0 | S31: Paid | T31: None
A32: ORD0028 | B32: 46124 | C32: CUS0010 | D32: Ira Iyer | E32: West | F32: Raipur WH | G32: PRD010 | H32: =VLOOKUP(G32,'Product Master'!$A$5:$K$104,2,FALSE()) -> Essential Home Item 010 | I32: =VLOOKUP(G32,'Product Master'!$A$5:$K$104,3,FALSE()) -> Home & Kitchen | J32: 16 | K32: 7388.75 | L32: =J32*K32 -> 118220 | M32: Pending | O32: 46132 | Q32: =IF(P32<>"",MAX(1,P32-B32),IF(M32="Dispatched",MAX(1,O32-B32),0)) -> 0 | R32: =IF(M32="Cancelled",0,IF(P32<>"",MAX(0,P32-O32),IF(T32<>"None",MAX(1,O32-B32-2),0))) -> 6 | S32: Partially Paid | T32: Warehouse backlog
A33: ORD0029 | B33: 46205 | C33: CUS0145 | D33: Rohan Sahu | E33: North | F33: Delhi WH | G33: PRD077 | H33: =VLOOKUP(G33,'Product Master'!$A$5:$K$104,2,FALSE()) -> Everyday Industrial Item 077 | I33: =VLOOKUP(G33,'Product Master'!$A$5:$K$104,3,FALSE()) -> Industrial | J33: 25 | K33: 3653.35 | L33: =J33*K33 -> 91333.75 | M33: Delivered | N33: 46206 | O33: 46212 | P33: 46208 | Q33: =IF(P33<>"",MAX(1,P33-B33),IF(M33="Dispatched",MAX(1,O33-B33),0)) -> 3 | R33: =IF(M33="Cancelled",0,IF(P33<>"",MAX(0,P33-O33),IF(T33<>"None",MAX(1,O33-B33-2),0))) -> 0 | S33: Paid | T33: None
A34: ORD0030 | B34: 46151 | C34: CUS0119 | D34: Kabir Rao | E34: North | F34: Delhi WH | G34: PRD014 | H34: =VLOOKUP(G34,'Product Master'!$A$5:$K$104,2,FALSE()) -> Pro Packaging Item 014 | I34: =VLOOKUP(G34,'Product Master'!$A$5:$K$104,3,FALSE()) -> Packaging | J34: 9 | K34: 4696.7 | L34: =J34*K34 -> 42270.3 | M34: Delivered | N34: 46154 | O34: 46156 | P34: 46157 | Q34: =IF(P34<>"",MAX(1,P34-B34),IF(M34="Dispatched",MAX(1,O34-B34),0)) -> 6 | R34: =IF(M34="Cancelled",0,IF(P34<>"",MAX(0,P34-O34),IF(T34<>"None",MAX(1,O34-B34-2),0))) -> 1 | S34: Refunded | T34: Weather disruption
A35: ORD0031 | B35: 46178 | C35: CUS0088 | D35: Dev Sahu | E35: East | F35: Mumbai WH | G35: PRD014 | H35: =VLOOKUP(G35,'Product Master'!$A$5:$K$104,2,FALSE()) -> Pro Packaging Item 014 | I35: =VLOOKUP(G35,'Product Master'!$A$5:$K$104,3,FALSE()) -> Packaging | J35: 3 | K35: 4696.7 | L35: =J35*K35 -> 14090.1 | M35: Delivered | N35: 46180 | O35: 46182 | P35: 46182 | Q35: =IF(P35<>"",MAX(1,P35-B35),IF(M35="Dispatched",MAX(1,O35-B35),0)) -> 4 | R35: =IF(M35="Cancelled",0,IF(P35<>"",MAX(0,P35-O35),IF(T35<>"None",MAX(1,O35-B35-2),0))) -> 0 | S35: Paid | T35: None
A36: ORD0032 | B36: 46178 | C36: CUS0018 | D36: Aditi Sharma | E36: West | F36: Delhi WH | G36: PRD045 | H36: =VLOOKUP(G36,'Product Master'!$A$5:$K$104,2,FALSE()) -> Essential Industrial Item 045 | I36: =VLOOKUP(G36,'Product Master'!$A$5:$K$104,3,FALSE()) -> Industrial | J36: 15 | K36: 9908.93 | L36: =J36*K36 -> 148633.95 | M36: Processing | O36: 46187 | Q36: =IF(P36<>"",MAX(1,P36-B36),IF(M36="Dispatched",MAX(1,O36-B36),0)) -> 0 | R36: =IF(M36="Cancelled",0,IF(P36<>"",MAX(0,P36-O36),IF(T36<>"None",MAX(1,O36-B36-2),0))) -> 7 | S36: Pending | T36: Awaiting stock
A37: ORD0033 | B37: 45989 | C37: CUS0142 | D37: Meera Rao | E37: East | F37: Delhi WH | G37: PRD003 | H37: =VLOOKUP(G37,'Product Master'!$A$5:$K$104,2,FALSE()) -> Premium Office Item 003 | I37: =VLOOKUP(G37,'Product Master'!$A$5:$K$104,3,FALSE()) -> Office Supplies | J37: 22 | K37: 1653.15 | L37: =J37*K37 -> 36369.3 | M37: Processing | O37: 45994 | Q37: =IF(P37<>"",MAX(1,P37-B37),IF(M37="Dispatched",MAX(1,O37-B37),0)) -> 0 | R37: =IF(M37="Cancelled",0,IF(P37<>"",MAX(0,P37-O37),IF(T37<>"None",MAX(1,O37-B37-2),0))) -> 0 | S37: Paid | T37: None
A38: ORD0034 | B38: 46167 | C38: CUS0008 | D38: Vivaan Das | E38: West | F38: Bengaluru WH | G38: PRD030 | H38: =VLOOKUP(G38,'Product Master'!$A$5:$K$104,2,FALSE()) -> Premium Packaging Item 030 | I38: =VLOOKUP(G38,'Product Master'!$A$5:$K$104,3,FALSE()) -> Packaging | J38: 6 | K38: 6643.61 | L38: =J38*K38 -> 39861.66 | M38: Pending | O38: 46175 | Q38: =IF(P38<>"",MAX(1,P38-B38),IF(M38="Dispatched",MAX(1,O38-B38),0)) -> 0 | R38: =IF(M38="Cancelled",0,IF(P38<>"",MAX(0,P38-O38),IF(T38<>"None",MAX(1,O38-B38-2),0))) -> 6 | S38: Paid | T38: Payment hold
A39: ORD0035 | B39: 46130 | C39: CUS0205 | D39: Meera Rao | E39: South | F39: Bengaluru WH | G39: PRD001 | H39: =VLOOKUP(G39,'Product Master'!$A$5:$K$104,2,FALSE()) -> Everyday Electronics Item 001 | I39: =VLOOKUP(G39,'Product Master'!$A$5:$K$104,3,FALSE()) -> Electronics | J39: 9 | K39: 2912.4 | L39: =J39*K39 -> 26211.6 | M39: Processing | O39: 46133 | Q39: =IF(P39<>"",MAX(1,P39-B39),IF(M39="Dispatched",MAX(1,O39-B39),0)) -> 0 | R39: =IF(M39="Cancelled",0,IF(P39<>"",MAX(0,P39-O39),IF(T39<>"None",MAX(1,O39-B39-2),0))) -> 0 | S39: Paid | T39: None
A40: ORD0036 | B40: 46165 | C40: CUS0153 | D40: Rohan Joshi | E40: East | F40: Mumbai WH | G40: PRD015 | H40: =VLOOKUP(G40,'Product Master'!$A$5:$K$104,2,FALSE()) -> Classic Apparel Item 015 | I40: =VLOOKUP(G40,'Product Master'!$A$5:$K$104,3,FALSE()) -> Apparel | J40: 17 | K40: 1631 | L40: =J40*K40 -> 27727 | M40: Cancelled | O40: 46172 | Q40: =IF(P40<>"",MAX(1,P40-B40),IF(M40="Dispatched",MAX(1,O40-B40),0)) -> 0 | R40: =IF(M40="Cancelled",0,IF(P40<>"",MAX(0,P40-O40),IF(T40<>"None",MAX(1,O40-B40-2),0))) -> 0 | S40: Paid | T40: Customer cancellation
A41: ORD0037 | B41: 45989 | C41: CUS0081 | D41: Anaya Nair | E41: East | F41: Mumbai WH | G41: PRD045 | H41: =VLOOKUP(G41,'Product Master'!$A$5:$K$104,2,FALSE()) -> Essential Industrial Item 045 | I41: =VLOOKUP(G41,'Product Master'!$A$5:$K$104,3,FALSE()) -> Industrial | J41: 20 | K41: 9908.93 | L41: =J41*K41 -> 198178.6 | M41: Delivered | N41: 45989 | O41: 45995 | P41: 45994 | Q41: =IF(P41<>"",MAX(1,P41-B41),IF(M41="Dispatched",MAX(1,O41-B41),0)) -> 5 | R41: =IF(M41="Cancelled",0,IF(P41<>"",MAX(0,P41-O41),IF(T41<>"None",MAX(1,O41-B41-2),0))) -> 0 | S41: Paid | T41: None
A42: ORD0038 | B42: 46024 | C42: CUS0125 | D42: Meera Mehta | E42: South | F42: Raipur WH | G42: PRD048 | H42: =VLOOKUP(G42,'Product Master'!$A$5:$K$104,2,FALSE()) -> Eco Automotive Item 048 | I42: =VLOOKUP(G42,'Product Master'!$A$5:$K$104,3,FALSE()) -> Automotive | J42: 13 | K42: 444.67 | L42: =J42*K42 -> 5780.71 | M42: Delivered | N42: 46027 | O42: 46028 | P42: 46030 | Q42: =IF(P42<>"",MAX(1,P42-B42),IF(M42="Dispatched",MAX(1,O42-B42),0)) -> 6 | R42: =IF(M42="Cancelled",0,IF(P42<>"",MAX(0,P42-O42),IF(T42<>"None",MAX(1,O42-B42-2),0))) -> 2 | S42: Paid | T42: Warehouse backlog
A43: ORD0039 | B43: 46078 | C43: CUS0125 | D43: Kabir Nair | E43: South | F43: Kolkata WH | G43: PRD018 | H43: =VLOOKUP(G43,'Product Master'!$A$5:$K$104,2,FALSE()) -> Smart Home Item 018 | I43: =VLOOKUP(G43,'Product Master'!$A$5:$K$104,3,FALSE()) -> Home & Kitchen | J43: 15 | K43: 5693.61 | L43: =J43*K43 -> 85404.15 | M43: Pending | O43: 46085 | Q43: =IF(P43<>"",MAX(1,P43-B43),IF(M43="Dispatched",MAX(1,O43-B43),0)) -> 0 | R43: =IF(M43="Cancelled",0,IF(P43<>"",MAX(0,P43-O43),IF(T43<>"None",MAX(1,O43-B43-2),0))) -> 0 | S43: Pending | T43: None
A44: ORD0040 | B44: 46218 | C44: CUS0022 | D44: Aarav Sahu | E44: West | F44: Mumbai WH | G44: PRD065 | H44: =VLOOKUP(G44,'Product Master'!$A$5:$K$104,2,FALSE()) -> Compact Electronics Item 065 | I44: =VLOOKUP(G44,'Product Master'!$A$5:$K$104,3,FALSE()) -> Electronics | J44: 22 | K44: 7172.77 | L44: =J44*K44 -> 157800.94 | M44: Delivered | N44: 46221 | O44: 46227 | P44: 46226 | Q44: =IF(P44<>"",MAX(1,P44-B44),IF(M44="Dispatched",MAX(1,O44-B44),0)) -> 8 | R44: =IF(M44="Cancelled",0,IF(P44<>"",MAX(0,P44-O44),IF(T44<>"None",MAX(1,O44-B44-2),0))) -> 0 | S44: Pending | T44: None
A45: ORD0041 | B45: 46080 | C45: CUS0029 | D45: Anaya Gupta | E45: East | F45: Bengaluru WH | G45: PRD005 | H45: =VLOOKUP(G45,'Product Master'!$A$5:$K$104,2,FALSE()) -> Everyday Industrial Item 005 | I45: =VLOOKUP(G45,'Product Master'!$A$5:$K$104,3,FALSE()) -> Industrial | J45: 18 | K45: 1573.69 | L45: =J45*K45 -> 28326.42 | M45: Delivered | N45: 46083 | O45: 46089 | P45: 46097 | Q45: =IF(P45<>"",MAX(1,P45-B45),IF(M45="Dispatched",MAX(1,O45-B45),0)) -> 17 | R45: =IF(M45="Cancelled",0,IF(P45<>"",MAX(0,P45-O45),IF(T45<>"None",MAX(1,O45-B45-2),0))) -> 8 | S45: Pending | T45: Address issue
A46: ORD0042 | B46: 46118 | C46: CUS0077 | D46: Diya Das | E46: North | F46: Mumbai WH | G46: PRD070 | H46: =VLOOKUP(G46,'Product Master'!$A$5:$K$104,2,FALSE()) -> Eco Packaging Item 070 | I46: =VLOOKUP(G46,'Product Master'!$A$5:$K$104,3,FALSE()) -> Packaging | J46: 18 | K46: 6067.79 | L46: =J46*K46 -> 109220.22 | M46: Delivered | N46: 46118 | O46: 46126 | P46: 46126 | Q46: =IF(P46<>"",MAX(1,P46-B46),IF(M46="Dispatched",MAX(1,O46-B46),0)) -> 8 | R46: =IF(M46="Cancelled",0,IF(P46<>"",MAX(0,P46-O46),IF(T46<>"None",MAX(1,O46-B46-2),0))) -> 0 | S46: Paid | T46: None
A47: ORD0043 | B47: 45975 | C47: CUS0043 | D47: Kabir Sahu | E47: North | F47: Bengaluru WH | G47: PRD057 | H47: =VLOOKUP(G47,'Product Master'!$A$5:$K$104,2,FALSE()) -> Essential Electronics Item 057 | I47: =VLOOKUP(G47,'Product Master'!$A$5:$K$104,3,FALSE()) -> Electronics | J47: 7 | K47: 8152.77 | L47: =J47*K47 -> 57069.39 | M47: Processing | O47: 45982 | Q47: =IF(P47<>"",MAX(1,P47-B47),IF(M47="Dispatched",MAX(1,O47-B47),0)) -> 0 | R47: =IF(M47="Cancelled",0,IF(P47<>"",MAX(0,P47-O47),IF(T47<>"None",MAX(1,O47-B47-2),0))) -> 0 | S47: Paid | T47: None
A48: ORD0044 | B48: 46036 | C48: CUS0075 | D48: Arjun Mishra | E48: Central | F48: Kolkata WH | G48: PRD008 | H48: =VLOOKUP(G48,'Product Master'!$A$5:$K$104,2,FALSE()) -> Smart Automotive Item 008 | I48: =VLOOKUP(G48,'Product Master'!$A$5:$K$104,3,FALSE()) -> Automotive | J48: 18 | K48: 8489.02 | L48: =J48*K48 -> 152802.36 | M48: Delivered | N48: 46038 | O48: 46040 | P48: 46040 | Q48: =IF(P48<>"",MAX(1,P48-B48),IF(M48="Dispatched",MAX(1,O48-B48),0)) -> 4 | R48: =IF(M48="Cancelled",0,IF(P48<>"",MAX(0,P48-O48),IF(T48<>"None",MAX(1,O48-B48-2),0))) -> 0 | S48: Paid | T48: None
A49: ORD0045 | B49: 46278 | C49: CUS0180 | D49: Kabir Nair | E49: South | F49: Mumbai WH | G49: PRD013 | H49: =VLOOKUP(G49,'Product Master'!$A$5:$K$104,2,FALSE()) -> Eco Industrial Item 013 | I49: =VLOOKUP(G49,'Product Master'!$A$5:$K$104,3,FALSE()) -> Industrial | J49: 2 | K49: 12957.77 | L49: =J49*K49 -> 25915.54 | M49: Cancelled | O49: 46282 | Q49: =IF(P49<>"",MAX(1,P49-B49),IF(M49="Dispatched",MAX(1,O49-B49),0)) -> 0 | R49: =IF(M49="Cancelled",0,IF(P49<>"",MAX(0,P49-O49),IF(T49<>"None",MAX(1,O49-B49-2),0))) -> 0 | S49: Paid | T49: Customer cancellation
A50: ORD0046 | B50: 46095 | C50: CUS0020 | D50: Ishaan Singh | E50: West | F50: Mumbai WH | G50: PRD032 | H50: =VLOOKUP(G50,'Product Master'!$A$5:$K$104,2,FALSE()) -> Smart Automotive Item 032 | I50: =VLOOKUP(G50,'Product Master'!$A$5:$K$104,3,FALSE()) -> Automotive | J50: 5 | K50: 10211.16 | L50: =J50*K50 -> 51055.8 | M50: Delivered | N50: 46098 | O50: 46101 | P50: 46103 | Q50: =IF(P50<>"",MAX(1,P50-B50),IF(M50="Dispatched",MAX(1,O50-B50),0)) -> 8 | R50: =IF(M50="Cancelled",0,IF(P50<>"",MAX(0,P50-O50),IF(T50<>"None",MAX(1,O50-B50-2),0))) -> 2 | S50: Paid | T50: Weather disruption
A51: ORD0047 | B51: 46073 | C51: CUS0218 | D51: Ishaan Sahu | E51: East | F51: Mumbai WH | G51: PRD089 | H51: =VLOOKUP(G51,'Product Master'!$A$5:$K$104,2,FALSE()) -> Everyday Electronics Item 089 | I51: =VLOOKUP(G51,'Product Master'!$A$5:$K$104,3,FALSE()) -> Electronics | J51: 16 | K51: 2282.32 | L51: =J51*K51 -> 36517.12 | M51: Delivered | N51: 46073 | O51: 46075 | P51: 46079 | Q51: =IF(P51<>"",MAX(1,P51-B51),IF(M51="Dispatched",MAX(1,O51-B51),0)) -> 6 | R51: =IF(M51="Cancelled",0,IF(P51<>"",MAX(0,P51-O51),IF(T51<>"None",MAX(1,O51-B51-2),0))) -> 4 | S51: Paid | T51: Supplier delay
A52: ORD0048 | B52: 46042 | C52: CUS0034 | D52: Myra Sahu | E52: South | F52: Mumbai WH | G52: PRD055 | H52: =VLOOKUP(G52,'Product Master'!$A$5:$K$104,2,FALSE()) -> Eco Apparel Item 055 | I52: =VLOOKUP(G52,'Product Master'!$A$5:$K$104,3,FALSE()) -> Apparel | J52: 9 | K52: 3025.58 | L52: =J52*K52 -> 27230.22 | M52: Delivered | N52: 46044 | O52: 46048 | P52: 46056 | Q52: =IF(P52<>"",MAX(1,P52-B52),IF(M52="Dispatched",MAX(1,O52-B52),0)) -> 14 | R52: =IF(M52="Cancelled",0,IF(P52<>"",MAX(0,P52-O52),IF(T52<>"None",MAX(1,O52-B52-2),0))) -> 8 | S52: Paid | T52: Address issue
A53: ORD0049 | B53: 46280 | C53: CUS0032 | D53: Meera Das | E53: North | F53: Delhi WH | G53: PRD098 | H53: =VLOOKUP(G53,'Product Master'!$A$5:$K$104,2,FALSE()) -> Compact Home Item 098 | I53: =VLOOKUP(G53,'Product Master'!$A$5:$K$104,3,FALSE()) -> Home & Kitchen | J53: 4 | K53: 9200.31 | L53: =J53*K53 -> 36801.24 | M53: Pending | O53: 46289 | Q53: =IF(P53<>"",MAX(1,P53-B53),IF(M53="Dispatched",MAX(1,O53-B53),0)) -> 0 | R53: =IF(M53="Cancelled",0,IF(P53<>"",MAX(0,P53-O53),IF(T53<>"None",MAX(1,O53-B53-2),0))) -> 0 | S53: Paid | T53: None
A54: ORD0050 | B54: 46150 | C54: CUS0168 | D54: Ira Gupta | E54: South | F54: Kolkata WH | G54: PRD026 | H54: =VLOOKUP(G54,'Product Master'!$A$5:$K$104,2,FALSE()) -> Classic Home Item 026 | I54: =VLOOKUP(G54,'Product Master'!$A$5:$K$104,3,FALSE()) -> Home & Kitchen | J54: 6 | K54: 4898.07 | L54: =J54*K54 -> 29388.42 | M54: Dispatched | N54: 46150 | O54: 46156 | Q54: =IF(P54<>"",MAX(1,P54-B54),IF(M54="Dispatched",MAX(1,O54-B54),0)) -> 6 | R54: =IF(M54="Cancelled",0,IF(P54<>"",MAX(0,P54-O54),IF(T54<>"None",MAX(1,O54-B54-2),0))) -> 4 | S54: Paid | T54: Carrier delay
A55: ORD0051 | B55: 46271 | C55: CUS0168 | D55: Ishaan Iyer | E55: South | F55: Delhi WH | G55: PRD084 | H55: =VLOOKUP(G55,'Product Master'!$A$5:$K$104,2,FALSE()) -> Eco Personal Item 084 | I55: =VLOOKUP(G55,'Product Master'!$A$5:$K$104,3,FALSE()) -> Personal Care | J55: 13 | K55: 4628.26 | L55: =J55*K55 -> 60167.38 | M55: Pending | O55: 46276 | Q55: =IF(P55<>"",MAX(1,P55-B55),IF(M55="Dispatched",MAX(1,O55-B55),0)) -> 0 | R55: =IF(M55="Cancelled",0,IF(P55<>"",MAX(0,P55-O55),IF(T55<>"None",MAX(1,O55-B55-2),0))) -> 0 | S55: Paid | T55: None
A56: ORD0052 | B56: 46040 | C56: CUS0179 | D56: Reyansh Mishra | E56: North | F56: Bengaluru WH | G56: PRD062 | H56: =VLOOKUP(G56,'Product Master'!$A$5:$K$104,2,FALSE()) -> Compact Packaging Item 062 | I56: =VLOOKUP(G56,'Product Master'!$A$5:$K$104,3,FALSE()) -> Packaging | J56: 19 | K56: 10323.31 | L56: =J56*K56 -> 196142.89 | M56: Delivered | N56: 46040 | O56: 46049 | P56: 46045 | Q56: =IF(P56<>"",MAX(1,P56-B56),IF(M56="Dispatched",MAX(1,O56-B56),0)) -> 5 | R56: =IF(M56="Cancelled",0,IF(P56<>"",MAX(0,P56-O56),IF(T56<>"None",MAX(1,O56-B56-2),0))) -> 0 | S56: Paid | T56: None
A57: ORD0053 | B57: 46147 | C57: CUS0081 | D57: Ira Gupta | E57: South | F57: Mumbai WH | G57: PRD089 | H57: =VLOOKUP(G57,'Product Master'!$A$5:$K$104,2,FALSE()) -> Everyday Electronics Item 089 | I57: =VLOOKUP(G57,'Product Master'!$A$5:$K$104,3,FALSE()) -> Electronics | J57: 3 | K57: 2282.32 | L57: =J57*K57 -> 6846.96 | M57: Delivered | N57: 46147 | O57: 46150 | P57: 46148 | Q57: =IF(P57<>"",MAX(1,P57-B57),IF(M57="Dispatched",MAX(1,O57-B57),0)) -> 1 | R57: =IF(M57="Cancelled",0,IF(P57<>"",MAX(0,P57-O57),IF(T57<>"None",MAX(1,O57-B57-2),0))) -> 0 | S57: Paid | T57: None
A58: ORD0054 | B58: 45999 | C58: CUS0161 | D58: Kabir Singh | E58: South | F58: Delhi WH | G58: PRD083 | H58: =VLOOKUP(G58,'Product Master'!$A$5:$K$104,2,FALSE()) -> Essential Office Item 083 | I58: =VLOOKUP(G58,'Product Master'!$A$5:$K$104,3,FALSE()) -> Office Supplies | J58: 17 | K58: 4117.89 | L58: =J58*K58 -> 70004.13 | M58: Delivered | N58: 46002 | O58: 46003 | P58: 46004 | Q58: =IF(P58<>"",MAX(1,P58-B58),IF(M58="Dispatched",MAX(1,O58-B58),0)) -> 5 | R58: =IF(M58="Cancelled",0,IF(P58<>"",MAX(0,P58-O58),IF(T58<>"None",MAX(1,O58-B58-2),0))) -> 1 | S58: Paid | T58: Warehouse backlog
A59: ORD0055 | B59: 46157 | C59: CUS0110 | D59: Reyansh Sahu | E59: North | F59: Delhi WH | G59: PRD028 | H59: =VLOOKUP(G59,'Product Master'!$A$5:$K$104,2,FALSE()) -> Pro Personal Item 028 | I59: =VLOOKUP(G59,'Product Master'!$A$5:$K$104,3,FALSE()) -> Personal Care | J59: 5 | K59: 2131.21 | L59: =J59*K59 -> 10656.05 | M59: Processing | O59: 46165 | Q59: =IF(P59<>"",MAX(1,P59-B59),IF(M59="Dispatched",MAX(1,O59-B59),0)) -> 0 | R59: =IF(M59="Cancelled",0,IF(P59<>"",MAX(0,P59-O59),IF(T59<>"None",MAX(1,O59-B59-2),0))) -> 0 | S59: Paid | T59: None
A60: ORD0056 | B60: 46072 | C60: CUS0007 | D60: Aditi Nair | E60: North | F60: Bengaluru WH | G60: PRD083 | H60: =VLOOKUP(G60,'Product Master'!$A$5:$K$104,2,FALSE()) -> Essential Office Item 083 | I60: =VLOOKUP(G60,'Product Master'!$A$5:$K$104,3,FALSE()) -> Office Supplies | J60: 18 | K60: 4117.89 | L60: =J60*K60 -> 74122.02 | M60: Pending | O60: 46078 | Q60: =IF(P60<>"",MAX(1,P60-B60),IF(M60="Dispatched",MAX(1,O60-B60),0)) -> 0 | R60: =IF(M60="Cancelled",0,IF(P60<>"",MAX(0,P60-O60),IF(T60<>"None",MAX(1,O60-B60-2),0))) -> 4 | S60: Paid | T60: Warehouse backlog
A61: ORD0057 | B61: 46191 | C61: CUS0062 | D61: Myra Khan | E61: West | F61: Kolkata WH | G61: PRD025 | H61: =VLOOKUP(G61,'Product Master'!$A$5:$K$104,2,FALSE()) -> Pro Electronics Item 025 | I61: =VLOOKUP(G61,'Product Master'!$A$5:$K$104,3,FALSE()) -> Electronics | J61: 21 | K61: 9400.79 | L61: =J61*K61 -> 197416.59 | M61: Delivered | N61: 46194 | O61: 46196 | P61: 46198 | Q61: =IF(P61<>"",MAX(1,P61-B61),IF(M61="Dispatched",MAX(1,O61-B61),0)) -> 7 | R61: =IF(M61="Cancelled",0,IF(P61<>"",MAX(0,P61-O61),IF(T61<>"None",MAX(1,O61-B61-2),0))) -> 2 | S61: Paid | T61: Carrier delay
A62: ORD0058 | B62: 46201 | C62: CUS0196 | D62: Myra Sahu | E62: East | F62: Kolkata WH | G62: PRD002 | H62: =VLOOKUP(G62,'Product Master'!$A$5:$K$104,2,FALSE()) -> Premium Home Item 002 | I62: =VLOOKUP(G62,'Product Master'!$A$5:$K$104,3,FALSE()) -> Home & Kitchen | J62: 5 | K62: 9429.37 | L62: =J62*K62 -> 47146.85 | M62: Delivered | N62: 46203 | O62: 46209 | P62: 46217 | Q62: =IF(P62<>"",MAX(1,P62-B62),IF(M62="Dispatched",MAX(1,O62-B62),0)) -> 16 | R62: =IF(M62="Cancelled",0,IF(P62<>"",MAX(0,P62-O62),IF(T62<>"None",MAX(1,O62-B62-2),0))) -> 8 | S62: Paid | T62: Warehouse backlog
A63: ORD0059 | B63: 46231 | C63: CUS0161 | D63: Kiara Singh | E63: North | F63: Kolkata WH | G63: PRD009 | H63: =VLOOKUP(G63,'Product Master'!$A$5:$K$104,2,FALSE()) -> Essential Electronics Item 009 | I63: =VLOOKUP(G63,'Product Master'!$A$5:$K$104,3,FALSE()) -> Electronics | J63: 7 | K63: 5778.46 | L63: =J63*K63 -> 40449.22 | M63: Delivered | N63: 46234 | O63: 46238 | P63: 46241 | Q63: =IF(P63<>"",MAX(1,P63-B63),IF(M63="Dispatched",MAX(1,O63-B63),0)) -> 10 | R63: =IF(M63="Cancelled",0,IF(P63<>"",MAX(0,P63-O63),IF(T63<>"None",MAX(1,O63-B63-2),0))) -> 3 | S63: Pending | T63: Supplier delay
A64: ORD0060 | B64: 45973 | C64: CUS0131 | D64: Vivaan Sahu | E64: Central | F64: Raipur WH | G64: PRD082 | H64: =VLOOKUP(G64,'Product Master'!$A$5:$K$104,2,FALSE()) -> Compact Home Item 082 | I64: =VLOOKUP(G64,'Product Master'!$A$5:$K$104,3,FALSE()) -> Home & Kitchen | J64: 20 | K64: 3454.52 | L64: =J64*K64 -> 69090.4 | M64: Delivered | N64: 45975 | O64: 45976 | P64: 45976 | Q64: =IF(P64<>"",MAX(1,P64-B64),IF(M64="Dispatched",MAX(1,O64-B64),0)) -> 3 | R64: =IF(M64="Cancelled",0,IF(P64<>"",MAX(0,P64-O64),IF(T64<>"None",MAX(1,O64-B64-2),0))) -> 0 | S64: Paid | T64: None
A65: ORD0061 | B65: 46098 | C65: CUS0063 | D65: Ishaan Singh | E65: Central | F65: Delhi WH | G65: PRD051 | H65: =VLOOKUP(G65,'Product Master'!$A$5:$K$104,2,FALSE()) -> Classic Office Item 051 | I65: =VLOOKUP(G65,'Product Master'!$A$5:$K$104,3,FALSE()) -> Office Supplies | J65: 10 | K65: 4705.56 | L65: =J65*K65 -> 47055.6 | M65: Pending | O65: 46103 | Q65: =IF(P65<>"",MAX(1,P65-B65),IF(M65="Dispatched",MAX(1,O65-B65),0)) -> 0 | R65: =IF(M65="Cancelled",0,IF(P65<>"",MAX(0,P65-O65),IF(T65<>"None",MAX(1,O65-B65-2),0))) -> 0 | S65: Paid | T65: None
A66: ORD0062 | B66: 46244 | C66: CUS0004 | D66: Kabir Iyer | E66: North | F66: Kolkata WH | G66: PRD078 | H66: =VLOOKUP(G66,'Product Master'!$A$5:$K$104,2,FALSE()) -> Smart Packaging Item 078 | I66: =VLOOKUP(G66,'Product Master'!$A$5:$K$104,3,FALSE()) -> Packaging | J66: 22 | K66: 627.95 | L66: =J66*K66 -> 13814.9 | M66: Processing | O66: 46248 | Q66: =IF(P66<>"",MAX(1,P66-B66),IF(M66="Dispatched",MAX(1,O66-B66),0)) -> 0 | R66: =IF(M66="Cancelled",0,IF(P66<>"",MAX(0,P66-O66),IF(T66<>"None",MAX(1,O66-B66-2),0))) -> 2 | S66: Paid | T66: Warehouse backlog
A67: ORD0063 | B67: 46185 | C67: CUS0188 | D67: Anaya Sahu | E67: Central | F67: Raipur WH | G67: PRD045 | H67: =VLOOKUP(G67,'Product Master'!$A$5:$K$104,2,FALSE()) -> Essential Industrial Item 045 | I67: =VLOOKUP(G67,'Product Master'!$A$5:$K$104,3,FALSE()) -> Industrial | J67: 24 | K67: 9908.93 | L67: =J67*K67 -> 237814.32 | M67: Delivered | N67: 46186 | O67: 46192 | P67: 46192 | Q67: =IF(P67<>"",MAX(1,P67-B67),IF(M67="Dispatched",MAX(1,O67-B67),0)) -> 7 | R67: =IF(M67="Cancelled",0,IF(P67<>"",MAX(0,P67-O67),IF(T67<>"None",MAX(1,O67-B67-2),0))) -> 0 | S67: Partially Paid | T67: None
A68: ORD0064 | B68: 46102 | C68: CUS0093 | D68: Diya Das | E68: East | F68: Raipur WH | G68: PRD055 | H68: =VLOOKUP(G68,'Product Master'!$A$5:$K$104,2,FALSE()) -> Eco Apparel Item 055 | I68: =VLOOKUP(G68,'Product Master'!$A$5:$K$104,3,FALSE()) -> Apparel | J68: 3 | K68: 3025.58 | L68: =J68*K68 -> 9076.74 | M68: Delivered | N68: 46105 | O68: 46105 | P68: 46109 | Q68: =IF(P68<>"",MAX(1,P68-B68),IF(M68="Dispatched",MAX(1,O68-B68),0)) -> 7 | R68: =IF(M68="Cancelled",0,IF(P68<>"",MAX(0,P68-O68),IF(T68<>"None",MAX(1,O68-B68-2),0))) -> 4 | S68: Partially Paid | T68: Address issue
A69: ORD0065 | B69: 46016 | C69: CUS0012 | D69: Aarav Nair | E69: South | F69: Kolkata WH | G69: PRD048 | H69: =VLOOKUP(G69,'Product Master'!$A$5:$K$104,2,FALSE()) -> Eco Automotive Item 048 | I69: =VLOOKUP(G69,'Product Master'!$A$5:$K$104,3,FALSE()) -> Automotive | J69: 25 | K69: 444.67 | L69: =J69*K69 -> 11116.75 | M69: Delivered | N69: 46017 | O69: 46019 | P69: 46027 | Q69: =IF(P69<>"",MAX(1,P69-B69),IF(M69="Dispatched",MAX(1,O69-B69),0)) -> 11 | R69: =IF(M69="Cancelled",0,IF(P69<>"",MAX(0,P69-O69),IF(T69<>"None",MAX(1,O69-B69-2),0))) -> 8 | S69: Paid | T69: Carrier delay
A70: ORD0066 | B70: 46117 | C70: CUS0107 | D70: Reyansh Gupta | E70: South | F70: Bengaluru WH | G70: PRD050 | H70: =VLOOKUP(G70,'Product Master'!$A$5:$K$104,2,FALSE()) -> Eco Home Item 050 | I70: =VLOOKUP(G70,'Product Master'!$A$5:$K$104,3,FALSE()) -> Home & Kitchen | J70: 2 | K70: 5831.62 | L70: =J70*K70 -> 11663.24 | M70: Delivered | N70: 46118 | O70: 46125 | P70: 46126 | Q70: =IF(P70<>"",MAX(1,P70-B70),IF(M70="Dispatched",MAX(1,O70-B70),0)) -> 9 | R70: =IF(M70="Cancelled",0,IF(P70<>"",MAX(0,P70-O70),IF(T70<>"None",MAX(1,O70-B70-2),0))) -> 1 | S70: Pending | T70: Warehouse backlog
A71: ORD0067 | B71: 46223 | C71: CUS0206 | D71: Diya Singh | E71: North | F71: Raipur WH | G71: PRD048 | H71: =VLOOKUP(G71,'Product Master'!$A$5:$K$104,2,FALSE()) -> Eco Automotive Item 048 | I71: =VLOOKUP(G71,'Product Master'!$A$5:$K$104,3,FALSE()) -> Automotive | J71: 22 | K71: 444.67 | L71: =J71*K71 -> 9782.74 | M71: Dispatched | N71: 46224 | O71: 46227 | Q71: =IF(P71<>"",MAX(1,P71-B71),IF(M71="Dispatched",MAX(1,O71-B71),0)) -> 4 | R71: =IF(M71="Cancelled",0,IF(P71<>"",MAX(0,P71-O71),IF(T71<>"None",MAX(1,O71-B71-2),0))) -> 0 | S71: Paid | T71: None
A72: ORD0068 | B72: 46169 | C72: CUS0075 | D72: Aditi Iyer | E72: East | F72: Kolkata WH | G72: PRD037 | H72: =VLOOKUP(G72,'Product Master'!$A$5:$K$104,2,FALSE()) -> Pro Industrial Item 037 | I72: =VLOOKUP(G72,'Product Master'!$A$5:$K$104,3,FALSE()) -> Industrial | J72: 3 | K72: 6419.17 | L72: =J72*K72 -> 19257.51 | M72: Delivered | N72: 46171 | O72: 46171 | P72: 46171 | Q72: =IF(P72<>"",MAX(1,P72-B72),IF(M72="Dispatched",MAX(1,O72-B72),0)) -> 2 | R72: =IF(M72="Cancelled",0,IF(P72<>"",MAX(0,P72-O72),IF(T72<>"None",MAX(1,O72-B72-2),0))) -> 0 | S72: Paid | T72: None
A73: ORD0069 | B73: 46168 | C73: CUS0002 | D73: Kiara Sharma | E73: Central | F73: Mumbai WH | G73: PRD048 | H73: =VLOOKUP(G73,'Product Master'!$A$5:$K$104,2,FALSE()) -> Eco Automotive Item 048 | I73: =VLOOKUP(G73,'Product Master'!$A$5:$K$104,3,FALSE()) -> Automotive | J73: 25 | K73: 444.67 | L73: =J73*K73 -> 11116.75 | M73: Processing | O73: 46173 | Q73: =IF(P73<>"",MAX(1,P73-B73),IF(M73="Dispatched",MAX(1,O73-B73),0)) -> 0 | R73: =IF(M73="Cancelled",0,IF(P73<>"",MAX(0,P73-O73),IF(T73<>"None",MAX(1,O73-B73-2),0))) -> 0 | S73: Paid | T73: None
A74: ORD0070 | B74: 46108 | C74: CUS0027 | D74: Vivaan Mehta | E74: North | F74: Kolkata WH | G74: PRD082 | H74: =VLOOKUP(G74,'Product Master'!$A$5:$K$104,2,FALSE()) -> Compact Home Item 082 | I74: =VLOOKUP(G74,'Product Master'!$A$5:$K$104,3,FALSE()) -> Home & Kitchen | J74: 1 | K74: 3454.52 | L74: =J74*K74 -> 3454.52 | M74: Processing | O74: 46116 | Q74: =IF(P74<>"",MAX(1,P74-B74),IF(M74="Dispatched",MAX(1,O74-B74),0)) -> 0 | R74: =IF(M74="Cancelled",0,IF(P74<>"",MAX(0,P74-O74),IF(T74<>"None",MAX(1,O74-B74-2),0))) -> 6 | S74: Refunded | T74: Awaiting stock
A75: ORD0071 | B75: 46145 | C75: CUS0180 | D75: Ira Das | E75: North | F75: Bengaluru WH | G75: PRD063 | H75: =VLOOKUP(G75,'Product Master'!$A$5:$K$104,2,FALSE()) -> Everyday Apparel Item 063 | I75: =VLOOKUP(G75,'Product Master'!$A$5:$K$104,3,FALSE()) -> Apparel | J75: 23 | K75: 3551.07 | L75: =J75*K75 -> 81674.61 | M75: Delivered | N75: 46146 | O75: 46147 | P75: 46155 | Q75: =IF(P75<>"",MAX(1,P75-B75),IF(M75="Dispatched",MAX(1,O75-B75),0)) -> 10 | R75: =IF(M75="Cancelled",0,IF(P75<>"",MAX(0,P75-O75),IF(T75<>"None",MAX(1,O75-B75-2),0))) -> 8 | S75: Refunded | T75: Weather disruption
A76: ORD0072 | B76: 45974 | C76: CUS0152 | D76: Diya Singh | E76: North | F76: Raipur WH | G76: PRD075 | H76: =VLOOKUP(G76,'Product Master'!$A$5:$K$104,2,FALSE()) -> Everyday Office Item 075 | I76: =VLOOKUP(G76,'Product Master'!$A$5:$K$104,3,FALSE()) -> Office Supplies | J76: 5 | K76: 6952.03 | L76: =J76*K76 -> 34760.15 | M76: Pending | O76: 45982 | Q76: =IF(P76<>"",MAX(1,P76-B76),IF(M76="Dispatched",MAX(1,O76-B76),0)) -> 0 | R76: =IF(M76="Cancelled",0,IF(P76<>"",MAX(0,P76-O76),IF(T76<>"None",MAX(1,O76-B76-2),0))) -> 6 | S76: Paid | T76: Awaiting stock
A77: ORD0073 | B77: 45997 | C77: CUS0180 | D77: Reyansh Rao | E77: East | F77: Kolkata WH | G77: PRD031 | H77: =VLOOKUP(G77,'Product Master'!$A$5:$K$104,2,FALSE()) -> Essential Apparel Item 031 | I77: =VLOOKUP(G77,'Product Master'!$A$5:$K$104,3,FALSE()) -> Apparel | J77: 11 | K77: 11597.85 | L77: =J77*K77 -> 127576.35 | M77: Cancelled | O77: 46005 | Q77: =IF(P77<>"",MAX(1,P77-B77),IF(M77="Dispatched",MAX(1,O77-B77),0)) -> 0 | R77: =IF(M77="Cancelled",0,IF(P77<>"",MAX(0,P77-O77),IF(T77<>"None",MAX(1,O77-B77-2),0))) -> 0 | S77: Paid | T77: Customer cancellation
A78: ORD0074 | B78: 46050 | C78: CUS0028 | D78: Meera Das | E78: South | F78: Bengaluru WH | G78: PRD010 | H78: =VLOOKUP(G78,'Product Master'!$A$5:$K$104,2,FALSE()) -> Essential Home Item 010 | I78: =VLOOKUP(G78,'Product Master'!$A$5:$K$104,3,FALSE()) -> Home & Kitchen | J78: 25 | K78: 7388.75 | L78: =J78*K78 -> 184718.75 | M78: Processing | O78: 46053 | Q78: =IF(P78<>"",MAX(1,P78-B78),IF(M78="Dispatched",MAX(1,O78-B78),0)) -> 0 | R78: =IF(M78="Cancelled",0,IF(P78<>"",MAX(0,P78-O78),IF(T78<>"None",MAX(1,O78-B78-2),0))) -> 1 | S78: Paid | T78: Warehouse backlog
A79: ORD0075 | B79: 46139 | C79: CUS0219 | D79: Anaya Patel | E79: Central | F79: Kolkata WH | G79: PRD016 | H79: =VLOOKUP(G79,'Product Master'!$A$5:$K$104,2,FALSE()) -> Pro Automotive Item 016 | I79: =VLOOKUP(G79,'Product Master'!$A$5:$K$104,3,FALSE()) -> Automotive | J79: 25 | K79: 5263.77 | L79: =J79*K79 -> 131594.25 | M79: Delivered | N79: 46142 | O79: 46145 | P79: 46145 | Q79: =IF(P79<>"",MAX(1,P79-B79),IF(M79="Dispatched",MAX(1,O79-B79),0)) -> 6 | R79: =IF(M79="Cancelled",0,IF(P79<>"",MAX(0,P79-O79),IF(T79<>"None",MAX(1,O79-B79-2),0))) -> 0 | S79: Paid | T79: None
A80: ORD0076 | B80: 46282 | C80: CUS0024 | D80: Saanvi Rao | E80: Central | F80: Delhi WH | G80: PRD039 | H80: =VLOOKUP(G80,'Product Master'!$A$5:$K$104,2,FALSE()) -> Eco Apparel Item 039 | I80: =VLOOKUP(G80,'Product Master'!$A$5:$K$104,3,FALSE()) -> Apparel | J80: 7 | K80: 3575.06 | L80: =J80*K80 -> 25025.42 | M80: Dispatched | N80: 46283 | O80: 46289 | Q80: =IF(P80<>"",MAX(1,P80-B80),IF(M80="Dispatched",MAX(1,O80-B80),0)) -> 7 | R80: =IF(M80="Cancelled",0,IF(P80<>"",MAX(0,P80-O80),IF(T80<>"None",MAX(1,O80-B80-2),0))) -> 0 | S80: Paid | T80: None
A81: ORD0077 | B81: 45956 | C81: CUS0064 | D81: Anaya Das | E81: East | F81: Kolkata WH | G81: PRD087 | H81: =VLOOKUP(G81,'Product Master'!$A$5:$K$104,2,FALSE()) -> Compact Apparel Item 087 | I81: =VLOOKUP(G81,'Product Master'!$A$5:$K$104,3,FALSE()) -> Apparel | J81: 6 | K81: 8400.02 | L81: =J81*K81 -> 50400.12 | M81: Delivered | N81: 45959 | O81: 45964 | P81: 45972 | Q81: =IF(P81<>"",MAX(1,P81-B81),IF(M81="Dispatched",MAX(1,O81-B81),0)) -> 16 | R81: =IF(M81="Cancelled",0,IF(P81<>"",MAX(0,P81-O81),IF(T81<>"None",MAX(1,O81-B81-2),0))) -> 8 | S81: Paid | T81: Address issue
A82: ORD0078 | B82: 46002 | C82: CUS0051 | D82: Rohan Rao | E82: North | F82: Delhi WH | G82: PRD016 | H82: =VLOOKUP(G82,'Product Master'!$A$5:$K$104,2,FALSE()) -> Pro Automotive Item 016 | I82: =VLOOKUP(G82,'Product Master'!$A$5:$K$104,3,FALSE()) -> Automotive | J82: 25 | K82: 5263.77 | L82: =J82*K82 -> 131594.25 | M82: Cancelled | O82: 46006 | Q82: =IF(P82<>"",MAX(1,P82-B82),IF(M82="Dispatched",MAX(1,O82-B82),0)) -> 0 | R82: =IF(M82="Cancelled",0,IF(P82<>"",MAX(0,P82-O82),IF(T82<>"None",MAX(1,O82-B82-2),0))) -> 0 | S82: Paid | T82: Customer cancellation
A83: ORD0079 | B83: 46261 | C83: CUS0017 | D83: Vivaan Khan | E83: Central | F83: Raipur WH | G83: PRD011 | H83: =VLOOKUP(G83,'Product Master'!$A$5:$K$104,2,FALSE()) -> Essential Office Item 011 | I83: =VLOOKUP(G83,'Product Master'!$A$5:$K$104,3,FALSE()) -> Office Supplies | J83: 9 | K83: 635.87 | L83: =J83*K83 -> 5722.83 | M83: Dispatched | N83: 46261 | O83: 46264 | Q83: =IF(P83<>"",MAX(1,P83-B83),IF(M83="Dispatched",MAX(1,O83-B83),0)) -> 3 | R83: =IF(M83="Cancelled",0,IF(P83<>"",MAX(0,P83-O83),IF(T83<>"None",MAX(1,O83-B83-2),0))) -> 0 | S83: Paid | T83: None
A84: ORD0080 | B84: 45996 | C84: CUS0044 | D84: Kiara Mishra | E84: East | F84: Delhi WH | G84: PRD012 | H84: =VLOOKUP(G84,'Product Master'!$A$5:$K$104,2,FALSE()) -> Eco Personal Item 012 | I84: =VLOOKUP(G84,'Product Master'!$A$5:$K$104,3,FALSE()) -> Personal Care | J84: 2 | K84: 7685.49 | L84: =J84*K84 -> 15370.98 | M84: Cancelled | O84: 45998 | Q84: =IF(P84<>"",MAX(1,P84-B84),IF(M84="Dispatched",MAX(1,O84-B84),0)) -> 0 | R84: =IF(M84="Cancelled",0,IF(P84<>"",MAX(0,P84-O84),IF(T84<>"None",MAX(1,O84-B84-2),0))) -> 0 | S84: Pending | T84: Customer cancellation
A85: ORD0081 | B85: 46185 | C85: CUS0115 | D85: Kabir Sharma | E85: West | F85: Mumbai WH | G85: PRD004 | H85: =VLOOKUP(G85,'Product Master'!$A$5:$K$104,2,FALSE()) -> Everyday Personal Item 004 | I85: =VLOOKUP(G85,'Product Master'!$A$5:$K$104,3,FALSE()) -> Personal Care | J85: 6 | K85: 5442.69 | L85: =J85*K85 -> 32656.14 | M85: Delivered | N85: 46187 | O85: 46189 | P85: 46189 | Q85: =IF(P85<>"",MAX(1,P85-B85),IF(M85="Dispatched",MAX(1,O85-B85),0)) -> 4 | R85: =IF(M85="Cancelled",0,IF(P85<>"",MAX(0,P85-O85),IF(T85<>"None",MAX(1,O85-B85-2),0))) -> 0 | S85: Paid | T85: None
A86: ORD0082 | B86: 46246 | C86: CUS0023 | D86: Arjun Singh | E86: East | F86: Mumbai WH | G86: PRD032 | H86: =VLOOKUP(G86,'Product Master'!$A$5:$K$104,2,FALSE()) -> Smart Automotive Item 032 | I86: =VLOOKUP(G86,'Product Master'!$A$5:$K$104,3,FALSE()) -> Automotive | J86: 14 | K86: 10211.16 | L86: =J86*K86 -> 142956.24 | M86: Dispatched | N86: 46246 | O86: 46255 | Q86: =IF(P86<>"",MAX(1,P86-B86),IF(M86="Dispatched",MAX(1,O86-B86),0)) -> 9 | R86: =IF(M86="Cancelled",0,IF(P86<>"",MAX(0,P86-O86),IF(T86<>"None",MAX(1,O86-B86-2),0))) -> 0 | S86: Paid | T86: None
A87: ORD0083 | B87: 46033 | C87: CUS0098 | D87: Ira Das | E87: Central | F87: Bengaluru WH | G87: PRD083 | H87: =VLOOKUP(G87,'Product Master'!$A$5:$K$104,2,FALSE()) -> Essential Office Item 083 | I87: =VLOOKUP(G87,'Product Master'!$A$5:$K$104,3,FALSE()) -> Office Supplies | J87: 21 | K87: 4117.89 | L87: =J87*K87 -> 86475.69 | M87: Cancelled | O87: 46035 | Q87: =IF(P87<>"",MAX(1,P87-B87),IF(M87="Dispatched",MAX(1,O87-B87),0)) -> 0 | R87: =IF(M87="Cancelled",0,IF(P87<>"",MAX(0,P87-O87),IF(T87<>"None",MAX(1,O87-B87-2),0))) -> 0 | S87: Paid | T87: Customer cancellation
A88: ORD0084 | B88: 46179 | C88: CUS0057 | D88: Aarav Sahu | E88: Central | F88: Raipur WH | G88: PRD045 | H88: =VLOOKUP(G88,'Product Master'!$A$5:$K$104,2,FALSE()) -> Essential Industrial Item 045 | I88: =VLOOKUP(G88,'Product Master'!$A$5:$K$104,3,FALSE()) -> Industrial | J88: 11 | K88: 9908.93 | L88: =J88*K88 -> 108998.23 | M88: Delivered | N88: 46179 | O88: 46183 | P88: 46184 | Q88: =IF(P88<>"",MAX(1,P88-B88),IF(M88="Dispatched",MAX(1,O88-B88),0)) -> 5 | R88: =IF(M88="Cancelled",0,IF(P88<>"",MAX(0,P88-O88),IF(T88<>"None",MAX(1,O88-B88-2),0))) -> 1 | S88: Pending | T88: Address issue
A89: ORD0085 | B89: 45960 | C89: CUS0026 | D89: Saanvi Khan | E89: Central | F89: Kolkata WH | G89: PRD061 | H89: =VLOOKUP(G89,'Product Master'!$A$5:$K$104,2,FALSE()) -> Pro Industrial Item 061 | I89: =VLOOKUP(G89,'Product Master'!$A$5:$K$104,3,FALSE()) -> Industrial | J89: 25 | K89: 5193.69 | L89: =J89*K89 -> 129842.25 | M89: Pending | O89: 45965 | Q89: =IF(P89<>"",MAX(1,P89-B89),IF(M89="Dispatched",MAX(1,O89-B89),0)) -> 0 | R89: =IF(M89="Cancelled",0,IF(P89<>"",MAX(0,P89-O89),IF(T89<>"None",MAX(1,O89-B89-2),0))) -> 0 | S89: Paid | T89: None
A90: ORD0086 | B90: 46204 | C90: CUS0215 | D90: Meera Verma | E90: North | F90: Bengaluru WH | G90: PRD095 | H90: =VLOOKUP(G90,'Product Master'!$A$5:$K$104,2,FALSE()) -> Eco Apparel Item 095 | I90: =VLOOKUP(G90,'Product Master'!$A$5:$K$104,3,FALSE()) -> Apparel | J90: 19 | K90: 2884.81 | L90: =J90*K90 -> 54811.39 | M90: Dispatched | N90: 46206 | O90: 46212 | Q90: =IF(P90<>"",MAX(1,P90-B90),IF(M90="Dispatched",MAX(1,O90-B90),0)) -> 8 | R90: =IF(M90="Cancelled",0,IF(P90<>"",MAX(0,P90-O90),IF(T90<>"None",MAX(1,O90-B90-2),0))) -> 6 | S90: Paid | T90: Carrier delay
A91: ORD0087 | B91: 46093 | C91: CUS0145 | D91: Vivaan Mishra | E91: East | F91: Raipur WH | G91: PRD095 | H91: =VLOOKUP(G91,'Product Master'!$A$5:$K$104,2,FALSE()) -> Eco Apparel Item 095 | I91: =VLOOKUP(G91,'Product Master'!$A$5:$K$104,3,FALSE()) -> Apparel | J91: 1 | K91: 2884.81 | L91: =J91*K91 -> 2884.81 | M91: Processing | O91: 46100 | Q91: =IF(P91<>"",MAX(1,P91-B91),IF(M91="Dispatched",MAX(1,O91-B91),0)) -> 0 | R91: =IF(M91="Cancelled",0,IF(P91<>"",MAX(0,P91-O91),IF(T91<>"None",MAX(1,O91-B91-2),0))) -> 0 | S91: Refunded | T91: None
A92: ORD0088 | B92: 46183 | C92: CUS0006 | D92: Myra Sharma | E92: East | F92: Bengaluru WH | G92: PRD070 | H92: =VLOOKUP(G92,'Product Master'!$A$5:$K$104,2,FALSE()) -> Eco Packaging Item 070 | I92: =VLOOKUP(G92,'Product Master'!$A$5:$K$104,3,FALSE()) -> Packaging | J92: 16 | K92: 6067.79 | L92: =J92*K92 -> 97084.64 | M92: Delivered | N92: 46184 | O92: 46185 | P92: 46185 | Q92: =IF(P92<>"",MAX(1,P92-B92),IF(M92="Dispatched",MAX(1,O92-B92),0)) -> 2 | R92: =IF(M92="Cancelled",0,IF(P92<>"",MAX(0,P92-O92),IF(T92<>"None",MAX(1,O92-B92-2),0))) -> 0 | S92: Paid | T92: None
A93: ORD0089 | B93: 46245 | C93: CUS0038 | D93: Kabir Sahu | E93: South | F93: Kolkata WH | G93: PRD026 | H93: =VLOOKUP(G93,'Product Master'!$A$5:$K$104,2,FALSE()) -> Classic Home Item 026 | I93: =VLOOKUP(G93,'Product Master'!$A$5:$K$104,3,FALSE()) -> Home & Kitchen | J93: 23 | K93: 4898.07 | L93: =J93*K93 -> 112655.61 | M93: Delivered | N93: 46245 | O93: 46252 | P93: 46248 | Q93: =IF(P93<>"",MAX(1,P93-B93),IF(M93="Dispatched",MAX(1,O93-B93),0)) -> 3 | R93: =IF(M93="Cancelled",0,IF(P93<>"",MAX(0,P93-O93),IF(T93<>"None",MAX(1,O93-B93-2),0))) -> 0 | S93: Paid | T93: None
A94: ORD0090 | B94: 46200 | C94: CUS0151 | D94: Anaya Rao | E94: North | F94: Kolkata WH | G94: PRD047 | H94: =VLOOKUP(G94,'Product Master'!$A$5:$K$104,2,FALSE()) -> Premium Apparel Item 047 | I94: =VLOOKUP(G94,'Product Master'!$A$5:$K$104,3,FALSE()) -> Apparel | J94: 23 | K94: 3068.55 | L94: =J94*K94 -> 70576.65 | M94: Cancelled | O94: 46208 | Q94: =IF(P94<>"",MAX(1,P94-B94),IF(M94="Dispatched",MAX(1,O94-B94),0)) -> 0 | R94: =IF(M94="Cancelled",0,IF(P94<>"",MAX(0,P94-O94),IF(T94<>"None",MAX(1,O94-B94-2),0))) -> 0 | S94: Paid | T94: Customer cancellation
A95: ORD0091 | B95: 46000 | C95: CUS0097 | D95: Aditi Iyer | E95: West | F95: Mumbai WH | G95: PRD021 | H95: =VLOOKUP(G95,'Product Master'!$A$5:$K$104,2,FALSE()) -> Eco Industrial Item 021 | I95: =VLOOKUP(G95,'Product Master'!$A$5:$K$104,3,FALSE()) -> Industrial | J95: 21 | K95: 2056.91 | L95: =J95*K95 -> 43195.11 | M95: Delivered | N95: 46001 | O95: 46007 | P95: 46006 | Q95: =IF(P95<>"",MAX(1,P95-B95),IF(M95="Dispatched",MAX(1,O95-B95),0)) -> 6 | R95: =IF(M95="Cancelled",0,IF(P95<>"",MAX(0,P95-O95),IF(T95<>"None",MAX(1,O95-B95-2),0))) -> 0 | S95: Paid | T95: None
A96: ORD0092 | B96: 45996 | C96: CUS0155 | D96: Reyansh Sahu | E96: North | F96: Raipur WH | G96: PRD023 | H96: =VLOOKUP(G96,'Product Master'!$A$5:$K$104,2,FALSE()) -> Eco Apparel Item 023 | I96: =VLOOKUP(G96,'Product Master'!$A$5:$K$104,3,FALSE()) -> Apparel | J96: 13 | K96: 3494.59 | L96: =J96*K96 -> 45429.67 | M96: Dispatched | N96: 45997 | O96: 45998 | Q96: =IF(P96<>"",MAX(1,P96-B96),IF(M96="Dispatched",MAX(1,O96-B96),0)) -> 2 | R96: =IF(M96="Cancelled",0,IF(P96<>"",MAX(0,P96-O96),IF(T96<>"None",MAX(1,O96-B96-2),0))) -> 1 | S96: Refunded | T96: Carrier delay
A97: ORD0093 | B97: 46044 | C97: CUS0043 | D97: Ishaan Mishra | E97: Central | F97: Delhi WH | G97: PRD082 | H97: =VLOOKUP(G97,'Product Master'!$A$5:$K$104,2,FALSE()) -> Compact Home Item 082 | I97: =VLOOKUP(G97,'Product Master'!$A$5:$K$104,3,FALSE()) -> Home & Kitchen | J97: 16 | K97: 3454.52 | L97: =J97*K97 -> 55272.32 | M97: Delivered | N97: 46045 | O97: 46047 | P97: 46048 | Q97: =IF(P97<>"",MAX(1,P97-B97),IF(M97="Dispatched",MAX(1,O97-B97),0)) -> 4 | R97: =IF(M97="Cancelled",0,IF(P97<>"",MAX(0,P97-O97),IF(T97<>"None",MAX(1,O97-B97-2),0))) -> 1 | S97: Pending | T97: Supplier delay
A98: ORD0094 | B98: 46258 | C98: CUS0202 | D98: Anaya Iyer | E98: East | F98: Mumbai WH | G98: PRD094 | H98: =VLOOKUP(G98,'Product Master'!$A$5:$K$104,2,FALSE()) -> Classic Packaging Item 094 | I98: =VLOOKUP(G98,'Product Master'!$A$5:$K$104,3,FALSE()) -> Packaging | J98: 1 | K98: 6811.13 | L98: =J98*K98 -> 6811.13 | M98: Delivered | N98: 46258 | O98: 46263 | P98: 46264 | Q98: =IF(P98<>"",MAX(1,P98-B98),IF(M98="Dispatched",MAX(1,O98-B98),0)) -> 6 | R98: =IF(M98="Cancelled",0,IF(P98<>"",MAX(0,P98-O98),IF(T98<>"None",MAX(1,O98-B98-2),0))) -> 1 | S98: Paid | T98: Supplier delay
A99: ORD0095 | B99: 46128 | C99: CUS0026 | D99: Myra Sahu | E99: West | F99: Bengaluru WH | G99: PRD057 | H99: =VLOOKUP(G99,'Product Master'!$A$5:$K$104,2,FALSE()) -> Essential Electronics Item 057 | I99: =VLOOKUP(G99,'Product Master'!$A$5:$K$104,3,FALSE()) -> Electronics | J99: 14 | K99: 8152.77 | L99: =J99*K99 -> 114138.78 | M99: Delivered | N99: 46130 | O99: 46136 | P99: 46144 | Q99: =IF(P99<>"",MAX(1,P99-B99),IF(M99="Dispatched",MAX(1,O99-B99),0)) -> 16 | R99: =IF(M99="Cancelled",0,IF(P99<>"",MAX(0,P99-O99),IF(T99<>"None",MAX(1,O99-B99-2),0))) -> 8 | S99: Partially Paid | T99: Weather disruption
A100: ORD0096 | B100: 46264 | C100: CUS0082 | D100: Arjun Patel | E100: South | F100: Bengaluru WH | G100: PRD098 | H100: =VLOOKUP(G100,'Product Master'!$A$5:$K$104,2,FALSE()) -> Compact Home Item 098 | I100: =VLOOKUP(G100,'Product Master'!$A$5:$K$104,3,FALSE()) -> Home & Kitchen | J100: 15 | K100: 9200.31 | L100: =J100*K100 -> 138004.65 | M100: Delivered | N100: 46266 | O100: 46266 | P100: 46266 | Q100: =IF(P100<>"",MAX(1,P100-B100),IF(M100="Dispatched",MAX(1,O100-B100),0)) -> 2 | R100: =IF(M100="Cancelled",0,IF(P100<>"",MAX(0,P100-O100),IF(T100<>"None",MAX(1,O100-B100-2),0))) -> 0 | S100: Paid | T100: None
A101: ORD0097 | B101: 46018 | C101: CUS0087 | D101: Myra Iyer | E101: South | F101: Delhi WH | G101: PRD049 | H101: =VLOOKUP(G101,'Product Master'!$A$5:$K$104,2,FALSE()) -> Premium Electronics Item 049 | I101: =VLOOKUP(G101,'Product Master'!$A$5:$K$104,3,FALSE()) -> Electronics | J101: 18 | K101: 8712.18 | L101: =J101*K101 -> 156819.24 | M101: Cancelled | O101: 46021 | Q101: =IF(P101<>"",MAX(1,P101-B101),IF(M101="Dispatched",MAX(1,O101-B101),0)) -> 0 | R101: =IF(M101="Cancelled",0,IF(P101<>"",MAX(0,P101-O101),IF(T101<>"None",MAX(1,O101-B101-2),0))) -> 0 | S101: Paid | T101: Customer cancellation
...

Sheet Inventory Management
A1: INVENTORY MANAGEMENT LEDGER (100 SKUs)
A2: Closing Stock = Opening Stock + Stock Received - Units Sold + Units Returned • Automated Stock Status & Reorder Quantity.
A4: Product ID | B4: Product Name | C4: Category | D4: Supplier ID | E4: Supplier Name | F4: Warehouse | G4: Opening Stock | H4: Stock Received | I4: Units Sold | J4: Units Returned | K4: Closing Stock | L4: Minimum Stock Level | M4: Maximum Stock Level | N4: Unit Cost | O4: Inventory Value | P4: Stock Status | Q4: Reorder Quantity
A5: PRD001 | B5: =VLOOKUP(A5,'Product Master'!$A$5:$K$104,2,FALSE()) -> Everyday Electronics Item 001 | C5: Electronics | D5: SUP001 | E5: =VLOOKUP(D5,'Supplier Database'!$A$5:$K$29,2,FALSE()) -> Apex Supplies | F5: Mumbai WH | G5: 22 | H5: 28 | I5: =SUMIFS('Order Tracking'!$J$5:$J$604,'Order Tracking'!$G$5:$G$604,A5,'Order Tracking'!$M$5:$M$604,"<>Cancelled") -> 50 | J5: 0 | K5: =G5+H5-I5+J5 -> 0 | L5: 55 | M5: 275 | N5: =VLOOKUP(A5,'Product Master'!$A$5:$K$104,5,FALSE()) -> 2345.85 | O5: =K5*N5 -> 0 | P5: =IF(K5<=0,"Out of Stock",IF(K5<L5,"Low Stock",IF(K5>M5,"Overstocked","Healthy Stock"))) -> Out of Stock | Q5: =IF(K5<L5,MAX(0,M5-K5),0) -> 275
A6: PRD002 | B6: =VLOOKUP(A6,'Product Master'!$A$5:$K$104,2,FALSE()) -> Premium Home Item 002 | C6: Home & Kitchen | D6: SUP002 | E6: =VLOOKUP(D6,'Supplier Database'!$A$5:$K$29,2,FALSE()) -> Bright Distributors | F6: Raipur WH | G6: 25 | H6: 0 | I6: =SUMIFS('Order Tracking'!$J$5:$J$604,'Order Tracking'!$G$5:$G$604,A6,'Order Tracking'!$M$5:$M$604,"<>Cancelled") -> 16 | J6: 0 | K6: =G6+H6-I6+J6 -> 9 | L6: 42 | M6: 294 | N6: =VLOOKUP(A6,'Product Master'!$A$5:$K$104,5,FALSE()) -> 7961.45 | O6: =K6*N6 -> 71653.05 | P6: =IF(K6<=0,"Out of Stock",IF(K6<L6,"Low Stock",IF(K6>M6,"Overstocked","Healthy Stock"))) -> Low Stock | Q6: =IF(K6<L6,MAX(0,M6-K6),0) -> 285
A7: PRD003 | B7: =VLOOKUP(A7,'Product Master'!$A$5:$K$104,2,FALSE()) -> Premium Office Item 003 | C7: Office Supplies | D7: SUP003 | E7: =VLOOKUP(D7,'Supplier Database'!$A$5:$K$29,2,FALSE()) -> Core Industries | F7: Raipur WH | G7: 179 | H7: 270 | I7: =SUMIFS('Order Tracking'!$J$5:$J$604,'Order Tracking'!$G$5:$G$604,A7,'Order Tracking'!$M$5:$M$604,"<>Cancelled") -> 65 | J7: 0 | K7: =G7+H7-I7+J7 -> 384 | L7: 62 | M7: 558 | N7: =VLOOKUP(A7,'Product Master'!$A$5:$K$104,5,FALSE()) -> 1229.99 | O7: =K7*N7 -> 472316.16 | P7: =IF(K7<=0,"Out of Stock",IF(K7<L7,"Low Stock",IF(K7>M7,"Overstocked","Healthy Stock"))) -> Healthy Stock | Q7: =IF(K7<L7,MAX(0,M7-K7),0) -> 0
A8: PRD004 | B8: =VLOOKUP(A8,'Product Master'!$A$5:$K$104,2,FALSE()) -> Everyday Personal Item 004 | C8: Personal Care | D8: SUP004 | E8: =VLOOKUP(D8,'Supplier Database'!$A$5:$K$29,2,FALSE()) -> Delta Trading Co. | F8: Mumbai WH | G8: 57 | H8: 87 | I8: =SUMIFS('Order Tracking'!$J$5:$J$604,'Order Tracking'!$G$5:$G$604,A8,'Order Tracking'!$M$5:$M$604,"<>Cancelled") -> 27 | J8: 0 | K8: =G8+H8-I8+J8 -> 117 | L8: 53 | M8: 371 | N8: =VLOOKUP(A8,'Product Master'!$A$5:$K$104,5,FALSE()) -> 3791.99 | O8: =K8*N8 -> 443662.83 | P8: =IF(K8<=0,"Out of Stock",IF(K8<L8,"Low Stock",IF(K8>M8,"Overstocked","Healthy Stock"))) -> Healthy Stock | Q8: =IF(K8<L8,MAX(0,M8-K8),0) -> 0
A9: PRD005 | B9: =VLOOKUP(A9,'Product Master'!$A$5:$K$104,2,FALSE()) -> Everyday Industrial Item 005 | C9: Industrial | D9: SUP005 | E9: =VLOOKUP(D9,'Supplier Database'!$A$5:$K$29,2,FALSE()) -> Ever Logistics | F9: Delhi WH | G9: 39 | H9: 48 | I9: =SUMIFS('Order Tracking'!$J$5:$J$604,'Order Tracking'!$G$5:$G$604,A9,'Order Tracking'!$M$5:$M$604,"<>Cancelled") -> 87 | J9: 0 | K9: =G9+H9-I9+J9 -> 0 | L9: 28 | M9: 112 | N9: =VLOOKUP(A9,'Product Master'!$A$5:$K$104,5,FALSE()) -> 988.05 | O9: =K9*N9 -> 0 | P9: =IF(K9<=0,"Out of Stock",IF(K9<L9,"Low Stock",IF(K9>M9,"Overstocked","Healthy Stock"))) -> Out of Stock | Q9: =IF(K9<L9,MAX(0,M9-K9),0) -> 112
A10: PRD006 | B10: =VLOOKUP(A10,'Product Master'!$A$5:$K$104,2,FALSE()) -> Pro Packaging Item 006 | C10: Packaging | D10: SUP006 | E10: =VLOOKUP(D10,'Supplier Database'!$A$5:$K$29,2,FALSE()) -> Frontier Wholesale | F10: Delhi WH | G10: 139 | H10: 209 | I10: =SUMIFS('Order Tracking'!$J$5:$J$604,'Order Tracking'!$G$5:$G$604,A10,'Order Tracking'!$M$5:$M$604,"<>Cancelled") -> 94 | J10: 0 | K10: =G10+H10-I10+J10 -> 254 | L10: 41 | M10: 369 | N10: =VLOOKUP(A10,'Product Master'!$A$5:$K$104,5,FALSE()) -> 1422.65 | O10: =K10*N10 -> 361353.1 | P10: =IF(K10<=0,"Out of Stock",IF(K10<L10,"Low Stock",IF(K10>M10,"Overstocked","Healthy Stock"))) -> Healthy Stock | Q10: =IF(K10<L10,MAX(0,M10-K10),0) -> 0
A11: PRD007 | B11: =VLOOKUP(A11,'Product Master'!$A$5:$K$104,2,FALSE()) -> Everyday Apparel Item 007 | C11: Apparel | D11: SUP007 | E11: =VLOOKUP(D11,'Supplier Database'!$A$5:$K$29,2,FALSE()) -> Global Partners | F11: Delhi WH | G11: 46 | H11: 71 | I11: =SUMIFS('Order Tracking'!$J$5:$J$604,'Order Tracking'!$G$5:$G$604,A11,'Order Tracking'!$M$5:$M$604,"<>Cancelled") -> 20 | J11: 0 | K11: =G11+H11-I11+J11 -> 97 | L11: 26 | M11: 130 | N11: =VLOOKUP(A11,'Product Master'!$A$5:$K$104,5,FALSE()) -> 7267.41 | O11: =K11*N11 -> 704938.77 | P11: =IF(K11<=0,"Out of Stock",IF(K11<L11,"Low Stock",IF(K11>M11,"Overstocked","Healthy Stock"))) -> Healthy Stock | Q11: =IF(K11<L11,MAX(0,M11-K11),0) -> 0
A12: PRD008 | B12: =VLOOKUP(A12,'Product Master'!$A$5:$K$104,2,FALSE()) -> Smart Automotive Item 008 | C12: Automotive | D12: SUP008 | E12: =VLOOKUP(D12,'Supplier Database'!$A$5:$K$29,2,FALSE()) -> Horizon Supplies | F12: Raipur WH | G12: 500 | H12: 751 | I12: =SUMIFS('Order Tracking'!$J$5:$J$604,'Order Tracking'!$G$5:$G$604,A12,'Order Tracking'!$M$5:$M$604,"<>Cancelled") -> 149 | J12: 11 | K12: =G12+H12-I12+J12 -> 1113 | L12: 48 | M12: 240 | N12: =VLOOKUP(A12,'Product Master'!$A$5:$K$104,5,FALSE()) -> 7069.94 | O12: =K12*N12 -> 7868843.2 | P12: =IF(K12<=0,"Out of Stock",IF(K12<L12,"Low Stock",IF(K12>M12,"Overstocked","Healthy Stock"))) -> Overstocked | Q12: =IF(K12<L12,MAX(0,M12-K12),0) -> 0
A13: PRD009 | B13: =VLOOKUP(A13,'Product Master'!$A$5:$K$104,2,FALSE()) -> Essential Electronics Item 009 | C13: Electronics | D13: SUP009 | E13: =VLOOKUP(D13,'Supplier Database'!$A$5:$K$29,2,FALSE()) -> Indus Distributors | F13: Delhi WH | G13: 36 | H13: 44 | I13: =SUMIFS('Order Tracking'!$J$5:$J$604,'Order Tracking'!$G$5:$G$604,A13,'Order Tracking'!$M$5:$M$604,"<>Cancelled") -> 80 | J13: 0 | K13: =G13+H13-I13+J13 -> 0 | L13: 24 | M13: 96 | N13: =VLOOKUP(A13,'Product Master'!$A$5:$K$104,5,FALSE()) -> 3822.58 | O13: =K13*N13 -> 0 | P13: =IF(K13<=0,"Out of Stock",IF(K13<L13,"Low Stock",IF(K13>M13,"Overstocked","Healthy Stock"))) -> Out of Stock | Q13: =IF(K13<L13,MAX(0,M13-K13),0) -> 96
A14: PRD010 | B14: =VLOOKUP(A14,'Product Master'!$A$5:$K$104,2,FALSE()) -> Essential Home Item 010 | C14: Home & Kitchen | D14: SUP010 | E14: =VLOOKUP(D14,'Supplier Database'!$A$5:$K$29,2,FALSE()) -> Jupiter Industries | F14: Delhi WH | G14: 67 | H14: 102 | I14: =SUMIFS('Order Tracking'!$J$5:$J$604,'Order Tracking'!$G$5:$G$604,A14,'Order Tracking'!$M$5:$M$604,"<>Cancelled") -> 147 | J14: 0 | K14: =G14+H14-I14+J14 -> 22 | L14: 33 | M14: 297 | N14: =VLOOKUP(A14,'Product Master'!$A$5:$K$104,5,FALSE()) -> 5910.74 | O14: =K14*N14 -> 130036.28 | P14: =IF(K14<=0,"Out of Stock",IF(K14<L14,"Low Stock",IF(K14>M14,"Overstocked","Healthy Stock"))) -> Low Stock | Q14: =IF(K14<L14,MAX(0,M14-K14),0) -> 275
A15: PRD011 | B15: =VLOOKUP(A15,'Product Master'!$A$5:$K$104,2,FALSE()) -> Essential Office Item 011 | C15: Office Supplies | D15: SUP011 | E15: =VLOOKUP(D15,'Supplier Database'!$A$5:$K$29,2,FALSE()) -> Kinetic Trading Co. | F15: Raipur WH | G15: 144 | H15: 217 | I15: =SUMIFS('Order Tracking'!$J$5:$J$604,'Order Tracking'!$G$5:$G$604,A15,'Order Tracking'!$M$5:$M$604,"<>Cancelled") -> 24 | J15: 0 | K15: =G15+H15-I15+J15 -> 337 | L15: 41 | M15: 205 | N15: =VLOOKUP(A15,'Product Master'!$A$5:$K$104,5,FALSE()) -> 470.53 | O15: =K15*N15 -> 158568.61 | P15: =IF(K15<=0,"Out of Stock",IF(K15<L15,"Low Stock",IF(K15>M15,"Overstocked","Healthy Stock"))) -> Overstocked | Q15: =IF(K15<L15,MAX(0,M15-K15),0) -> 0
A16: PRD012 | B16: =VLOOKUP(A16,'Product Master'!$A$5:$K$104,2,FALSE()) -> Eco Personal Item 012 | C16: Personal Care | D16: SUP012 | E16: =VLOOKUP(D16,'Supplier Database'!$A$5:$K$29,2,FALSE()) -> Lotus Logistics | F16: Kolkata WH | G16: 123 | H16: 186 | I16: =SUMIFS('Order Tracking'!$J$5:$J$604,'Order Tracking'!$G$5:$G$604,A16,'Order Tracking'!$M$5:$M$604,"<>Cancelled") -> 147 | J16: 0 | K16: =G16+H16-I16+J16 -> 162 | L16: 45 | M16: 225 | N16: =VLOOKUP(A16,'Product Master'!$A$5:$K$104,5,FALSE()) -> 5708.9 | O16: =K16*N16 -> 924841.8 | P16: =IF(K16<=0,"Out of Stock",IF(K16<L16,"Low Stock",IF(K16>M16,"Overstocked","Healthy Stock"))) -> Healthy Stock | Q16: =IF(K16<L16,MAX(0,M16-K16),0) -> 0
... A104: PRD100 | B104: =VLOOKUP(A104,'Product Master'!$A$5:$K$104,2,FALSE()) -> Smart Personal Item 100 | C104: Personal Care | D104: SUP025 | E104: =VLOOKUP(D104,'Supplier Database'!$A$5:$K$29,2,FALSE()) -> Zenith Trading Co. | F104: Delhi WH | G104: 56 | H104: 84 | I104: =SUMIFS('Order Tracking'!$J$5:$J$604,'Order Tracking'!$G$5:$G$604,A104,'Order Tracking'!$M$5:$M$604,"<>Cancelled") -> 74 | J104: 2 | K104: =G104+H104-I104+J104 -> 68 | L104: 19 | M104: 95 | N104: =VLOOKUP(A104,'Product Master'!$A$5:$K$104,5,FALSE()) -> 7321.29 | O104: =K104*N104 -> 497847.72 | P104: =IF(K104<=0,"Out of Stock",IF(K104<L104,"Low Stock",IF(K104>M104,"Overstocked","Healthy Stock"))) -> Healthy Stock | Q104: =IF(K104<L104,MAX(0,M104-K104),0) -> 0

Sheet Supplier Database
A1: SUPPLIER MASTER DATABASE
A2: 25 fictional contracted suppliers • Includes payment terms, lead time (days), quality ratings, and active status dropdowns.
A4: Supplier ID | B4: Supplier Name | C4: Contact Person | D4: Region | E4: Product Category | F4: Contract Start Date | G4: Contract End Date | H4: Payment Terms | I4: Lead Time | J4: Supplier Rating | K4: Supplier Status
A5: SUP001 | B5: Apex Supplies | C5: Anaya Sharma | D5: East | E5: Personal Care | F5: 44644 | G5: 46440 | H5: Net 60 | I5: 3 | J5: 4.4 | K5: Active
A6: SUP002 | B6: Bright Distributors | C6: Ishaan Nair | D6: South | E6: Electronics | F6: 45405 | G6: 46714 | H6: Net 60 | I6: 8 | J6: 3.3 | K6: Active
A7: SUP003 | B7: Core Industries | C7: Aarav Sahu | D7: South | E7: Apparel | F7: 45051 | G7: 46502 | H7: Net 45 | I7: 3 | J7: 2.9 | K7: Active
A8: SUP004 | B8: Delta Trading Co. | C8: Ira Joshi | D8: East | E8: Electronics | F8: 45522 | G8: 46431 | H8: Net 15 | I8: 10 | J8: 3.4 | K8: Active
A9: SUP005 | B9: Ever Logistics | C9: Ira Joshi | D9: South | E9: Home & Kitchen | F9: 44873 | G9: 46510 | H9: Net 30 | I9: 3 | J9: 4.5 | K9: Active
A10: SUP006 | B10: Frontier Wholesale | C10: Ira Verma | D10: East | E10: Packaging | F10: 44874 | G10: 46743 | H10: Net 15 | I10: 11 | J10: 4.2 | K10: Active
A11: SUP007 | B11: Global Partners | C11: Saanvi Verma | D11: West | E11: Apparel | F11: 45253 | G11: 46638 | H11: Net 45 | I11: 14 | J11: 4.6 | K11: Active
A12: SUP008 | B12: Horizon Supplies | C12: Diya Sahu | D12: East | E12: Apparel | F12: 44964 | G12: 46683 | H12: Net 45 | I12: 5 | J12: 4.2 | K12: Active
A13: SUP009 | B13: Indus Distributors | C13: Dev Verma | D13: East | E13: Office Supplies | F13: 44913 | G13: 46639 | H13: Net 60 | I13: 8 | J13: 4.9 | K13: Active
A14: SUP010 | B14: Jupiter Industries | C14: Saanvi Verma | D14: Central | E14: Automotive | F14: 44565 | G14: 46467 | H14: Net 30 | I14: 14 | J14: 4.5 | K14: Active
A15: SUP011 | B15: Kinetic Trading Co. | C15: Rohan Singh | D15: Central | E15: Automotive | F15: 45430 | G15: 46409 | H15: Net 15 | I15: 12 | J15: 4.7 | K15: Active
A16: SUP012 | B16: Lotus Logistics | C16: Reyansh Patel | D16: East | E16: Apparel | F16: 44774 | G16: 46745 | H16: Net 45 | I16: 10 | J16: 4.6 | K16: Active
... A29: SUP025 | B29: Zenith Trading Co. | C29: Diya Joshi | D29: North | E29: Apparel | F29: 45584 | G29: 46641 | H29: Net 45 | I29: 5 | J29: 4.3 | K29: Active

Sheet Product Master
A1: PRODUCT MASTER CATALOG
A2: 100 fictional distribution SKUs across 8 categories • Formula-driven unit profit and profit margin linked to Supplier Database.
A4: Product ID | B4: Product Name | C4: Product Category | D4: Brand | E4: Unit Cost | F4: Selling Price | G4: Profit per Unit | H4: Profit Margin | I4: Supplier ID | J4: Reorder Level | K4: Product Status
A5: PRD001 | B5: Everyday Electronics Item 001 | C5: Electronics | D5: MetroWorks | E5: 2345.85 | F5: 2912.4 | G5: =F5-E5 -> 566.55 | H5: =IFERROR(G5/F5,0) -> 0.19453028 | I5: SUP001 | J5: 55 | K5: Active
A6: PRD002 | B6: Premium Home Item 002 | C6: Home & Kitchen | D6: UrbanNest | E6: 7961.45 | F6: 9429.37 | G6: =F6-E6 -> 1467.92 | H6: =IFERROR(G6/F6,0) -> 0.1556753 | I6: SUP002 | J6: 42 | K6: Active
A7: PRD003 | B7: Premium Office Item 003 | C7: Office Supplies | D7: DailyEase | E7: 1229.99 | F7: 1653.15 | G7: =F7-E7 -> 423.16 | H7: =IFERROR(G7/F7,0) -> 0.25597193 | I7: SUP003 | J7: 62 | K7: Active
A8: PRD004 | B8: Everyday Personal Item 004 | C8: Personal Care | D8: NovaCore | E8: 3791.99 | F8: 5442.69 | G8: =F8-E8 -> 1650.7 | H8: =IFERROR(G8/F8,0) -> 0.30328753 | I8: SUP004 | J8: 53 | K8: Active
A9: PRD005 | B9: Everyday Industrial Item 005 | C9: Industrial | D9: UrbanNest | E9: 988.05 | F9: 1573.69 | G9: =F9-E9 -> 585.64 | H9: =IFERROR(G9/F9,0) -> 0.37214445 | I9: SUP005 | J9: 28 | K9: Active
A10: PRD006 | B10: Pro Packaging Item 006 | C10: Packaging | D10: PrimeLine | E10: 1422.65 | F10: 1867.12 | G10: =F10-E10 -> 444.47 | H10: =IFERROR(G10/F10,0) -> 0.23805112 | I10: SUP006 | J10: 41 | K10: Active
A11: PRD007 | B11: Everyday Apparel Item 007 | C11: Apparel | D11: NovaCore | E11: 7267.41 | F11: 10301.86 | G11: =F11-E11 -> 3034.45 | H11: =IFERROR(G11/F11,0) -> 0.2945536 | I11: SUP007 | J11: 26 | K11: Active
A12: PRD008 | B12: Smart Automotive Item 008 | C12: Automotive | D12: ApexPro | E12: 7069.94 | F12: 8489.02 | G12: =F12-E12 -> 1419.08 | H12: =IFERROR(G12/F12,0) -> 0.16716653 | I12: SUP008 | J12: 48 | K12: Active
A13: PRD009 | B13: Essential Electronics Item 009 | C13: Electronics | D13: UrbanNest | E13: 3822.58 | F13: 5778.46 | G13: =F13-E13 -> 1955.88 | H13: =IFERROR(G13/F13,0) -> 0.33847773 | I13: SUP009 | J13: 24 | K13: Discontinued
A14: PRD010 | B14: Essential Home Item 010 | C14: Home & Kitchen | D14: PrimeLine | E14: 5910.74 | F14: 7388.75 | G14: =F14-E14 -> 1478.01 | H14: =IFERROR(G14/F14,0) -> 0.20003519 | I14: SUP010 | J14: 33 | K14: Active
A15: PRD011 | B15: Essential Office Item 011 | C15: Office Supplies | D15: PrimeLine | E15: 470.53 | F15: 635.87 | G15: =F15-E15 -> 165.34 | H15: =IFERROR(G15/F15,0) -> 0.2600217 | I15: SUP011 | J15: 41 | K15: Active
A16: PRD012 | B16: Eco Personal Item 012 | C16: Personal Care | D16: ApexPro | E16: 5708.9 | F16: 7685.49 | G16: =F16-E16 -> 1976.59 | H16: =IFERROR(G16/F16,0) -> 0.25718464 | I16: SUP012 | J16: 45 | K16: Active
... A104: PRD100 | B104: Smart Personal Item 100 | C104: Personal Care | D104: MetroWorks | E104: 7321.29 | F104: 9946.74 | G104: =F104-E104 -> 2625.45 | H104: =IFERROR(G104/F104,0) -> 0.2639508 | I104: SUP025 | J104: 19 | K104: Active

Sheet Purchase Management
A1: PURCHASE ORDER MANAGEMENT (220 PO RECORDS)
A2: Procurement ledger • VLOOKUP links Supplier & Product names; formulas compute Total Purchase Value, Pending Qty, and Supplier Delay Days.
A4: Purchase Order ID | B4: Purchase Order Date | C4: Supplier ID | D4: Supplier Name | E4: Product ID | F4: Product Name | G4: Quantity Ordered | H4: Unit Cost | I4: Total Purchase Value | J4: Expected Receipt Date | K4: Actual Receipt Date | L4: Received Quantity | M4: Pending Quantity | N4: Purchase Status | O4: Supplier Delay Days
A5: PO0001 | B5: 46314 | C5: SUP021 | D5: =VLOOKUP(C5,'Supplier Database'!$A$5:$K$29,2,FALSE()) -> Unity Partners | E5: PRD088 | F5: =VLOOKUP(E5,'Product Master'!$A$5:$K$104,2,FALSE()) -> Premium Automotive Item 088 | G5: 491 | H5: 878.1 | I5: =G5*H5 -> 431147.1 | J5: 46319 | L5: 0 | M5: =MAX(0,G5-L5) -> 491 | N5: Pending | O5: =IF(N5="Cancelled",0,IF(K5<>"",MAX(0,K5-J5),IF(N5="Delayed",MAX(0,'Daily MIS Report'!$B$4-J5),0))) -> 0
A6: PO0002 | B6: 46153 | C6: SUP004 | D6: =VLOOKUP(C6,'Supplier Database'!$A$5:$K$29,2,FALSE()) -> Delta Trading Co. | E6: PRD098 | F6: =VLOOKUP(E6,'Product Master'!$A$5:$K$104,2,FALSE()) -> Compact Home Item 098 | G6: 344 | H6: 7939.11 | I6: =G6*H6 -> 2731053.8 | J6: 46163 | K6: 46162 | L6: 344 | M6: =MAX(0,G6-L6) -> 0 | N6: Received | O6: =IF(N6="Cancelled",0,IF(K6<>"",MAX(0,K6-J6),IF(N6="Delayed",MAX(0,'Daily MIS Report'!$B$4-J6),0))) -> 0
A7: PO0003 | B7: 46286 | C7: SUP010 | D7: =VLOOKUP(C7,'Supplier Database'!$A$5:$K$29,2,FALSE()) -> Jupiter Industries | E7: PRD004 | F7: =VLOOKUP(E7,'Product Master'!$A$5:$K$104,2,FALSE()) -> Everyday Personal Item 004 | G7: 43 | H7: 3712.07 | I7: =G7*H7 -> 159619.01 | J7: 46300 | K7: 46300 | L7: 43 | M7: =MAX(0,G7-L7) -> 0 | N7: Received | O7: =IF(N7="Cancelled",0,IF(K7<>"",MAX(0,K7-J7),IF(N7="Delayed",MAX(0,'Daily MIS Report'!$B$4-J7),0))) -> 0
A8: PO0004 | B8: 46122 | C8: SUP014 | D8: =VLOOKUP(C8,'Supplier Database'!$A$5:$K$29,2,FALSE()) -> Northstar Partners | E8: PRD019 | F8: =VLOOKUP(E8,'Product Master'!$A$5:$K$104,2,FALSE()) -> Everyday Office Item 019 | G8: 145 | H8: 2317.62 | I8: =G8*H8 -> 336054.9 | J8: 46125 | K8: 46130 | L8: 47 | M8: =MAX(0,G8-L8) -> 98 | N8: Partially Received | O8: =IF(N8="Cancelled",0,IF(K8<>"",MAX(0,K8-J8),IF(N8="Delayed",MAX(0,'Daily MIS Report'!$B$4-J8),0))) -> 5
A9: PO0005 | B9: 46018 | C9: SUP006 | D9: =VLOOKUP(C9,'Supplier Database'!$A$5:$K$29,2,FALSE()) -> Frontier Wholesale | E9: PRD011 | F9: =VLOOKUP(E9,'Product Master'!$A$5:$K$104,2,FALSE()) -> Essential Office Item 011 | G9: 332 | H9: 491.47 | I9: =G9*H9 -> 163168.04 | J9: 46029 | K9: 46029 | L9: 255 | M9: =MAX(0,G9-L9) -> 77 | N9: Partially Received | O9: =IF(N9="Cancelled",0,IF(K9<>"",MAX(0,K9-J9),IF(N9="Delayed",MAX(0,'Daily MIS Report'!$B$4-J9),0))) -> 0
A10: PO0006 | B10: 46229 | C10: SUP005 | D10: =VLOOKUP(C10,'Supplier Database'!$A$5:$K$29,2,FALSE()) -> Ever Logistics | E10: PRD030 | F10: =VLOOKUP(E10,'Product Master'!$A$5:$K$104,2,FALSE()) -> Premium Packaging Item 030 | G10: 256 | H10: 5710.74 | I10: =G10*H10 -> 1461949.4 | J10: 46232 | K10: 46229 | L10: 256 | M10: =MAX(0,G10-L10) -> 0 | N10: Received | O10: =IF(N10="Cancelled",0,IF(K10<>"",MAX(0,K10-J10),IF(N10="Delayed",MAX(0,'Daily MIS Report'!$B$4-J10),0))) -> 0
A11: PO0007 | B11: 46169 | C11: SUP010 | D11: =VLOOKUP(C11,'Supplier Database'!$A$5:$K$29,2,FALSE()) -> Jupiter Industries | E11: PRD087 | F11: =VLOOKUP(E11,'Product Master'!$A$5:$K$104,2,FALSE()) -> Compact Apparel Item 087 | G11: 299 | H11: 5177.98 | I11: =G11*H11 -> 1548216 | J11: 46183 | K11: 46183 | L11: 299 | M11: =MAX(0,G11-L11) -> 0 | N11: Received | O11: =IF(N11="Cancelled",0,IF(K11<>"",MAX(0,K11-J11),IF(N11="Delayed",MAX(0,'Daily MIS Report'!$B$4-J11),0))) -> 0
A12: PO0008 | B12: 46231 | C12: SUP010 | D12: =VLOOKUP(C12,'Supplier Database'!$A$5:$K$29,2,FALSE()) -> Jupiter Industries | E12: PRD082 | F12: =VLOOKUP(E12,'Product Master'!$A$5:$K$104,2,FALSE()) -> Compact Home Item 082 | G12: 237 | H12: 2874.65 | I12: =G12*H12 -> 681292.05 | J12: 46245 | K12: 46245 | L12: 237 | M12: =MAX(0,G12-L12) -> 0 | N12: Received | O12: =IF(N12="Cancelled",0,IF(K12<>"",MAX(0,K12-J12),IF(N12="Delayed",MAX(0,'Daily MIS Report'!$B$4-J12),0))) -> 0
A13: PO0009 | B13: 46032 | C13: SUP013 | D13: =VLOOKUP(C13,'Supplier Database'!$A$5:$K$29,2,FALSE()) -> Meridian Wholesale | E13: PRD062 | F13: =VLOOKUP(E13,'Product Master'!$A$5:$K$104,2,FALSE()) -> Compact Packaging Item 062 | G13: 74 | H13: 6145.24 | I13: =G13*H13 -> 454747.76 | J13: 46034 | K13: 46037 | L13: 38 | M13: =MAX(0,G13-L13) -> 36 | N13: Partially Received | O13: =IF(N13="Cancelled",0,IF(K13<>"",MAX(0,K13-J13),IF(N13="Delayed",MAX(0,'Daily MIS Report'!$B$4-J13),0))) -> 3
A14: PO0010 | B14: 46289 | C14: SUP010 | D14: =VLOOKUP(C14,'Supplier Database'!$A$5:$K$29,2,FALSE()) -> Jupiter Industries | E14: PRD003 | F14: =VLOOKUP(E14,'Product Master'!$A$5:$K$104,2,FALSE()) -> Premium Office Item 003 | G14: 444 | H14: 1253.34 | I14: =G14*H14 -> 556482.96 | J14: 46303 | K14: 46300 | L14: 444 | M14: =MAX(0,G14-L14) -> 0 | N14: Received | O14: =IF(N14="Cancelled",0,IF(K14<>"",MAX(0,K14-J14),IF(N14="Delayed",MAX(0,'Daily MIS Report'!$B$4-J14),0))) -> 0
A15: PO0011 | B15: 46241 | C15: SUP024 | D15: =VLOOKUP(C15,'Supplier Database'!$A$5:$K$29,2,FALSE()) -> Yugma Industries | E15: PRD064 | F15: =VLOOKUP(E15,'Product Master'!$A$5:$K$104,2,FALSE()) -> Compact Automotive Item 064 | G15: 446 | H15: 3296.67 | I15: =G15*H15 -> 1470314.8 | J15: 46244 | K15: 46244 | L15: 446 | M15: =MAX(0,G15-L15) -> 0 | N15: Received | O15: =IF(N15="Cancelled",0,IF(K15<>"",MAX(0,K15-J15),IF(N15="Delayed",MAX(0,'Daily MIS Report'!$B$4-J15),0))) -> 0
A16: PO0012 | B16: 46241 | C16: SUP012 | D16: =VLOOKUP(C16,'Supplier Database'!$A$5:$K$29,2,FALSE()) -> Lotus Logistics | E16: PRD029 | F16: =VLOOKUP(E16,'Product Master'!$A$5:$K$104,2,FALSE()) -> Eco Industrial Item 029 | G16: 345 | H16: 7265.24 | I16: =G16*H16 -> 2506507.8 | J16: 46251 | K16: 46250 | L16: 345 | M16: =MAX(0,G16-L16) -> 0 | N16: Received | O16: =IF(N16="Cancelled",0,IF(K16<>"",MAX(0,K16-J16),IF(N16="Delayed",MAX(0,'Daily MIS Report'!$B$4-J16),0))) -> 0
A17: PO0013 | B17: 46252 | C17: SUP004 | D17: =VLOOKUP(C17,'Supplier Database'!$A$5:$K$29,2,FALSE()) -> Delta Trading Co. | E17: PRD081 | F17: =VLOOKUP(E17,'Product Master'!$A$5:$K$104,2,FALSE()) -> Premium Electronics Item 081 | G17: 350 | H17: 3564.2 | I17: =G17*H17 -> 1247470 | J17: 46262 | L17: 0 | M17: =MAX(0,G17-L17) -> 350 | N17: Pending | O17: =IF(N17="Cancelled",0,IF(K17<>"",MAX(0,K17-J17),IF(N17="Delayed",MAX(0,'Daily MIS Report'!$B$4-J17),0))) -> 0
A18: PO0014 | B18: 46302 | C18: SUP019 | D18: =VLOOKUP(C18,'Supplier Database'!$A$5:$K$29,2,FALSE()) -> Summit Logistics | E18: PRD047 | F18: =VLOOKUP(E18,'Product Master'!$A$5:$K$104,2,FALSE()) -> Premium Apparel Item 047 | G18: 394 | H18: 2167.04 | I18: =G18*H18 -> 853813.76 | J18: 46312 | L18: 5 | M18: =MAX(0,G18-L18) -> 389 | N18: Delayed | O18: =IF(N18="Cancelled",0,IF(K18<>"",MAX(0,K18-J18),IF(N18="Delayed",MAX(0,'Daily MIS Report'!$B$4-J18),0))) -> 2
A19: PO0015 | B19: 46313 | C19: SUP014 | D19: =VLOOKUP(C19,'Supplier Database'!$A$5:$K$29,2,FALSE()) -> Northstar Partners | E19: PRD023 | F19: =VLOOKUP(E19,'Product Master'!$A$5:$K$104,2,FALSE()) -> Eco Apparel Item 023 | G19: 122 | H19: 2520.31 | I19: =G19*H19 -> 307477.82 | J19: 46316 | K19: 46316 | L19: 122 | M19: =MAX(0,G19-L19) -> 0 | N19: Received | O19: =IF(N19="Cancelled",0,IF(K19<>"",MAX(0,K19-J19),IF(N19="Delayed",MAX(0,'Daily MIS Report'!$B$4-J19),0))) -> 0
A20: PO0016 | B20: 46302 | C20: SUP017 | D20: =VLOOKUP(C20,'Supplier Database'!$A$5:$K$29,2,FALSE()) -> Quantum Industries | E20: PRD035 | F20: =VLOOKUP(E20,'Product Master'!$A$5:$K$104,2,FALSE()) -> Smart Office Item 035 | G20: 445 | H20: 5853.98 | I20: =G20*H20 -> 2605021.1 | J20: 46310 | L20: 7 | M20: =MAX(0,G20-L20) -> 438 | N20: Delayed | O20: =IF(N20="Cancelled",0,IF(K20<>"",MAX(0,K20-J20),IF(N20="Delayed",MAX(0,'Daily MIS Report'!$B$4-J20),0))) -> 4
A21: PO0017 | B21: 46082 | C21: SUP024 | D21: =VLOOKUP(C21,'Supplier Database'!$A$5:$K$29,2,FALSE()) -> Yugma Industries | E21: PRD044 | F21: =VLOOKUP(E21,'Product Master'!$A$5:$K$104,2,FALSE()) -> Essential Personal Item 044 | G21: 431 | H21: 769.13 | I21: =G21*H21 -> 331495.03 | J21: 46085 | L21: 0 | M21: =MAX(0,G21-L21) -> 431 | N21: Cancelled | O21: =IF(N21="Cancelled",0,IF(K21<>"",MAX(0,K21-J21),IF(N21="Delayed",MAX(0,'Daily MIS Report'!$B$4-J21),0))) -> 0
A22: PO0018 | B22: 46003 | C22: SUP025 | D22: =VLOOKUP(C22,'Supplier Database'!$A$5:$K$29,2,FALSE()) -> Zenith Trading Co. | E22: PRD029 | F22: =VLOOKUP(E22,'Product Master'!$A$5:$K$104,2,FALSE()) -> Eco Industrial Item 029 | G22: 460 | H22: 7705.49 | I22: =G22*H22 -> 3544525.4 | J22: 46008 | K22: 46010 | L22: 434 | M22: =MAX(0,G22-L22) -> 26 | N22: Partially Received | O22: =IF(N22="Cancelled",0,IF(K22<>"",MAX(0,K22-J22),IF(N22="Delayed",MAX(0,'Daily MIS Report'!$B$4-J22),0))) -> 2
A23: PO0019 | B23: 46216 | C23: SUP012 | D23: =VLOOKUP(C23,'Supplier Database'!$A$5:$K$29,2,FALSE()) -> Lotus Logistics | E23: PRD012 | F23: =VLOOKUP(E23,'Product Master'!$A$5:$K$104,2,FALSE()) -> Eco Personal Item 012 | G23: 424 | H23: 5636.68 | I23: =G23*H23 -> 2389952.3 | J23: 46226 | K23: 46224 | L23: 424 | M23: =MAX(0,G23-L23) -> 0 | N23: Received | O23: =IF(N23="Cancelled",0,IF(K23<>"",MAX(0,K23-J23),IF(N23="Delayed",MAX(0,'Daily MIS Report'!$B$4-J23),0))) -> 0
A24: PO0020 | B24: 46163 | C24: SUP012 | D24: =VLOOKUP(C24,'Supplier Database'!$A$5:$K$29,2,FALSE()) -> Lotus Logistics | E24: PRD087 | F24: =VLOOKUP(E24,'Product Master'!$A$5:$K$104,2,FALSE()) -> Compact Apparel Item 087 | G24: 403 | H24: 5511.26 | I24: =G24*H24 -> 2221037.8 | J24: 46173 | K24: 46178 | L24: 327 | M24: =MAX(0,G24-L24) -> 76 | N24: Partially Received | O24: =IF(N24="Cancelled",0,IF(K24<>"",MAX(0,K24-J24),IF(N24="Delayed",MAX(0,'Daily MIS Report'!$B$4-J24),0))) -> 5
A25: PO0021 | B25: 46121 | C25: SUP004 | D25: =VLOOKUP(C25,'Supplier Database'!$A$5:$K$29,2,FALSE()) -> Delta Trading Co. | E25: PRD087 | F25: =VLOOKUP(E25,'Product Master'!$A$5:$K$104,2,FALSE()) -> Compact Apparel Item 087 | G25: 139 | H25: 5381.11 | I25: =G25*H25 -> 747974.29 | J25: 46131 | K25: 46134 | L25: 84 | M25: =MAX(0,G25-L25) -> 55 | N25: Partially Received | O25: =IF(N25="Cancelled",0,IF(K25<>"",MAX(0,K25-J25),IF(N25="Delayed",MAX(0,'Daily MIS Report'!$B$4-J25),0))) -> 3
A26: PO0022 | B26: 46243 | C26: SUP008 | D26: =VLOOKUP(C26,'Supplier Database'!$A$5:$K$29,2,FALSE()) -> Horizon Supplies | E26: PRD083 | F26: =VLOOKUP(E26,'Product Master'!$A$5:$K$104,2,FALSE()) -> Essential Office Item 083 | G26: 52 | H26: 2576.46 | I26: =G26*H26 -> 133975.92 | J26: 46248 | K26: 46248 | L26: 52 | M26: =MAX(0,G26-L26) -> 0 | N26: Received | O26: =IF(N26="Cancelled",0,IF(K26<>"",MAX(0,K26-J26),IF(N26="Delayed",MAX(0,'Daily MIS Report'!$B$4-J26),0))) -> 0
A27: PO0023 | B27: 46263 | C27: SUP014 | D27: =VLOOKUP(C27,'Supplier Database'!$A$5:$K$29,2,FALSE()) -> Northstar Partners | E27: PRD015 | F27: =VLOOKUP(E27,'Product Master'!$A$5:$K$104,2,FALSE()) -> Classic Apparel Item 015 | G27: 91 | H27: 969.87 | I27: =G27*H27 -> 88258.17 | J27: 46266 | K27: 46266 | L27: 91 | M27: =MAX(0,G27-L27) -> 0 | N27: Received | O27: =IF(N27="Cancelled",0,IF(K27<>"",MAX(0,K27-J27),IF(N27="Delayed",MAX(0,'Daily MIS Report'!$B$4-J27),0))) -> 0
A28: PO0024 | B28: 45990 | C28: SUP004 | D28: =VLOOKUP(C28,'Supplier Database'!$A$5:$K$29,2,FALSE()) -> Delta Trading Co. | E28: PRD031 | F28: =VLOOKUP(E28,'Product Master'!$A$5:$K$104,2,FALSE()) -> Essential Apparel Item 031 | G28: 474 | H28: 8184.47 | I28: =G28*H28 -> 3879438.8 | J28: 46000 | K28: 46001 | L28: 474 | M28: =MAX(0,G28-L28) -> 0 | N28: Received | O28: =IF(N28="Cancelled",0,IF(K28<>"",MAX(0,K28-J28),IF(N28="Delayed",MAX(0,'Daily MIS Report'!$B$4-J28),0))) -> 1
A29: PO0025 | B29: 46274 | C29: SUP024 | D29: =VLOOKUP(C29,'Supplier Database'!$A$5:$K$29,2,FALSE()) -> Yugma Industries | E29: PRD090 | F29: =VLOOKUP(E29,'Product Master'!$A$5:$K$104,2,FALSE()) -> Compact Home Item 090 | G29: 296 | H29: 8253.57 | I29: =G29*H29 -> 2443056.7 | J29: 46277 | L29: 0 | M29: =MAX(0,G29-L29) -> 296 | N29: Pending | O29: =IF(N29="Cancelled",0,IF(K29<>"",MAX(0,K29-J29),IF(N29="Delayed",MAX(0,'Daily MIS Report'!$B$4-J29),0))) -> 0
A30: PO0026 | B30: 46010 | C30: SUP014 | D30: =VLOOKUP(C30,'Supplier Database'!$A$5:$K$29,2,FALSE()) -> Northstar Partners | E30: PRD084 | F30: =VLOOKUP(E30,'Product Master'!$A$5:$K$104,2,FALSE()) -> Eco Personal Item 084 | G30: 70 | H30: 2942.31 | I30: =G30*H30 -> 205961.7 | J30: 46013 | K30: 46014 | L30: 5 | M30: =MAX(0,G30-L30) -> 65 | N30: Partially Received | O30: =IF(N30="Cancelled",0,IF(K30<>"",MAX(0,K30-J30),IF(N30="Delayed",MAX(0,'Daily MIS Report'!$B$4-J30),0))) -> 1
A31: PO0027 | B31: 46284 | C31: SUP012 | D31: =VLOOKUP(C31,'Supplier Database'!$A$5:$K$29,2,FALSE()) -> Lotus Logistics | E31: PRD028 | F31: =VLOOKUP(E31,'Product Master'!$A$5:$K$104,2,FALSE()) -> Pro Personal Item 028 | G31: 247 | H31: 1776.84 | I31: =G31*H31 -> 438879.48 | J31: 46294 | K31: 46294 | L31: 247 | M31: =MAX(0,G31-L31) -> 0 | N31: Received | O31: =IF(N31="Cancelled",0,IF(K31<>"",MAX(0,K31-J31),IF(N31="Delayed",MAX(0,'Daily MIS Report'!$B$4-J31),0))) -> 0
A32: PO0028 | B32: 45981 | C32: SUP022 | D32: =VLOOKUP(C32,'Supplier Database'!$A$5:$K$29,2,FALSE()) -> Vertex Supplies | E32: PRD048 | F32: =VLOOKUP(E32,'Product Master'!$A$5:$K$104,2,FALSE()) -> Eco Automotive Item 048 | G32: 298 | H32: 351.35 | I32: =G32*H32 -> 104702.3 | J32: 45985 | K32: 45984 | L32: 204 | M32: =MAX(0,G32-L32) -> 94 | N32: Partially Received | O32: =IF(N32="Cancelled",0,IF(K32<>"",MAX(0,K32-J32),IF(N32="Delayed",MAX(0,'Daily MIS Report'!$B$4-J32),0))) -> 0
A33: PO0029 | B33: 46072 | C33: SUP007 | D33: =VLOOKUP(C33,'Supplier Database'!$A$5:$K$29,2,FALSE()) -> Global Partners | E33: PRD016 | F33: =VLOOKUP(E33,'Product Master'!$A$5:$K$104,2,FALSE()) -> Pro Automotive Item 016 | G33: 454 | H33: 4132.07 | I33: =G33*H33 -> 1875959.8 | J33: 46086 | K33: 46086 | L33: 454 | M33: =MAX(0,G33-L33) -> 0 | N33: Received | O33: =IF(N33="Cancelled",0,IF(K33<>"",MAX(0,K33-J33),IF(N33="Delayed",MAX(0,'Daily MIS Report'!$B$4-J33),0))) -> 0
A34: PO0030 | B34: 46259 | C34: SUP021 | D34: =VLOOKUP(C34,'Supplier Database'!$A$5:$K$29,2,FALSE()) -> Unity Partners | E34: PRD077 | F34: =VLOOKUP(E34,'Product Master'!$A$5:$K$104,2,FALSE()) -> Everyday Industrial Item 077 | G34: 30 | H34: 2524.38 | I34: =G34*H34 -> 75731.4 | J34: 46263 | K34: 46262 | L34: 30 | M34: =MAX(0,G34-L34) -> 0 | N34: Received | O34: =IF(N34="Cancelled",0,IF(K34<>"",MAX(0,K34-J34),IF(N34="Delayed",MAX(0,'Daily MIS Report'!$B$4-J34),0))) -> 0
A35: PO0031 | B35: 46220 | C35: SUP007 | D35: =VLOOKUP(C35,'Supplier Database'!$A$5:$K$29,2,FALSE()) -> Global Partners | E35: PRD009 | F35: =VLOOKUP(E35,'Product Master'!$A$5:$K$104,2,FALSE()) -> Essential Electronics Item 009 | G35: 444 | H35: 3944.21 | I35: =G35*H35 -> 1751229.2 | J35: 46234 | K35: 46234 | L35: 444 | M35: =MAX(0,G35-L35) -> 0 | N35: Received | O35: =IF(N35="Cancelled",0,IF(K35<>"",MAX(0,K35-J35),IF(N35="Delayed",MAX(0,'Daily MIS Report'!$B$4-J35),0))) -> 0
A36: PO0032 | B36: 46050 | C36: SUP011 | D36: =VLOOKUP(C36,'Supplier Database'!$A$5:$K$29,2,FALSE()) -> Kinetic Trading Co. | E36: PRD100 | F36: =VLOOKUP(E36,'Product Master'!$A$5:$K$104,2,FALSE()) -> Smart Personal Item 100 | G36: 95 | H36: 7574.88 | I36: =G36*H36 -> 719613.6 | J36: 46062 | K36: 46063 | L36: 19 | M36: =MAX(0,G36-L36) -> 76 | N36: Partially Received | O36: =IF(N36="Cancelled",0,IF(K36<>"",MAX(0,K36-J36),IF(N36="Delayed",MAX(0,'Daily MIS Report'!$B$4-J36),0))) -> 1
A37: PO0033 | B37: 45997 | C37: SUP018 | D37: =VLOOKUP(C37,'Supplier Database'!$A$5:$K$29,2,FALSE()) -> Riverstone Trading Co. | E37: PRD033 | F37: =VLOOKUP(E37,'Product Master'!$A$5:$K$104,2,FALSE()) -> Compact Electronics Item 033 | G37: 428 | H37: 7417.92 | I37: =G37*H37 -> 3174869.8 | J37: 46009 | K37: 46008 | L37: 68 | M37: =MAX(0,G37-L37) -> 360 | N37: Partially Received | O37: =IF(N37="Cancelled",0,IF(K37<>"",MAX(0,K37-J37),IF(N37="Delayed",MAX(0,'Daily MIS Report'!$B$4-J37),0))) -> 0
A38: PO0034 | B38: 45938 | C38: SUP012 | D38: =VLOOKUP(C38,'Supplier Database'!$A$5:$K$29,2,FALSE()) -> Lotus Logistics | E38: PRD031 | F38: =VLOOKUP(E38,'Product Master'!$A$5:$K$104,2,FALSE()) -> Essential Apparel Item 031 | G38: 321 | H38: 7975.46 | I38: =G38*H38 -> 2560122.7 | J38: 45948 | K38: 45945 | L38: 321 | M38: =MAX(0,G38-L38) -> 0 | N38: Received | O38: =IF(N38="Cancelled",0,IF(K38<>"",MAX(0,K38-J38),IF(N38="Delayed",MAX(0,'Daily MIS Report'!$B$4-J38),0))) -> 0
A39: PO0035 | B39: 45995 | C39: SUP024 | D39: =VLOOKUP(C39,'Supplier Database'!$A$5:$K$29,2,FALSE()) -> Yugma Industries | E39: PRD054 | F39: =VLOOKUP(E39,'Product Master'!$A$5:$K$104,2,FALSE()) -> Pro Packaging Item 054 | G39: 289 | H39: 4849.19 | I39: =G39*H39 -> 1401415.9 | J39: 45998 | K39: 45998 | L39: 289 | M39: =MAX(0,G39-L39) -> 0 | N39: Received | O39: =IF(N39="Cancelled",0,IF(K39<>"",MAX(0,K39-J39),IF(N39="Delayed",MAX(0,'Daily MIS Report'!$B$4-J39),0))) -> 0
A40: PO0036 | B40: 46116 | C40: SUP017 | D40: =VLOOKUP(C40,'Supplier Database'!$A$5:$K$29,2,FALSE()) -> Quantum Industries | E40: PRD076 | F40: =VLOOKUP(E40,'Product Master'!$A$5:$K$104,2,FALSE()) -> Everyday Personal Item 076 | G40: 75 | H40: 6723.28 | I40: =G40*H40 -> 504246 | J40: 46121 | K40: 46118 | L40: 75 | M40: =MAX(0,G40-L40) -> 0 | N40: Received | O40: =IF(N40="Cancelled",0,IF(K40<>"",MAX(0,K40-J40),IF(N40="Delayed",MAX(0,'Daily MIS Report'!$B$4-J40),0))) -> 0
A41: PO0037 | B41: 46303 | C41: SUP022 | D41: =VLOOKUP(C41,'Supplier Database'!$A$5:$K$29,2,FALSE()) -> Vertex Supplies | E41: PRD067 | F41: =VLOOKUP(E41,'Product Master'!$A$5:$K$104,2,FALSE()) -> Premium Office Item 067 | G41: 174 | H41: 2224.51 | I41: =G41*H41 -> 387064.74 | J41: 46307 | L41: 0 | M41: =MAX(0,G41-L41) -> 174 | N41: Cancelled | O41: =IF(N41="Cancelled",0,IF(K41<>"",MAX(0,K41-J41),IF(N41="Delayed",MAX(0,'Daily MIS Report'!$B$4-J41),0))) -> 0
A42: PO0038 | B42: 45962 | C42: SUP016 | D42: =VLOOKUP(C42,'Supplier Database'!$A$5:$K$29,2,FALSE()) -> Pioneer Distributors | E42: PRD052 | F42: =VLOOKUP(E42,'Product Master'!$A$5:$K$104,2,FALSE()) -> Compact Personal Item 052 | G42: 238 | H42: 5567.82 | I42: =G42*H42 -> 1325141.2 | J42: 45969 | K42: 45973 | L42: 238 | M42: =MAX(0,G42-L42) -> 0 | N42: Received | O42: =IF(N42="Cancelled",0,IF(K42<>"",MAX(0,K42-J42),IF(N42="Delayed",MAX(0,'Daily MIS Report'!$B$4-J42),0))) -> 4
A43: PO0039 | B43: 45968 | C43: SUP003 | D43: =VLOOKUP(C43,'Supplier Database'!$A$5:$K$29,2,FALSE()) -> Core Industries | E43: PRD042 | F43: =VLOOKUP(E43,'Product Master'!$A$5:$K$104,2,FALSE()) -> Compact Home Item 042 | G43: 331 | H43: 3555.14 | I43: =G43*H43 -> 1176751.3 | J43: 45971 | K43: 45978 | L43: 331 | M43: =MAX(0,G43-L43) -> 0 | N43: Received | O43: =IF(N43="Cancelled",0,IF(K43<>"",MAX(0,K43-J43),IF(N43="Delayed",MAX(0,'Daily MIS Report'!$B$4-J43),0))) -> 7
A44: PO0040 | B44: 46295 | C44: SUP011 | D44: =VLOOKUP(C44,'Supplier Database'!$A$5:$K$29,2,FALSE()) -> Kinetic Trading Co. | E44: PRD049 | F44: =VLOOKUP(E44,'Product Master'!$A$5:$K$104,2,FALSE()) -> Premium Electronics Item 049 | G44: 325 | H44: 5929.01 | I44: =G44*H44 -> 1926928.2 | J44: 46307 | K44: 46309 | L44: 325 | M44: =MAX(0,G44-L44) -> 0 | N44: Received | O44: =IF(N44="Cancelled",0,IF(K44<>"",MAX(0,K44-J44),IF(N44="Delayed",MAX(0,'Daily MIS Report'!$B$4-J44),0))) -> 2
A45: PO0041 | B45: 46302 | C45: SUP023 | D45: =VLOOKUP(C45,'Supplier Database'!$A$5:$K$29,2,FALSE()) -> Westline Distributors | E45: PRD015 | F45: =VLOOKUP(E45,'Product Master'!$A$5:$K$104,2,FALSE()) -> Classic Apparel Item 015 | G45: 456 | H45: 1044.89 | I45: =G45*H45 -> 476469.84 | J45: 46309 | L45: 8 | M45: =MAX(0,G45-L45) -> 448 | N45: Delayed | O45: =IF(N45="Cancelled",0,IF(K45<>"",MAX(0,K45-J45),IF(N45="Delayed",MAX(0,'Daily MIS Report'!$B$4-J45),0))) -> 5
A46: PO0042 | B46: 46300 | C46: SUP007 | D46: =VLOOKUP(C46,'Supplier Database'!$A$5:$K$29,2,FALSE()) -> Global Partners | E46: PRD056 | F46: =VLOOKUP(E46,'Product Master'!$A$5:$K$104,2,FALSE()) -> Smart Automotive Item 056 | G46: 251 | H46: 2976.05 | I46: =G46*H46 -> 746988.55 | J46: 46314 | K46: 46314 | L46: 251 | M46: =MAX(0,G46-L46) -> 0 | N46: Received | O46: =IF(N46="Cancelled",0,IF(K46<>"",MAX(0,K46-J46),IF(N46="Delayed",MAX(0,'Daily MIS Report'!$B$4-J46),0))) -> 0
A47: PO0043 | B47: 46135 | C47: SUP014 | D47: =VLOOKUP(C47,'Supplier Database'!$A$5:$K$29,2,FALSE()) -> Northstar Partners | E47: PRD094 | F47: =VLOOKUP(E47,'Product Master'!$A$5:$K$104,2,FALSE()) -> Classic Packaging Item 094 | G47: 68 | H47: 4638.33 | I47: =G47*H47 -> 315406.44 | J47: 46138 | K47: 46138 | L47: 68 | M47: =MAX(0,G47-L47) -> 0 | N47: Received | O47: =IF(N47="Cancelled",0,IF(K47<>"",MAX(0,K47-J47),IF(N47="Delayed",MAX(0,'Daily MIS Report'!$B$4-J47),0))) -> 0
A48: PO0044 | B48: 46122 | C48: SUP005 | D48: =VLOOKUP(C48,'Supplier Database'!$A$5:$K$29,2,FALSE()) -> Ever Logistics | E48: PRD088 | F48: =VLOOKUP(E48,'Product Master'!$A$5:$K$104,2,FALSE()) -> Premium Automotive Item 088 | G48: 492 | H48: 898.31 | I48: =G48*H48 -> 441968.52 | J48: 46125 | K48: 46123 | L48: 492 | M48: =MAX(0,G48-L48) -> 0 | N48: Received | O48: =IF(N48="Cancelled",0,IF(K48<>"",MAX(0,K48-J48),IF(N48="Delayed",MAX(0,'Daily MIS Report'!$B$4-J48),0))) -> 0
A49: PO0045 | B49: 46302 | C49: SUP014 | D49: =VLOOKUP(C49,'Supplier Database'!$A$5:$K$29,2,FALSE()) -> Northstar Partners | E49: PRD013 | F49: =VLOOKUP(E49,'Product Master'!$A$5:$K$104,2,FALSE()) -> Eco Industrial Item 013 | G49: 401 | H49: 8538.47 | I49: =G49*H49 -> 3423926.5 | J49: 46311 | L49: 8 | M49: =MAX(0,G49-L49) -> 393 | N49: Delayed | O49: =IF(N49="Cancelled",0,IF(K49<>"",MAX(0,K49-J49),IF(N49="Delayed",MAX(0,'Daily MIS Report'!$B$4-J49),0))) -> 3
A50: PO0046 | B50: 45961 | C50: SUP019 | D50: =VLOOKUP(C50,'Supplier Database'!$A$5:$K$29,2,FALSE()) -> Summit Logistics | E50: PRD072 | F50: =VLOOKUP(E50,'Product Master'!$A$5:$K$104,2,FALSE()) -> Premium Automotive Item 072 | G50: 307 | H50: 1406.78 | I50: =G50*H50 -> 431881.46 | J50: 45966 | K50: 45966 | L50: 307 | M50: =MAX(0,G50-L50) -> 0 | N50: Received | O50: =IF(N50="Cancelled",0,IF(K50<>"",MAX(0,K50-J50),IF(N50="Delayed",MAX(0,'Daily MIS Report'!$B$4-J50),0))) -> 0
A51: PO0047 | B51: 46271 | C51: SUP025 | D51: =VLOOKUP(C51,'Supplier Database'!$A$5:$K$29,2,FALSE()) -> Zenith Trading Co. | E51: PRD055 | F51: =VLOOKUP(E51,'Product Master'!$A$5:$K$104,2,FALSE()) -> Eco Apparel Item 055 | G51: 464 | H51: 2271.55 | I51: =G51*H51 -> 1053999.2 | J51: 46276 | K51: 46276 | L51: 464 | M51: =MAX(0,G51-L51) -> 0 | N51: Received | O51: =IF(N51="Cancelled",0,IF(K51<>"",MAX(0,K51-J51),IF(N51="Delayed",MAX(0,'Daily MIS Report'!$B$4-J51),0))) -> 0
A52: PO0048 | B52: 46238 | C52: SUP010 | D52: =VLOOKUP(C52,'Supplier Database'!$A$5:$K$29,2,FALSE()) -> Jupiter Industries | E52: PRD046 | F52: =VLOOKUP(E52,'Product Master'!$A$5:$K$104,2,FALSE()) -> Classic Packaging Item 046 | G52: 73 | H52: 5376.6 | I52: =G52*H52 -> 392491.8 | J52: 46252 | K52: 46256 | L52: 73 | M52: =MAX(0,G52-L52) -> 0 | N52: Received | O52: =IF(N52="Cancelled",0,IF(K52<>"",MAX(0,K52-J52),IF(N52="Delayed",MAX(0,'Daily MIS Report'!$B$4-J52),0))) -> 4
A53: PO0049 | B53: 46045 | C53: SUP004 | D53: =VLOOKUP(C53,'Supplier Database'!$A$5:$K$29,2,FALSE()) -> Delta Trading Co. | E53: PRD045 | F53: =VLOOKUP(E53,'Product Master'!$A$5:$K$104,2,FALSE()) -> Essential Industrial Item 045 | G53: 452 | H53: 6711.74 | I53: =G53*H53 -> 3033706.5 | J53: 46055 | K53: 46055 | L53: 452 | M53: =MAX(0,G53-L53) -> 0 | N53: Received | O53: =IF(N53="Cancelled",0,IF(K53<>"",MAX(0,K53-J53),IF(N53="Delayed",MAX(0,'Daily MIS Report'!$B$4-J53),0))) -> 0
A54: PO0050 | B54: 46224 | C54: SUP008 | D54: =VLOOKUP(C54,'Supplier Database'!$A$5:$K$29,2,FALSE()) -> Horizon Supplies | E54: PRD055 | F54: =VLOOKUP(E54,'Product Master'!$A$5:$K$104,2,FALSE()) -> Eco Apparel Item 055 | G54: 452 | H54: 2179.41 | I54: =G54*H54 -> 985093.32 | J54: 46229 | L54: 0 | M54: =MAX(0,G54-L54) -> 452 | N54: Pending | O54: =IF(N54="Cancelled",0,IF(K54<>"",MAX(0,K54-J54),IF(N54="Delayed",MAX(0,'Daily MIS Report'!$B$4-J54),0))) -> 0
A55: PO0051 | B55: 46249 | C55: SUP020 | D55: =VLOOKUP(C55,'Supplier Database'!$A$5:$K$29,2,FALSE()) -> Trident Wholesale | E55: PRD087 | F55: =VLOOKUP(E55,'Product Master'!$A$5:$K$104,2,FALSE()) -> Compact Apparel Item 087 | G55: 349 | H55: 5436.35 | I55: =G55*H55 -> 1897286.1 | J55: 46261 | K55: 46265 | L55: 137 | M55: =MAX(0,G55-L55) -> 212 | N55: Partially Received | O55: =IF(N55="Cancelled",0,IF(K55<>"",MAX(0,K55-J55),IF(N55="Delayed",MAX(0,'Daily MIS Report'!$B$4-J55),0))) -> 4
A56: PO0052 | B56: 46302 | C56: SUP006 | D56: =VLOOKUP(C56,'Supplier Database'!$A$5:$K$29,2,FALSE()) -> Frontier Wholesale | E56: PRD035 | F56: =VLOOKUP(E56,'Product Master'!$A$5:$K$104,2,FALSE()) -> Smart Office Item 035 | G56: 379 | H56: 6291.58 | I56: =G56*H56 -> 2384508.8 | J56: 46310 | L56: 5 | M56: =MAX(0,G56-L56) -> 374 | N56: Delayed | O56: =IF(N56="Cancelled",0,IF(K56<>"",MAX(0,K56-J56),IF(N56="Delayed",MAX(0,'Daily MIS Report'!$B$4-J56),0))) -> 4
A57: PO0053 | B57: 45934 | C57: SUP006 | D57: =VLOOKUP(C57,'Supplier Database'!$A$5:$K$29,2,FALSE()) -> Frontier Wholesale | E57: PRD019 | F57: =VLOOKUP(E57,'Product Master'!$A$5:$K$104,2,FALSE()) -> Everyday Office Item 019 | G57: 309 | H57: 2352.58 | I57: =G57*H57 -> 726947.22 | J57: 45945 | K57: 45942 | L57: 309 | M57: =MAX(0,G57-L57) -> 0 | N57: Received | O57: =IF(N57="Cancelled",0,IF(K57<>"",MAX(0,K57-J57),IF(N57="Delayed",MAX(0,'Daily MIS Report'!$B$4-J57),0))) -> 0
A58: PO0054 | B58: 45977 | C58: SUP024 | D58: =VLOOKUP(C58,'Supplier Database'!$A$5:$K$29,2,FALSE()) -> Yugma Industries | E58: PRD068 | F58: =VLOOKUP(E58,'Product Master'!$A$5:$K$104,2,FALSE()) -> Compact Personal Item 068 | G58: 130 | H58: 4881.82 | I58: =G58*H58 -> 634636.6 | J58: 45980 | K58: 45979 | L58: 130 | M58: =MAX(0,G58-L58) -> 0 | N58: Received | O58: =IF(N58="Cancelled",0,IF(K58<>"",MAX(0,K58-J58),IF(N58="Delayed",MAX(0,'Daily MIS Report'!$B$4-J58),0))) -> 0
A59: PO0055 | B59: 46120 | C59: SUP010 | D59: =VLOOKUP(C59,'Supplier Database'!$A$5:$K$29,2,FALSE()) -> Jupiter Industries | E59: PRD093 | F59: =VLOOKUP(E59,'Product Master'!$A$5:$K$104,2,FALSE()) -> Compact Industrial Item 093 | G59: 186 | H59: 5145.19 | I59: =G59*H59 -> 957005.34 | J59: 46134 | K59: 46133 | L59: 14 | M59: =MAX(0,G59-L59) -> 172 | N59: Partially Received | O59: =IF(N59="Cancelled",0,IF(K59<>"",MAX(0,K59-J59),IF(N59="Delayed",MAX(0,'Daily MIS Report'!$B$4-J59),0))) -> 0
A60: PO0056 | B60: 46010 | C60: SUP006 | D60: =VLOOKUP(C60,'Supplier Database'!$A$5:$K$29,2,FALSE()) -> Frontier Wholesale | E60: PRD097 | F60: =VLOOKUP(E60,'Product Master'!$A$5:$K$104,2,FALSE()) -> Smart Electronics Item 097 | G60: 336 | H60: 1114.3 | I60: =G60*H60 -> 374404.8 | J60: 46021 | K60: 46025 | L60: 336 | M60: =MAX(0,G60-L60) -> 0 | N60: Received | O60: =IF(N60="Cancelled",0,IF(K60<>"",MAX(0,K60-J60),IF(N60="Delayed",MAX(0,'Daily MIS Report'!$B$4-J60),0))) -> 4
A61: PO0057 | B61: 46269 | C61: SUP014 | D61: =VLOOKUP(C61,'Supplier Database'!$A$5:$K$29,2,FALSE()) -> Northstar Partners | E61: PRD063 | F61: =VLOOKUP(E61,'Product Master'!$A$5:$K$104,2,FALSE()) -> Everyday Apparel Item 063 | G61: 330 | H61: 2420.12 | I61: =G61*H61 -> 798639.6 | J61: 46272 | K61: 46272 | L61: 330 | M61: =MAX(0,G61-L61) -> 0 | N61: Received | O61: =IF(N61="Cancelled",0,IF(K61<>"",MAX(0,K61-J61),IF(N61="Delayed",MAX(0,'Daily MIS Report'!$B$4-J61),0))) -> 0
A62: PO0058 | B62: 45989 | C62: SUP012 | D62: =VLOOKUP(C62,'Supplier Database'!$A$5:$K$29,2,FALSE()) -> Lotus Logistics | E62: PRD056 | F62: =VLOOKUP(E62,'Product Master'!$A$5:$K$104,2,FALSE()) -> Smart Automotive Item 056 | G62: 76 | H62: 2769.66 | I62: =G62*H62 -> 210494.16 | J62: 45999 | K62: 46001 | L62: 68 | M62: =MAX(0,G62-L62) -> 8 | N62: Partially Received | O62: =IF(N62="Cancelled",0,IF(K62<>"",MAX(0,K62-J62),IF(N62="Delayed",MAX(0,'Daily MIS Report'!$B$4-J62),0))) -> 2
A63: PO0059 | B63: 46272 | C63: SUP010 | D63: =VLOOKUP(C63,'Supplier Database'!$A$5:$K$29,2,FALSE()) -> Jupiter Industries | E63: PRD006 | F63: =VLOOKUP(E63,'Product Master'!$A$5:$K$104,2,FALSE()) -> Pro Packaging Item 006 | G63: 132 | H63: 1404.77 | I63: =G63*H63 -> 185429.64 | J63: 46286 | K63: 46285 | L63: 53 | M63: =MAX(0,G63-L63) -> 79 | N63: Partially Received | O63: =IF(N63="Cancelled",0,IF(K63<>"",MAX(0,K63-J63),IF(N63="Delayed",MAX(0,'Daily MIS Report'!$B$4-J63),0))) -> 0
A64: PO0060 | B64: 46085 | C64: SUP007 | D64: =VLOOKUP(C64,'Supplier Database'!$A$5:$K$29,2,FALSE()) -> Global Partners | E64: PRD099 | F64: =VLOOKUP(E64,'Product Master'!$A$5:$K$104,2,FALSE()) -> Eco Office Item 099 | G64: 90 | H64: 6880.59 | I64: =G64*H64 -> 619253.1 | J64: 46099 | K64: 46097 | L64: 90 | M64: =MAX(0,G64-L64) -> 0 | N64: Received | O64: =IF(N64="Cancelled",0,IF(K64<>"",MAX(0,K64-J64),IF(N64="Delayed",MAX(0,'Daily MIS Report'!$B$4-J64),0))) -> 0
A65: PO0061 | B65: 45934 | C65: SUP016 | D65: =VLOOKUP(C65,'Supplier Database'!$A$5:$K$29,2,FALSE()) -> Pioneer Distributors | E65: PRD096 | F65: =VLOOKUP(E65,'Product Master'!$A$5:$K$104,2,FALSE()) -> Eco Automotive Item 096 | G65: 240 | H65: 5795.15 | I65: =G65*H65 -> 1390836 | J65: 45941 | K65: 45941 | L65: 240 | M65: =MAX(0,G65-L65) -> 0 | N65: Received | O65: =IF(N65="Cancelled",0,IF(K65<>"",MAX(0,K65-J65),IF(N65="Delayed",MAX(0,'Daily MIS Report'!$B$4-J65),0))) -> 0
A66: PO0062 | B66: 46187 | C66: SUP018 | D66: =VLOOKUP(C66,'Supplier Database'!$A$5:$K$29,2,FALSE()) -> Riverstone Trading Co. | E66: PRD086 | F66: =VLOOKUP(E66,'Product Master'!$A$5:$K$104,2,FALSE()) -> Classic Packaging Item 086 | G66: 432 | H66: 4639.82 | I66: =G66*H66 -> 2004402.2 | J66: 46199 | K66: 46202 | L66: 432 | M66: =MAX(0,G66-L66) -> 0 | N66: Received | O66: =IF(N66="Cancelled",0,IF(K66<>"",MAX(0,K66-J66),IF(N66="Delayed",MAX(0,'Daily MIS Report'!$B$4-J66),0))) -> 3
A67: PO0063 | B67: 46154 | C67: SUP001 | D67: =VLOOKUP(C67,'Supplier Database'!$A$5:$K$29,2,FALSE()) -> Apex Supplies | E67: PRD059 | F67: =VLOOKUP(E67,'Product Master'!$A$5:$K$104,2,FALSE()) -> Eco Office Item 059 | G67: 491 | H67: 251.1 | I67: =G67*H67 -> 123290.1 | J67: 46157 | K67: 46157 | L67: 491 | M67: =MAX(0,G67-L67) -> 0 | N67: Received | O67: =IF(N67="Cancelled",0,IF(K67<>"",MAX(0,K67-J67),IF(N67="Delayed",MAX(0,'Daily MIS Report'!$B$4-J67),0))) -> 0
A68: PO0064 | B68: 46224 | C68: SUP013 | D68: =VLOOKUP(C68,'Supplier Database'!$A$5:$K$29,2,FALSE()) -> Meridian Wholesale | E68: PRD091 | F68: =VLOOKUP(E68,'Product Master'!$A$5:$K$104,2,FALSE()) -> Premium Office Item 091 | G68: 347 | H68: 4335.81 | I68: =G68*H68 -> 1504526.1 | J68: 46226 | K68: 46228 | L68: 347 | M68: =MAX(0,G68-L68) -> 0 | N68: Received | O68: =IF(N68="Cancelled",0,IF(K68<>"",MAX(0,K68-J68),IF(N68="Delayed",MAX(0,'Daily MIS Report'!$B$4-J68),0))) -> 2
A69: PO0065 | B69: 46302 | C69: SUP006 | D69: =VLOOKUP(C69,'Supplier Database'!$A$5:$K$29,2,FALSE()) -> Frontier Wholesale | E69: PRD080 | F69: =VLOOKUP(E69,'Product Master'!$A$5:$K$104,2,FALSE()) -> Classic Automotive Item 080 | G69: 255 | H69: 1651.37 | I69: =G69*H69 -> 421099.35 | J69: 46309 | L69: 1 | M69: =MAX(0,G69-L69) -> 254 | N69: Delayed | O69: =IF(N69="Cancelled",0,IF(K69<>"",MAX(0,K69-J69),IF(N69="Delayed",MAX(0,'Daily MIS Report'!$B$4-J69),0))) -> 5
A70: PO0066 | B70: 46154 | C70: SUP004 | D70: =VLOOKUP(C70,'Supplier Database'!$A$5:$K$29,2,FALSE()) -> Delta Trading Co. | E70: PRD032 | F70: =VLOOKUP(E70,'Product Master'!$A$5:$K$104,2,FALSE()) -> Smart Automotive Item 032 | G70: 243 | H70: 6908.77 | I70: =G70*H70 -> 1678831.1 | J70: 46164 | K70: 46164 | L70: 243 | M70: =MAX(0,G70-L70) -> 0 | N70: Received | O70: =IF(N70="Cancelled",0,IF(K70<>"",MAX(0,K70-J70),IF(N70="Delayed",MAX(0,'Daily MIS Report'!$B$4-J70),0))) -> 0
A71: PO0067 | B71: 46089 | C71: SUP024 | D71: =VLOOKUP(C71,'Supplier Database'!$A$5:$K$29,2,FALSE()) -> Yugma Industries | E71: PRD044 | F71: =VLOOKUP(E71,'Product Master'!$A$5:$K$104,2,FALSE()) -> Essential Personal Item 044 | G71: 133 | H71: 790.22 | I71: =G71*H71 -> 105099.26 | J71: 46092 | K71: 46092 | L71: 133 | M71: =MAX(0,G71-L71) -> 0 | N71: Received | O71: =IF(N71="Cancelled",0,IF(K71<>"",MAX(0,K71-J71),IF(N71="Delayed",MAX(0,'Daily MIS Report'!$B$4-J71),0))) -> 0
A72: PO0068 | B72: 46255 | C72: SUP004 | D72: =VLOOKUP(C72,'Supplier Database'!$A$5:$K$29,2,FALSE()) -> Delta Trading Co. | E72: PRD068 | F72: =VLOOKUP(E72,'Product Master'!$A$5:$K$104,2,FALSE()) -> Compact Personal Item 068 | G72: 281 | H72: 4773.42 | I72: =G72*H72 -> 1341331 | J72: 46265 | L72: 0 | M72: =MAX(0,G72-L72) -> 281 | N72: Pending | O72: =IF(N72="Cancelled",0,IF(K72<>"",MAX(0,K72-J72),IF(N72="Delayed",MAX(0,'Daily MIS Report'!$B$4-J72),0))) -> 0
A73: PO0069 | B73: 46110 | C73: SUP024 | D73: =VLOOKUP(C73,'Supplier Database'!$A$5:$K$29,2,FALSE()) -> Yugma Industries | E73: PRD083 | F73: =VLOOKUP(E73,'Product Master'!$A$5:$K$104,2,FALSE()) -> Essential Office Item 083 | G73: 437 | H73: 2428.09 | I73: =G73*H73 -> 1061075.3 | J73: 46113 | K73: 46113 | L73: 437 | M73: =MAX(0,G73-L73) -> 0 | N73: Received | O73: =IF(N73="Cancelled",0,IF(K73<>"",MAX(0,K73-J73),IF(N73="Delayed",MAX(0,'Daily MIS Report'!$B$4-J73),0))) -> 0
A74: PO0070 | B74: 46032 | C74: SUP006 | D74: =VLOOKUP(C74,'Supplier Database'!$A$5:$K$29,2,FALSE()) -> Frontier Wholesale | E74: PRD078 | F74: =VLOOKUP(E74,'Product Master'!$A$5:$K$104,2,FALSE()) -> Smart Packaging Item 078 | G74: 98 | H74: 468.21 | I74: =G74*H74 -> 45884.58 | J74: 46043 | K74: 46043 | L74: 81 | M74: =MAX(0,G74-L74) -> 17 | N74: Partially Received | O74: =IF(N74="Cancelled",0,IF(K74<>"",MAX(0,K74-J74),IF(N74="Delayed",MAX(0,'Daily MIS Report'!$B$4-J74),0))) -> 0
A75: PO0071 | B75: 46183 | C75: SUP015 | D75: =VLOOKUP(C75,'Supplier Database'!$A$5:$K$29,2,FALSE()) -> Orbit Supplies | E75: PRD097 | F75: =VLOOKUP(E75,'Product Master'!$A$5:$K$104,2,FALSE()) -> Smart Electronics Item 097 | G75: 308 | H75: 1214.67 | I75: =G75*H75 -> 374118.36 | J75: 46197 | K75: 46198 | L75: 308 | M75: =MAX(0,G75-L75) -> 0 | N75: Received | O75: =IF(N75="Cancelled",0,IF(K75<>"",MAX(0,K75-J75),IF(N75="Delayed",MAX(0,'Daily MIS Report'!$B$4-J75),0))) -> 1
A76: PO0072 | B76: 46252 | C76: SUP011 | D76: =VLOOKUP(C76,'Supplier Database'!$A$5:$K$29,2,FALSE()) -> Kinetic Trading Co. | E76: PRD020 | F76: =VLOOKUP(E76,'Product Master'!$A$5:$K$104,2,FALSE()) -> Eco Personal Item 020 | G76: 245 | H76: 2860.57 | I76: =G76*H76 -> 700839.65 | J76: 46264 | K76: 46264 | L76: 245 | M76: =MAX(0,G76-L76) -> 0 | N76: Received | O76: =IF(N76="Cancelled",0,IF(K76<>"",MAX(0,K76-J76),IF(N76="Delayed",MAX(0,'Daily MIS Report'!$B$4-J76),0))) -> 0
A77: PO0073 | B77: 46071 | C77: SUP019 | D77: =VLOOKUP(C77,'Supplier Database'!$A$5:$K$29,2,FALSE()) -> Summit Logistics | E77: PRD008 | F77: =VLOOKUP(E77,'Product Master'!$A$5:$K$104,2,FALSE()) -> Smart Automotive Item 008 | G77: 200 | H77: 7076.16 | I77: =G77*H77 -> 1415232 | J77: 46076 | K77: 46076 | L77: 200 | M77: =MAX(0,G77-L77) -> 0 | N77: Received | O77: =IF(N77="Cancelled",0,IF(K77<>"",MAX(0,K77-J77),IF(N77="Delayed",MAX(0,'Daily MIS Report'!$B$4-J77),0))) -> 0
A78: PO0074 | B78: 45950 | C78: SUP002 | D78: =VLOOKUP(C78,'Supplier Database'!$A$5:$K$29,2,FALSE()) -> Bright Distributors | E78: PRD048 | F78: =VLOOKUP(E78,'Product Master'!$A$5:$K$104,2,FALSE()) -> Eco Automotive Item 048 | G78: 445 | H78: 326.63 | I78: =G78*H78 -> 145350.35 | J78: 45958 | K78: 45963 | L78: 47 | M78: =MAX(0,G78-L78) -> 398 | N78: Partially Received | O78: =IF(N78="Cancelled",0,IF(K78<>"",MAX(0,K78-J78),IF(N78="Delayed",MAX(0,'Daily MIS Report'!$B$4-J78),0))) -> 5
A79: PO0075 | B79: 46245 | C79: SUP020 | D79: =VLOOKUP(C79,'Supplier Database'!$A$5:$K$29,2,FALSE()) -> Trident Wholesale | E79: PRD065 | F79: =VLOOKUP(E79,'Product Master'!$A$5:$K$104,2,FALSE()) -> Compact Electronics Item 065 | G79: 216 | H79: 4735.86 | I79: =G79*H79 -> 1022945.8 | J79: 46257 | K79: 46254 | L79: 216 | M79: =MAX(0,G79-L79) -> 0 | N79: Received | O79: =IF(N79="Cancelled",0,IF(K79<>"",MAX(0,K79-J79),IF(N79="Delayed",MAX(0,'Daily MIS Report'!$B$4-J79),0))) -> 0
A80: PO0076 | B80: 46161 | C80: SUP019 | D80: =VLOOKUP(C80,'Supplier Database'!$A$5:$K$29,2,FALSE()) -> Summit Logistics | E80: PRD084 | F80: =VLOOKUP(E80,'Product Master'!$A$5:$K$104,2,FALSE()) -> Eco Personal Item 084 | G80: 116 | H80: 2768.44 | I80: =G80*H80 -> 321139.04 | J80: 46166 | K80: 46165 | L80: 116 | M80: =MAX(0,G80-L80) -> 0 | N80: Received | O80: =IF(N80="Cancelled",0,IF(K80<>"",MAX(0,K80-J80),IF(N80="Delayed",MAX(0,'Daily MIS Report'!$B$4-J80),0))) -> 0
A81: PO0077 | B81: 45962 | C81: SUP015 | D81: =VLOOKUP(C81,'Supplier Database'!$A$5:$K$29,2,FALSE()) -> Orbit Supplies | E81: PRD014 | F81: =VLOOKUP(E81,'Product Master'!$A$5:$K$104,2,FALSE()) -> Pro Packaging Item 014 | G81: 435 | H81: 3042.78 | I81: =G81*H81 -> 1323609.3 | J81: 45976 | K81: 45974 | L81: 435 | M81: =MAX(0,G81-L81) -> 0 | N81: Received | O81: =IF(N81="Cancelled",0,IF(K81<>"",MAX(0,K81-J81),IF(N81="Delayed",MAX(0,'Daily MIS Report'!$B$4-J81),0))) -> 0
A82: PO0078 | B82: 46189 | C82: SUP021 | D82: =VLOOKUP(C82,'Supplier Database'!$A$5:$K$29,2,FALSE()) -> Unity Partners | E82: PRD023 | F82: =VLOOKUP(E82,'Product Master'!$A$5:$K$104,2,FALSE()) -> Eco Apparel Item 023 | G82: 40 | H82: 2556.89 | I82: =G82*H82 -> 102275.6 | J82: 46193 | K82: 46193 | L82: 40 | M82: =MAX(0,G82-L82) -> 0 | N82: Received | O82: =IF(N82="Cancelled",0,IF(K82<>"",MAX(0,K82-J82),IF(N82="Delayed",MAX(0,'Daily MIS Report'!$B$4-J82),0))) -> 0
A83: PO0079 | B83: 46302 | C83: SUP017 | D83: =VLOOKUP(C83,'Supplier Database'!$A$5:$K$29,2,FALSE()) -> Quantum Industries | E83: PRD079 | F83: =VLOOKUP(E83,'Product Master'!$A$5:$K$104,2,FALSE()) -> Essential Apparel Item 079 | G83: 101 | H83: 8047.21 | I83: =G83*H83 -> 812768.21 | J83: 46307 | L83: 6 | M83: =MAX(0,G83-L83) -> 95 | N83: Delayed | O83: =IF(N83="Cancelled",0,IF(K83<>"",MAX(0,K83-J83),IF(N83="Delayed",MAX(0,'Daily MIS Report'!$B$4-J83),0))) -> 7
A84: PO0080 | B84: 46140 | C84: SUP025 | D84: =VLOOKUP(C84,'Supplier Database'!$A$5:$K$29,2,FALSE()) -> Zenith Trading Co. | E84: PRD044 | F84: =VLOOKUP(E84,'Product Master'!$A$5:$K$104,2,FALSE()) -> Essential Personal Item 044 | G84: 367 | H84: 815.84 | I84: =G84*H84 -> 299413.28 | J84: 46145 | L84: 0 | M84: =MAX(0,G84-L84) -> 367 | N84: Pending | O84: =IF(N84="Cancelled",0,IF(K84<>"",MAX(0,K84-J84),IF(N84="Delayed",MAX(0,'Daily MIS Report'!$B$4-J84),0))) -> 0
A85: PO0081 | B85: 46262 | C85: SUP011 | D85: =VLOOKUP(C85,'Supplier Database'!$A$5:$K$29,2,FALSE()) -> Kinetic Trading Co. | E85: PRD009 | F85: =VLOOKUP(E85,'Product Master'!$A$5:$K$104,2,FALSE()) -> Essential Electronics Item 009 | G85: 188 | H85: 3636.58 | I85: =G85*H85 -> 683677.04 | J85: 46274 | K85: 46275 | L85: 65 | M85: =MAX(0,G85-L85) -> 123 | N85: Partially Received | O85: =IF(N85="Cancelled",0,IF(K85<>"",MAX(0,K85-J85),IF(N85="Delayed",MAX(0,'Daily MIS Report'!$B$4-J85),0))) -> 1
A86: PO0082 | B86: 46301 | C86: SUP022 | D86: =VLOOKUP(C86,'Supplier Database'!$A$5:$K$29,2,FALSE()) -> Vertex Supplies | E86: PRD078 | F86: =VLOOKUP(E86,'Product Master'!$A$5:$K$104,2,FALSE()) -> Smart Packaging Item 078 | G86: 467 | H86: 434.98 | I86: =G86*H86 -> 203135.66 | J86: 46305 | K86: 46308 | L86: 467 | M86: =MAX(0,G86-L86) -> 0 | N86: Received | O86: =IF(N86="Cancelled",0,IF(K86<>"",MAX(0,K86-J86),IF(N86="Delayed",MAX(0,'Daily MIS Report'!$B$4-J86),0))) -> 3
A87: PO0083 | B87: 46110 | C87: SUP010 | D87: =VLOOKUP(C87,'Supplier Database'!$A$5:$K$29,2,FALSE()) -> Jupiter Industries | E87: PRD084 | F87: =VLOOKUP(E87,'Product Master'!$A$5:$K$104,2,FALSE()) -> Eco Personal Item 084 | G87: 377 | H87: 2884.07 | I87: =G87*H87 -> 1087294.4 | J87: 46124 | K87: 46122 | L87: 377 | M87: =MAX(0,G87-L87) -> 0 | N87: Received | O87: =IF(N87="Cancelled",0,IF(K87<>"",MAX(0,K87-J87),IF(N87="Delayed",MAX(0,'Daily MIS Report'!$B$4-J87),0))) -> 0
A88: PO0084 | B88: 46302 | C88: SUP018 | D88: =VLOOKUP(C88,'Supplier Database'!$A$5:$K$29,2,FALSE()) -> Riverstone Trading Co. | E88: PRD049 | F88: =VLOOKUP(E88,'Product Master'!$A$5:$K$104,2,FALSE()) -> Premium Electronics Item 049 | G88: 349 | H88: 6114.1 | I88: =G88*H88 -> 2133820.9 | J88: 46308 | L88: 10 | M88: =MAX(0,G88-L88) -> 339 | N88: Delayed | O88: =IF(N88="Cancelled",0,IF(K88<>"",MAX(0,K88-J88),IF(N88="Delayed",MAX(0,'Daily MIS Report'!$B$4-J88),0))) -> 6
A89: PO0085 | B89: 46290 | C89: SUP024 | D89: =VLOOKUP(C89,'Supplier Database'!$A$5:$K$29,2,FALSE()) -> Yugma Industries | E89: PRD088 | F89: =VLOOKUP(E89,'Product Master'!$A$5:$K$104,2,FALSE()) -> Premium Automotive Item 088 | G89: 487 | H89: 903.94 | I89: =G89*H89 -> 440218.78 | J89: 46293 | K89: 46295 | L89: 261 | M89: =MAX(0,G89-L89) -> 226 | N89: Partially Received | O89: =IF(N89="Cancelled",0,IF(K89<>"",MAX(0,K89-J89),IF(N89="Delayed",MAX(0,'Daily MIS Report'!$B$4-J89),0))) -> 2
A90: PO0086 | B90: 46116 | C90: SUP001 | D90: =VLOOKUP(C90,'Supplier Database'!$A$5:$K$29,2,FALSE()) -> Apex Supplies | E90: PRD047 | F90: =VLOOKUP(E90,'Product Master'!$A$5:$K$104,2,FALSE()) -> Premium Apparel Item 047 | G90: 178 | H90: 2180.33 | I90: =G90*H90 -> 388098.74 | J90: 46119 | K90: 46119 | L90: 178 | M90: =MAX(0,G90-L90) -> 0 | N90: Received | O90: =IF(N90="Cancelled",0,IF(K90<>"",MAX(0,K90-J90),IF(N90="Delayed",MAX(0,'Daily MIS Report'!$B$4-J90),0))) -> 0
A91: PO0087 | B91: 46302 | C91: SUP008 | D91: =VLOOKUP(C91,'Supplier Database'!$A$5:$K$29,2,FALSE()) -> Horizon Supplies | E91: PRD018 | F91: =VLOOKUP(E91,'Product Master'!$A$5:$K$104,2,FALSE()) -> Smart Home Item 018 | G91: 99 | H91: 3293.27 | I91: =G91*H91 -> 326033.73 | J91: 46311 | L91: 1 | M91: =MAX(0,G91-L91) -> 98 | N91: Delayed | O91: =IF(N91="Cancelled",0,IF(K91<>"",MAX(0,K91-J91),IF(N91="Delayed",MAX(0,'Daily MIS Report'!$B$4-J91),0))) -> 3
A92: PO0088 | B92: 46190 | C92: SUP025 | D92: =VLOOKUP(C92,'Supplier Database'!$A$5:$K$29,2,FALSE()) -> Zenith Trading Co. | E92: PRD070 | F92: =VLOOKUP(E92,'Product Master'!$A$5:$K$104,2,FALSE()) -> Eco Packaging Item 070 | G92: 447 | H92: 3939.68 | I92: =G92*H92 -> 1761037 | J92: 46195 | K92: 46196 | L92: 447 | M92: =MAX(0,G92-L92) -> 0 | N92: Received | O92: =IF(N92="Cancelled",0,IF(K92<>"",MAX(0,K92-J92),IF(N92="Delayed",MAX(0,'Daily MIS Report'!$B$4-J92),0))) -> 1
A93: PO0089 | B93: 46247 | C93: SUP005 | D93: =VLOOKUP(C93,'Supplier Database'!$A$5:$K$29,2,FALSE()) -> Ever Logistics | E93: PRD077 | F93: =VLOOKUP(E93,'Product Master'!$A$5:$K$104,2,FALSE()) -> Everyday Industrial Item 077 | G93: 212 | H93: 2557.57 | I93: =G93*H93 -> 542204.84 | J93: 46250 | K93: 46249 | L93: 212 | M93: =MAX(0,G93-L93) -> 0 | N93: Received | O93: =IF(N93="Cancelled",0,IF(K93<>"",MAX(0,K93-J93),IF(N93="Delayed",MAX(0,'Daily MIS Report'!$B$4-J93),0))) -> 0
A94: PO0090 | B94: 46300 | C94: SUP015 | D94: =VLOOKUP(C94,'Supplier Database'!$A$5:$K$29,2,FALSE()) -> Orbit Supplies | E94: PRD006 | F94: =VLOOKUP(E94,'Product Master'!$A$5:$K$104,2,FALSE()) -> Pro Packaging Item 006 | G94: 230 | H94: 1399.48 | I94: =G94*H94 -> 321880.4 | J94: 46314 | L94: 0 | M94: =MAX(0,G94-L94) -> 230 | N94: Pending | O94: =IF(N94="Cancelled",0,IF(K94<>"",MAX(0,K94-J94),IF(N94="Delayed",MAX(0,'Daily MIS Report'!$B$4-J94),0))) -> 0
A95: PO0091 | B95: 46158 | C95: SUP020 | D95: =VLOOKUP(C95,'Supplier Database'!$A$5:$K$29,2,FALSE()) -> Trident Wholesale | E95: PRD037 | F95: =VLOOKUP(E95,'Product Master'!$A$5:$K$104,2,FALSE()) -> Pro Industrial Item 037 | G95: 405 | H95: 4806.27 | I95: =G95*H95 -> 1946539.4 | J95: 46170 | K95: 46170 | L95: 405 | M95: =MAX(0,G95-L95) -> 0 | N95: Received | O95: =IF(N95="Cancelled",0,IF(K95<>"",MAX(0,K95-J95),IF(N95="Delayed",MAX(0,'Daily MIS Report'!$B$4-J95),0))) -> 0
A96: PO0092 | B96: 46053 | C96: SUP010 | D96: =VLOOKUP(C96,'Supplier Database'!$A$5:$K$29,2,FALSE()) -> Jupiter Industries | E96: PRD061 | F96: =VLOOKUP(E96,'Product Master'!$A$5:$K$104,2,FALSE()) -> Pro Industrial Item 061 | G96: 482 | H96: 4080.12 | I96: =G96*H96 -> 1966617.8 | J96: 46067 | K96: 46071 | L96: 482 | M96: =MAX(0,G96-L96) -> 0 | N96: Received | O96: =IF(N96="Cancelled",0,IF(K96<>"",MAX(0,K96-J96),IF(N96="Delayed",MAX(0,'Daily MIS Report'!$B$4-J96),0))) -> 4
A97: PO0093 | B97: 46167 | C97: SUP025 | D97: =VLOOKUP(C97,'Supplier Database'!$A$5:$K$29,2,FALSE()) -> Zenith Trading Co. | E97: PRD037 | F97: =VLOOKUP(E97,'Product Master'!$A$5:$K$104,2,FALSE()) -> Pro Industrial Item 037 | G97: 418 | H97: 4600.92 | I97: =G97*H97 -> 1923184.6 | J97: 46172 | K97: 46171 | L97: 418 | M97: =MAX(0,G97-L97) -> 0 | N97: Received | O97: =IF(N97="Cancelled",0,IF(K97<>"",MAX(0,K97-J97),IF(N97="Delayed",MAX(0,'Daily MIS Report'!$B$4-J97),0))) -> 0
A98: PO0094 | B98: 46033 | C98: SUP020 | D98: =VLOOKUP(C98,'Supplier Database'!$A$5:$K$29,2,FALSE()) -> Trident Wholesale | E98: PRD018 | F98: =VLOOKUP(E98,'Product Master'!$A$5:$K$104,2,FALSE()) -> Smart Home Item 018 | G98: 466 | H98: 3365.22 | I98: =G98*H98 -> 1568192.5 | J98: 46045 | K98: 46050 | L98: 191 | M98: =MAX(0,G98-L98) -> 275 | N98: Partially Received | O98: =IF(N98="Cancelled",0,IF(K98<>"",MAX(0,K98-J98),IF(N98="Delayed",MAX(0,'Daily MIS Report'!$B$4-J98),0))) -> 5
A99: PO0095 | B99: 46214 | C99: SUP004 | D99: =VLOOKUP(C99,'Supplier Database'!$A$5:$K$29,2,FALSE()) -> Delta Trading Co. | E99: PRD092 | F99: =VLOOKUP(E99,'Product Master'!$A$5:$K$104,2,FALSE()) -> Essential Personal Item 092 | G99: 453 | H99: 6733.9 | I99: =G99*H99 -> 3050456.7 | J99: 46224 | K99: 46222 | L99: 453 | M99: =MAX(0,G99-L99) -> 0 | N99: Received | O99: =IF(N99="Cancelled",0,IF(K99<>"",MAX(0,K99-J99),IF(N99="Delayed",MAX(0,'Daily MIS Report'!$B$4-J99),0))) -> 0
A100: PO0096 | B100: 46302 | C100: SUP009 | D100: =VLOOKUP(C100,'Supplier Database'!$A$5:$K$29,2,FALSE()) -> Indus Distributors | E100: PRD058 | F100: =VLOOKUP(E100,'Product Master'!$A$5:$K$104,2,FALSE()) -> Pro Home Item 058 | G100: 483 | H100: 3531.52 | I100: =G100*H100 -> 1705724.2 | J100: 46308 | L100: 1 | M100: =MAX(0,G100-L100) -> 482 | N100: Delayed | O100: =IF(N100="Cancelled",0,IF(K100<>"",MAX(0,K100-J100),IF(N100="Delayed",MAX(0,'Daily MIS Report'!$B$4-J100),0))) -> 6
A101: PO0097 | B101: 46044 | C101: SUP015 | D101: =VLOOKUP(C101,'Supplier Database'!$A$5:$K$29,2,FALSE()) -> Orbit Supplies | E101: PRD045 | F101: =VLOOKUP(E101,'Product Master'!$A$5:$K$104,2,FALSE()) -> Essential Industrial Item 045 | G101: 496 | H101: 6288.06 | I101: =G101*H101 -> 3118877.8 | J101: 46058 | K101: 46065 | L101: 496 | M101: =MAX(0,G101-L101) -> 0 | N101: Received | O101: =IF(N101="Cancelled",0,IF(K101<>"",MAX(0,K101-J101),IF(N101="Delayed",MAX(0,'Daily MIS Report'!$B$4-J101),0))) -> 7
...

Sheet Daily MIS Report
A1: DAILY OPERATIONAL MIS REPORT
A2: Select any reporting date in cell B4 (yellow input cell) to automatically calculate daily order, sales, procurement, and delivery metrics.
A4: Reporting Date | B4: 46314
A6: Selected Date Operational KPI Summary | E6: Trailing 7-Day Daily Operational Log (Relative to B4)
A7: Daily Operational Metric | B7: Calculated Value | C7: Metric Definition / Basis | E7: Date | F7: Orders Received | G7: Orders Dispatched | H7: Daily Sales (₹)
A8: Orders Received | B8: =COUNTIF('Order Tracking'!$B$5:$B$604,$B$4) -> 6 | C8: Orders placed on selected Report Date | E8: =$B$4-6 -> 46308 | F8: =COUNTIF('Order Tracking'!$B$5:$B$604,E8) -> 1 | G8: =COUNTIF('Order Tracking'!$N$5:$N$604,E8) -> 0 | H8: =SUMIFS('Order Tracking'!$L$5:$L$604,'Order Tracking'!$B$5:$B$604,E8) -> 214616.8
A9: Orders Processed | B9: =COUNTIFS('Order Tracking'!$B$5:$B$604,$B$4,'Order Tracking'!$M$5:$M$604,"Processing") -> 2 | C9: Orders from Report Date in Processing status | E9: =$B$4-5 -> 46309 | F9: =COUNTIF('Order Tracking'!$B$5:$B$604,E9) -> 1 | G9: =COUNTIF('Order Tracking'!$N$5:$N$604,E9) -> 1 | H9: =SUMIFS('Order Tracking'!$L$5:$L$604,'Order Tracking'!$B$5:$B$604,E9) -> 160479.25
A10: Orders Dispatched | B10: =COUNTIF('Order Tracking'!$N$5:$N$604,$B$4) -> 4 | C10: Orders dispatched on selected Report Date | E10: =$B$4-4 -> 46310 | F10: =COUNTIF('Order Tracking'!$B$5:$B$604,E10) -> 3 | G10: =COUNTIF('Order Tracking'!$N$5:$N$604,E10) -> 1 | H10: =SUMIFS('Order Tracking'!$L$5:$L$604,'Order Tracking'!$B$5:$B$604,E10) -> 138979.19
A11: Orders Delivered | B11: =COUNTIFS('Order Tracking'!$P$5:$P$604,$B$4,'Order Tracking'!$M$5:$M$604,"Delivered") -> 3 | C11: Orders delivered on selected Report Date | E11: =$B$4-3 -> 46311 | F11: =COUNTIF('Order Tracking'!$B$5:$B$604,E11) -> 2 | G11: =COUNTIF('Order Tracking'!$N$5:$N$604,E11) -> 3 | H11: =SUMIFS('Order Tracking'!$L$5:$L$604,'Order Tracking'!$B$5:$B$604,E11) -> 141701.78
A12: Pending Orders | B12: =COUNTIFS('Order Tracking'!$B$5:$B$604,$B$4,'Order Tracking'!$M$5:$M$604,"Pending") -> 2 | C12: Orders from Report Date in Pending status | E12: =$B$4-2 -> 46312 | F12: =COUNTIF('Order Tracking'!$B$5:$B$604,E12) -> 1 | G12: =COUNTIF('Order Tracking'!$N$5:$N$604,E12) -> 1 | H12: =SUMIFS('Order Tracking'!$L$5:$L$604,'Order Tracking'!$B$5:$B$604,E12) -> 79573.92
A13: Delayed Orders | B13: =COUNTIFS('Order Tracking'!$B$5:$B$604,$B$4,'Order Tracking'!$R$5:$R$604,">0")+COUNTIFS('Order Tracking'!$P$5:$P$604,$B$4,'Order Tracking'!$R$5:$R$604,">0") -> 3 | C13: Orders placed/delivered with Delay Days > 0 | E13: =$B$4-1 -> 46313 | F13: =COUNTIF('Order Tracking'!$B$5:$B$604,E13) -> 1 | G13: =COUNTIF('Order Tracking'!$N$5:$N$604,E13) -> 1 | H13: =SUMIFS('Order Tracking'!$L$5:$L$604,'Order Tracking'!$B$5:$B$604,E13) -> 227112.82
A14: Total Sales | B14: =SUMIFS('Order Tracking'!$L$5:$L$604,'Order Tracking'!$B$5:$B$604,$B$4) -> 616977.88 | C14: Gross sales of orders placed on Report Date | E14: =$B$4 -> 46314 | F14: =COUNTIF('Order Tracking'!$B$5:$B$604,E14) -> 6 | G14: =COUNTIF('Order Tracking'!$N$5:$N$604,E14) -> 4 | H14: =SUMIFS('Order Tracking'!$L$5:$L$604,'Order Tracking'!$B$5:$B$604,E14) -> 616977.88
A15: Purchase Value | B15: =SUMIFS('Purchase Management'!$I$5:$I$224,'Purchase Management'!$B$5:$B$224,$B$4) -> 488527.5 | C15: Total value of POs issued on Report Date
A16: Inventory Value | B16: =SUM('Inventory Management'!$O$5:$O$104) -> 98642688 | C16: Current warehouse stock valuation (100 SKUs)
